Workbook

Sheet 🎯 Command Center
A1: 🎯 COMMAND CENTER — Smart Daily Plan · Dependency Aware · Month-Locked · Overdue Enforced
A2: Enter available hours → auto-plan fills. Hard prereqs block topics. Overdue topics jump to top. Last-2-wk-of-month: overdue locked + force-inserted. Swap pool = cur+next week (default) or same month (Settings).
A4: ⚙️ SETTINGS PANEL — Yellow cells = editable. Toggle column = ON/OFF instantly.
B5: Setting | C5: Value | E5: Toggle | F5: Description
B6: Max swaps per WEEK | C6: 3 | E6: ✅ ON | F6: Resets Monday. Counter shown in today's bar.
B7: Max swaps per MONTH | C7: 10 | E7: ✅ ON | F7: Counted from 1st to last day of month.
B8: Max swaps per TOPIC (lifetime) | C8: 3 | E8: ✅ ON | F8: Each topic can be deferred this many times total.
B9: Overdue window (days) | C9: 14 | E9: ✅ ON | F9: Topic missed > this many days = ⏰ OVERDUE.
B10: Max topics in today's plan | C10: 10 | E10: ✅ ON | F10: Plan shows up to N topics fitting your hours.
B11: Force-insert overdue (last 2 wks of month) | C11: 2 | E11: ✅ ON | F11: Max overdue topics force-added even if over budget.
B12: Weekday hours budget | C12: 1.5 | E12: ✅ ON | F12: Default Mon-Fri. Override cell L24 daily.
B13: Weekend hours budget | C13: 3.5 | E13: ✅ ON | F13: Default Sat-Sun.
B14: Swap pool mode | C14: Option 2 — Current+Next Week | E14: — | F14: Option 1 = Same month only | Option 2 = Current week + next week (default).
B15: Hard prereq enforcement | C15: — | E15: ✅ ON | F15: Topics with unfinished prereqs hidden from plan.
B16: Lock swaps in last 2 wks of month | C16: — | E16: ✅ ON | F16: Overdue topics locked (🔒). Non-overdue still swappable within same month.
B17: Auto-status from Daily Log | C17: — | E17: ✅ ON | F17: Pool Final Status reads from Daily Log automatically.
A18: 📊 FEASIBILITY CHECK — Avg pace × remaining weeks vs topics left this month.
A19: ="Avg: "&ROUND(A450,1)&"h/wk" -> Avg: 10.5h/wk | C19: ="Avail: "&ROUND(A454,1)&"h" -> Avail: 31.5h | E19: ="Overdue: "&ROUND(A455,1)&"h" -> Overdue: 0h | G19: ="Pend: "&ROUND(A456,1)&"h" -> Pend: 0h | I19: ="Need: "&ROUND(A457,1)&"h" -> Need: 0h | K19: =IF(A458>=0,"Gap:+"&ROUND(A458,1)&"h ✅","Gap:"&ROUND(A458,1)&"h ❌") -> Gap:+31.5h ✅ | M19: =IF(A460=0,"🟢 Open",IF(A460=1,"🟡 Overdue locked","🔴 All locked")) -> 🟢 Open | O19: =IF(NOT(A452),"✅ Not in last 2 weeks — swaps open.",IF(A453,"🔴 LAST WEEK — full lock.",IF(A459,"🟡 Feasible — "&ROUND(A458,1)&"h buffer. Overdue locked.","🔴 NOT feasible — "&ROUND(ABS(A458),1)&"h short. All locked."))) -> ✅ Not in last 2 weeks — swaps open.
A22: 📅 TODAY'S PLAN
B24: Today | C24: =TEXT(TODAY(),"DD-MMM-YYYY (DDDD)") -> 30-Mar-2026 (Monday) | H24: =IFERROR("W"&INT((TODAY()-DATE(2026,3,30))/7)+1&" / 39","") -> W1 / 39 | J24: =IFERROR("M"&INT((INT((TODAY()-DATE(2026,3,30))/7))/4+1),"") -> M1 | L24: Avail hrs → | M24: =IF(WEEKDAY(TODAY(),2)>=6,$C$13,$C$12) -> 1.5 | O24: ← override | Q24: =IFERROR(COUNTIFS('📋 Swap History'!$C$4:$C$200,">="&(TODAY()-WEEKDAY(TODAY(),2)+1),'📋 Swap History'!$C$4:$C$200,"<="&(TODAY()-WEEKDAY(TODAY(),2)+7)),0) -> 0 | R24: =IFERROR("/ "&$C$6,"/ ??") -> / 3 | T24: =IF(E6="❌ OFF","(limit off)",IF(Q24>=$C$6,"🔒 Week limit hit","✅ "&($C$6-Q24)&" left")) -> ✅ 3 left
A25: 🚨 MUST DO = force-inserted overdue (last 2 wks of month) | ⏰ OVERDUE = missed > 14 days | 🔒 LOCKED = can't swap | ⬜ = prereq not done (hidden)
B26: # | C26: Badge | E26: Priority | G26: Topic (prereq-cleared, due today) | L26: Phase | N26: Min | O26: Avg | P26: Max | Q26: Cum hrs | R26: Hrs left | S26: Status | T26: Swap? 🔄=yes | U26: Resource
B27: =IF(AND(U401,1<=$C$10),1,"") | C27: =IF(AND(U401,1<=$C$10),IF(P401,"🚨 MUST DO",IF(O401,"⏰ OVERDUE","")),"—") -> — | E27: =IF(AND(U401,1<=$C$10),G401,"—") -> — | G27: =IF(AND(U401,1<=$C$10),B401,"— (not enough time / prereq blocked)") -> — (not enough time / prereq blocked) | L27: =IF(AND(U401,1<=$C$10),C401,"—") -> — | N27: =IF(AND(U401,1<=$C$10),D401,"—") -> — | O27: =IF(AND(U401,1<=$C$10),E401,"—") -> — | P27: =IF(AND(U401,1<=$C$10),F401,"—") -> — | Q27: =IF(AND(U401,1<=$C$10),T401,"—") -> — | R27: =IF(AND(U401,1<=$C$10),$M$24-T401,"—") -> — | S27: =IF(AND(U401,1<=$C$10),H401,"—") -> — | T27: — Keep | U27: =IFERROR(IF(AND(U401,1<=$C$10),INDEX('📆 Daily Schedule'!$Q$5:$Q$400,MATCH(B401,'📆 Daily Schedule'!$F$5:$F$400,0)),"—"),"—") -> —
B28: =IF(AND(U402,2<=$C$10),2,"") | C28: =IF(AND(U402,2<=$C$10),IF(P402,"🚨 MUST DO",IF(O402,"⏰ OVERDUE","")),"—") -> — | E28: =IF(AND(U402,2<=$C$10),G402,"—") -> — | G28: =IF(AND(U402,2<=$C$10),B402,"— (not enough time / prereq blocked)") -> — (not enough time / prereq blocked) | L28: =IF(AND(U402,2<=$C$10),C402,"—") -> — | N28: =IF(AND(U402,2<=$C$10),D402,"—") -> — | O28: =IF(AND(U402,2<=$C$10),E402,"—") -> — | P28: =IF(AND(U402,2<=$C$10),F402,"—") -> — | Q28: =IF(AND(U402,2<=$C$10),T402,"—") -> — | R28: =IF(AND(U402,2<=$C$10),$M$24-T402,"—") -> — | S28: =IF(AND(U402,2<=$C$10),H402,"—") -> — | T28: — Keep | U28: =IFERROR(IF(AND(U402,2<=$C$10),INDEX('📆 Daily Schedule'!$Q$5:$Q$400,MATCH(B402,'📆 Daily Schedule'!$F$5:$F$400,0)),"—"),"—") -> —
B29: =IF(AND(U403,3<=$C$10),3,"") | C29: =IF(AND(U403,3<=$C$10),IF(P403,"🚨 MUST DO",IF(O403,"⏰ OVERDUE","")),"—") -> — | E29: =IF(AND(U403,3<=$C$10),G403,"—") -> — | G29: =IF(AND(U403,3<=$C$10),B403,"— (not enough time / prereq blocked)") -> — (not enough time / prereq blocked) | L29: =IF(AND(U403,3<=$C$10),C403,"—") -> — | N29: =IF(AND(U403,3<=$C$10),D403,"—") -> — | O29: =IF(AND(U403,3<=$C$10),E403,"—") -> — | P29: =IF(AND(U403,3<=$C$10),F403,"—") -> — | Q29: =IF(AND(U403,3<=$C$10),T403,"—") -> — | R29: =IF(AND(U403,3<=$C$10),$M$24-T403,"—") -> — | S29: =IF(AND(U403,3<=$C$10),H403,"—") -> — | T29: — Keep | U29: =IFERROR(IF(AND(U403,3<=$C$10),INDEX('📆 Daily Schedule'!$Q$5:$Q$400,MATCH(B403,'📆 Daily Schedule'!$F$5:$F$400,0)),"—"),"—") -> —
B30: =IF(AND(U404,4<=$C$10),4,"") | C30: =IF(AND(U404,4<=$C$10),IF(P404,"🚨 MUST DO",IF(O404,"⏰ OVERDUE","")),"—") -> — | E30: =IF(AND(U404,4<=$C$10),G404,"—") -> — | G30: =IF(AND(U404,4<=$C$10),B404,"— (not enough time / prereq blocked)") -> — (not enough time / prereq blocked) | L30: =IF(AND(U404,4<=$C$10),C404,"—") -> — | N30: =IF(AND(U404,4<=$C$10),D404,"—") -> — | O30: =IF(AND(U404,4<=$C$10),E404,"—") -> — | P30: =IF(AND(U404,4<=$C$10),F404,"—") -> — | Q30: =IF(AND(U404,4<=$C$10),T404,"—") -> — | R30: =IF(AND(U404,4<=$C$10),$M$24-T404,"—") -> — | S30: =IF(AND(U404,4<=$C$10),H404,"—") -> — | T30: — Keep | U30: =IFERROR(IF(AND(U404,4<=$C$10),INDEX('📆 Daily Schedule'!$Q$5:$Q$400,MATCH(B404,'📆 Daily Schedule'!$F$5:$F$400,0)),"—"),"—") -> —
B31: =IF(AND(U405,5<=$C$10),5,"") | C31: =IF(AND(U405,5<=$C$10),IF(P405,"🚨 MUST DO",IF(O405,"⏰ OVERDUE","")),"—") -> — | E31: =IF(AND(U405,5<=$C$10),G405,"—") -> — | G31: =IF(AND(U405,5<=$C$10),B405,"— (not enough time / prereq blocked)") -> — (not enough time / prereq blocked) | L31: =IF(AND(U405,5<=$C$10),C405,"—") -> — | N31: =IF(AND(U405,5<=$C$10),D405,"—") -> — | O31: =IF(AND(U405,5<=$C$10),E405,"—") -> — | P31: =IF(AND(U405,5<=$C$10),F405,"—") -> — | Q31: =IF(AND(U405,5<=$C$10),T405,"—") -> — | R31: =IF(AND(U405,5<=$C$10),$M$24-T405,"—") -> — | S31: =IF(AND(U405,5<=$C$10),H405,"—") -> — | T31: — Keep | U31: =IFERROR(IF(AND(U405,5<=$C$10),INDEX('📆 Daily Schedule'!$Q$5:$Q$400,MATCH(B405,'📆 Daily Schedule'!$F$5:$F$400,0)),"—"),"—") -> —
B32: =IF(AND(U406,6<=$C$10),6,"") | C32: =IF(AND(U406,6<=$C$10),IF(P406,"🚨 MUST DO",IF(O406,"⏰ OVERDUE","")),"—") -> — | E32: =IF(AND(U406,6<=$C$10),G406,"—") -> — | G32: =IF(AND(U406,6<=$C$10),B406,"— (not enough time / prereq blocked)") -> — (not enough time / prereq blocked) | L32: =IF(AND(U406,6<=$C$10),C406,"—") -> — | N32: =IF(AND(U406,6<=$C$10),D406,"—") -> — | O32: =IF(AND(U406,6<=$C$10),E406,"—") -> — | P32: =IF(AND(U406,6<=$C$10),F406,"—") -> — | Q32: =IF(AND(U406,6<=$C$10),T406,"—") -> — | R32: =IF(AND(U406,6<=$C$10),$M$24-T406,"—") -> — | S32: =IF(AND(U406,6<=$C$10),H406,"—") -> — | T32: — Keep | U32: =IFERROR(IF(AND(U406,6<=$C$10),INDEX('📆 Daily Schedule'!$Q$5:$Q$400,MATCH(B406,'📆 Daily Schedule'!$F$5:$F$400,0)),"—"),"—") -> —
B33: =IF(AND(U407,7<=$C$10),7,"") | C33: =IF(AND(U407,7<=$C$10),IF(P407,"🚨 MUST DO",IF(O407,"⏰ OVERDUE","")),"—") -> — | E33: =IF(AND(U407,7<=$C$10),G407,"—") -> — | G33: =IF(AND(U407,7<=$C$10),B407,"— (not enough time / prereq blocked)") -> — (not enough time / prereq blocked) | L33: =IF(AND(U407,7<=$C$10),C407,"—") -> — | N33: =IF(AND(U407,7<=$C$10),D407,"—") -> — | O33: =IF(AND(U407,7<=$C$10),E407,"—") -> — | P33: =IF(AND(U407,7<=$C$10),F407,"—") -> — | Q33: =IF(AND(U407,7<=$C$10),T407,"—") -> — | R33: =IF(AND(U407,7<=$C$10),$M$24-T407,"—") -> — | S33: =IF(AND(U407,7<=$C$10),H407,"—") -> — | T33: — Keep | U33: =IFERROR(IF(AND(U407,7<=$C$10),INDEX('📆 Daily Schedule'!$Q$5:$Q$400,MATCH(B407,'📆 Daily Schedule'!$F$5:$F$400,0)),"—"),"—") -> —
B34: =IF(AND(U408,8<=$C$10),8,"") | C34: =IF(AND(U408,8<=$C$10),IF(P408,"🚨 MUST DO",IF(O408,"⏰ OVERDUE","")),"—") -> — | E34: =IF(AND(U408,8<=$C$10),G408,"—") -> — | G34: =IF(AND(U408,8<=$C$10),B408,"— (not enough time / prereq blocked)") -> — (not enough time / prereq blocked) | L34: =IF(AND(U408,8<=$C$10),C408,"—") -> — | N34: =IF(AND(U408,8<=$C$10),D408,"—") -> — | O34: =IF(AND(U408,8<=$C$10),E408,"—") -> — | P34: =IF(AND(U408,8<=$C$10),F408,"—") -> — | Q34: =IF(AND(U408,8<=$C$10),T408,"—") -> — | R34: =IF(AND(U408,8<=$C$10),$M$24-T408,"—") -> — | S34: =IF(AND(U408,8<=$C$10),H408,"—") -> — | T34: — Keep | U34: =IFERROR(IF(AND(U408,8<=$C$10),INDEX('📆 Daily Schedule'!$Q$5:$Q$400,MATCH(B408,'📆 Daily Schedule'!$F$5:$F$400,0)),"—"),"—") -> —
B35: =IF(AND(U409,9<=$C$10),9,"") | C35: =IF(AND(U409,9<=$C$10),IF(P409,"🚨 MUST DO",IF(O409,"⏰ OVERDUE","")),"—") -> — | E35: =IF(AND(U409,9<=$C$10),G409,"—") -> — | G35: =IF(AND(U409,9<=$C$10),B409,"— (not enough time / prereq blocked)") -> — (not enough time / prereq blocked) | L35: =IF(AND(U409,9<=$C$10),C409,"—") -> — | N35: =IF(AND(U409,9<=$C$10),D409,"—") -> — | O35: =IF(AND(U409,9<=$C$10),E409,"—") -> — | P35: =IF(AND(U409,9<=$C$10),F409,"—") -> — | Q35: =IF(AND(U409,9<=$C$10),T409,"—") -> — | R35: =IF(AND(U409,9<=$C$10),$M$24-T409,"—") -> — | S35: =IF(AND(U409,9<=$C$10),H409,"—") -> — | T35: — Keep | U35: =IFERROR(IF(AND(U409,9<=$C$10),INDEX('📆 Daily Schedule'!$Q$5:$Q$400,MATCH(B409,'📆 Daily Schedule'!$F$5:$F$400,0)),"—"),"—") -> —
B36: =IF(AND(U410,10<=$C$10),10,"") | C36: =IF(AND(U410,10<=$C$10),IF(P410,"🚨 MUST DO",IF(O410,"⏰ OVERDUE","")),"—") -> — | E36: =IF(AND(U410,10<=$C$10),G410,"—") -> — | G36: =IF(AND(U410,10<=$C$10),B410,"— (not enough time / prereq blocked)") -> — (not enough time / prereq blocked) | L36: =IF(AND(U410,10<=$C$10),C410,"—") -> — | N36: =IF(AND(U410,10<=$C$10),D410,"—") -> — | O36: =IF(AND(U410,10<=$C$10),E410,"—") -> — | P36: =IF(AND(U410,10<=$C$10),F410,"—") -> — | Q36: =IF(AND(U410,10<=$C$10),T410,"—") -> — | R36: =IF(AND(U410,10<=$C$10),$M$24-T410,"—") -> — | S36: =IF(AND(U410,10<=$C$10),H410,"—") -> — | T36: — Keep | U36: =IFERROR(IF(AND(U410,10<=$C$10),INDEX('📆 Daily Schedule'!$Q$5:$Q$400,MATCH(B410,'📆 Daily Schedule'!$F$5:$F$400,0)),"—"),"—") -> —
B37: =IF(AND(U411,11<=$C$10),11,"") | C37: =IF(AND(U411,11<=$C$10),IF(P411,"🚨 MUST DO",IF(O411,"⏰ OVERDUE","")),"—") -> — | E37: =IF(AND(U411,11<=$C$10),G411,"—") -> — | G37: =IF(AND(U411,11<=$C$10),B411,"— (not enough time / prereq blocked)") -> — (not enough time / prereq blocked) | L37: =IF(AND(U411,11<=$C$10),C411,"—") -> — | N37: =IF(AND(U411,11<=$C$10),D411,"—") -> — | O37: =IF(AND(U411,11<=$C$10),E411,"—") -> — | P37: =IF(AND(U411,11<=$C$10),F411,"—") -> — | Q37: =IF(AND(U411,11<=$C$10),T411,"—") -> — | R37: =IF(AND(U411,11<=$C$10),$M$24-T411,"—") -> — | S37: =IF(AND(U411,11<=$C$10),H411,"—") -> — | T37: — Keep | U37: =IFERROR(IF(AND(U411,11<=$C$10),INDEX('📆 Daily Schedule'!$Q$5:$Q$400,MATCH(B411,'📆 Daily Schedule'!$F$5:$F$400,0)),"—"),"—") -> —
B38: =IF(AND(U412,12<=$C$10),12,"") | C38: =IF(AND(U412,12<=$C$10),IF(P412,"🚨 MUST DO",IF(O412,"⏰ OVERDUE","")),"—") -> — | E38: =IF(AND(U412,12<=$C$10),G412,"—") -> — | G38: =IF(AND(U412,12<=$C$10),B412,"— (not enough time / prereq blocked)") -> — (not enough time / prereq blocked) | L38: =IF(AND(U412,12<=$C$10),C412,"—") -> — | N38: =IF(AND(U412,12<=$C$10),D412,"—") -> — | O38: =IF(AND(U412,12<=$C$10),E412,"—") -> — | P38: =IF(AND(U412,12<=$C$10),F412,"—") -> — | Q38: =IF(AND(U412,12<=$C$10),T412,"—") -> — | R38: =IF(AND(U412,12<=$C$10),$M$24-T412,"—") -> — | S38: =IF(AND(U412,12<=$C$10),H412,"—") -> — | T38: — Keep | U38: =IFERROR(IF(AND(U412,12<=$C$10),INDEX('📆 Daily Schedule'!$Q$5:$Q$400,MATCH(B412,'📆 Daily Schedule'!$F$5:$F$400,0)),"—"),"—") -> —
B39: =IF(AND(U413,13<=$C$10),13,"") | C39: =IF(AND(U413,13<=$C$10),IF(P413,"🚨 MUST DO",IF(O413,"⏰ OVERDUE","")),"—") -> — | E39: =IF(AND(U413,13<=$C$10),G413,"—") -> — | G39: =IF(AND(U413,13<=$C$10),B413,"— (not enough time / prereq blocked)") -> — (not enough time / prereq blocked) | L39: =IF(AND(U413,13<=$C$10),C413,"—") -> — | N39: =IF(AND(U413,13<=$C$10),D413,"—") -> — | O39: =IF(AND(U413,13<=$C$10),E413,"—") -> — | P39: =IF(AND(U413,13<=$C$10),F413,"—") -> — | Q39: =IF(AND(U413,13<=$C$10),T413,"—") -> — | R39: =IF(AND(U413,13<=$C$10),$M$24-T413,"—") -> — | S39: =IF(AND(U413,13<=$C$10),H413,"—") -> — | T39: — Keep | U39: =IFERROR(IF(AND(U413,13<=$C$10),INDEX('📆 Daily Schedule'!$Q$5:$Q$400,MATCH(B413,'📆 Daily Schedule'!$F$5:$F$400,0)),"—"),"—") -> —
B40: =IF(AND(U414,14<=$C$10),14,"") | C40: =IF(AND(U414,14<=$C$10),IF(P414,"🚨 MUST DO",IF(O414,"⏰ OVERDUE","")),"—") -> — | E40: =IF(AND(U414,14<=$C$10),G414,"—") -> — | G40: =IF(AND(U414,14<=$C$10),B414,"— (not enough time / prereq blocked)") -> — (not enough time / prereq blocked) | L40: =IF(AND(U414,14<=$C$10),C414,"—") -> — | N40: =IF(AND(U414,14<=$C$10),D414,"—") -> — | O40: =IF(AND(U414,14<=$C$10),E414,"—") -> — | P40: =IF(AND(U414,14<=$C$10),F414,"—") -> — | Q40: =IF(AND(U414,14<=$C$10),T414,"—") -> — | R40: =IF(AND(U414,14<=$C$10),$M$24-T414,"—") -> — | S40: =IF(AND(U414,14<=$C$10),H414,"—") -> — | T40: — Keep | U40: =IFERROR(IF(AND(U414,14<=$C$10),INDEX('📆 Daily Schedule'!$Q$5:$Q$400,MATCH(B414,'📆 Daily Schedule'!$F$5:$F$400,0)),"—"),"—") -> —
B41: =IF(AND(U415,15<=$C$10),15,"") | C41: =IF(AND(U415,15<=$C$10),IF(P415,"🚨 MUST DO",IF(O415,"⏰ OVERDUE","")),"—") -> — | E41: =IF(AND(U415,15<=$C$10),G415,"—") -> — | G41: =IF(AND(U415,15<=$C$10),B415,"— (not enough time / prereq blocked)") -> — (not enough time / prereq blocked) | L41: =IF(AND(U415,15<=$C$10),C415,"—") -> — | N41: =IF(AND(U415,15<=$C$10),D415,"—") -> — | O41: =IF(AND(U415,15<=$C$10),E415,"—") -> — | P41: =IF(AND(U415,15<=$C$10),F415,"—") -> — | Q41: =IF(AND(U415,15<=$C$10),T415,"—") -> — | R41: =IF(AND(U415,15<=$C$10),$M$24-T415,"—") -> — | S41: =IF(AND(U415,15<=$C$10),H415,"—") -> — | T41: — Keep | U41: =IFERROR(IF(AND(U415,15<=$C$10),INDEX('📆 Daily Schedule'!$Q$5:$Q$400,MATCH(B415,'📆 Daily Schedule'!$F$5:$F$400,0)),"—"),"—") -> —
B42: =IF(AND(U416,16<=$C$10),16,"") | C42: =IF(AND(U416,16<=$C$10),IF(P416,"🚨 MUST DO",IF(O416,"⏰ OVERDUE","")),"—") -> — | E42: =IF(AND(U416,16<=$C$10),G416,"—") -> — | G42: =IF(AND(U416,16<=$C$10),B416,"— (not enough time / prereq blocked)") -> — (not enough time / prereq blocked) | L42: =IF(AND(U416,16<=$C$10),C416,"—") -> — | N42: =IF(AND(U416,16<=$C$10),D416,"—") -> — | O42: =IF(AND(U416,16<=$C$10),E416,"—") -> — | P42: =IF(AND(U416,16<=$C$10),F416,"—") -> — | Q42: =IF(AND(U416,16<=$C$10),T416,"—") -> — | R42: =IF(AND(U416,16<=$C$10),$M$24-T416,"—") -> — | S42: =IF(AND(U416,16<=$C$10),H416,"—") -> — | T42: — Keep | U42: =IFERROR(IF(AND(U416,16<=$C$10),INDEX('📆 Daily Schedule'!$Q$5:$Q$400,MATCH(B416,'📆 Daily Schedule'!$F$5:$F$400,0)),"—"),"—") -> —
B43: =IF(AND(U417,17<=$C$10),17,"") | C43: =IF(AND(U417,17<=$C$10),IF(P417,"🚨 MUST DO",IF(O417,"⏰ OVERDUE","")),"—") -> — | E43: =IF(AND(U417,17<=$C$10),G417,"—") -> — | G43: =IF(AND(U417,17<=$C$10),B417,"— (not enough time / prereq blocked)") -> — (not enough time / prereq blocked) | L43: =IF(AND(U417,17<=$C$10),C417,"—") -> — | N43: =IF(AND(U417,17<=$C$10),D417,"—") -> — | O43: =IF(AND(U417,17<=$C$10),E417,"—") -> — | P43: =IF(AND(U417,17<=$C$10),F417,"—") -> — | Q43: =IF(AND(U417,17<=$C$10),T417,"—") -> — | R43: =IF(AND(U417,17<=$C$10),$M$24-T417,"—") -> — | S43: =IF(AND(U417,17<=$C$10),H417,"—") -> — | T43: — Keep | U43: =IFERROR(IF(AND(U417,17<=$C$10),INDEX('📆 Daily Schedule'!$Q$5:$Q$400,MATCH(B417,'📆 Daily Schedule'!$F$5:$F$400,0)),"—"),"—") -> —
B44: =IF(AND(U418,18<=$C$10),18,"") | C44: =IF(AND(U418,18<=$C$10),IF(P418,"🚨 MUST DO",IF(O418,"⏰ OVERDUE","")),"—") -> — | E44: =IF(AND(U418,18<=$C$10),G418,"—") -> — | G44: =IF(AND(U418,18<=$C$10),B418,"— (not enough time / prereq blocked)") -> — (not enough time / prereq blocked) | L44: =IF(AND(U418,18<=$C$10),C418,"—") -> — | N44: =IF(AND(U418,18<=$C$10),D418,"—") -> — | O44: =IF(AND(U418,18<=$C$10),E418,"—") -> — | P44: =IF(AND(U418,18<=$C$10),F418,"—") -> — | Q44: =IF(AND(U418,18<=$C$10),T418,"—") -> — | R44: =IF(AND(U418,18<=$C$10),$M$24-T418,"—") -> — | S44: =IF(AND(U418,18<=$C$10),H418,"—") -> — | T44: — Keep | U44: =IFERROR(IF(AND(U418,18<=$C$10),INDEX('📆 Daily Schedule'!$Q$5:$Q$400,MATCH(B418,'📆 Daily Schedule'!$F$5:$F$400,0)),"—"),"—") -> —
B45: =IF(AND(U419,19<=$C$10),19,"") | C45: =IF(AND(U419,19<=$C$10),IF(P419,"🚨 MUST DO",IF(O419,"⏰ OVERDUE","")),"—") -> — | E45: =IF(AND(U419,19<=$C$10),G419,"—") -> — | G45: =IF(AND(U419,19<=$C$10),B419,"— (not enough time / prereq blocked)") -> — (not enough time / prereq blocked) | L45: =IF(AND(U419,19<=$C$10),C419,"—") -> — | N45: =IF(AND(U419,19<=$C$10),D419,"—") -> — | O45: =IF(AND(U419,19<=$C$10),E419,"—") -> — | P45: =IF(AND(U419,19<=$C$10),F419,"—") -> — | Q45: =IF(AND(U419,19<=$C$10),T419,"—") -> — | R45: =IF(AND(U419,19<=$C$10),$M$24-T419,"—") -> — | S45: =IF(AND(U419,19<=$C$10),H419,"—") -> — | T45: — Keep | U45: =IFERROR(IF(AND(U419,19<=$C$10),INDEX('📆 Daily Schedule'!$Q$5:$Q$400,MATCH(B419,'📆 Daily Schedule'!$F$5:$F$400,0)),"—"),"—") -> —
B46: =IF(AND(U420,20<=$C$10),20,"") | C46: =IF(AND(U420,20<=$C$10),IF(P420,"🚨 MUST DO",IF(O420,"⏰ OVERDUE","")),"—") -> — | E46: =IF(AND(U420,20<=$C$10),G420,"—") -> — | G46: =IF(AND(U420,20<=$C$10),B420,"— (not enough time / prereq blocked)") -> — (not enough time / prereq blocked) | L46: =IF(AND(U420,20<=$C$10),C420,"—") -> — | N46: =IF(AND(U420,20<=$C$10),D420,"—") -> — | O46: =IF(AND(U420,20<=$C$10),E420,"—") -> — | P46: =IF(AND(U420,20<=$C$10),F420,"—") -> — | Q46: =IF(AND(U420,20<=$C$10),T420,"—") -> — | R46: =IF(AND(U420,20<=$C$10),$M$24-T420,"—") -> — | S46: =IF(AND(U420,20<=$C$10),H420,"—") -> — | T46: — Keep | U46: =IFERROR(IF(AND(U420,20<=$C$10),INDEX('📆 Daily Schedule'!$Q$5:$Q$400,MATCH(B420,'📆 Daily Schedule'!$F$5:$F$400,0)),"—"),"—") -> —
B47: =IF(AND(U421,21<=$C$10),21,"") | C47: =IF(AND(U421,21<=$C$10),IF(P421,"🚨 MUST DO",IF(O421,"⏰ OVERDUE","")),"—") -> — | E47: =IF(AND(U421,21<=$C$10),G421,"—") -> — | G47: =IF(AND(U421,21<=$C$10),B421,"— (not enough time / prereq blocked)") -> — (not enough time / prereq blocked) | L47: =IF(AND(U421,21<=$C$10),C421,"—") -> — | N47: =IF(AND(U421,21<=$C$10),D421,"—") -> — | O47: =IF(AND(U421,21<=$C$10),E421,"—") -> — | P47: =IF(AND(U421,21<=$C$10),F421,"—") -> — | Q47: =IF(AND(U421,21<=$C$10),T421,"—") -> — | R47: =IF(AND(U421,21<=$C$10),$M$24-T421,"—") -> — | S47: =IF(AND(U421,21<=$C$10),H421,"—") -> — | T47: — Keep | U47: =IFERROR(IF(AND(U421,21<=$C$10),INDEX('📆 Daily Schedule'!$Q$5:$Q$400,MATCH(B421,'📆 Daily Schedule'!$F$5:$F$400,0)),"—"),"—") -> —
B48: =IF(AND(U422,22<=$C$10),22,"") | C48: =IF(AND(U422,22<=$C$10),IF(P422,"🚨 MUST DO",IF(O422,"⏰ OVERDUE","")),"—") -> — | E48: =IF(AND(U422,22<=$C$10),G422,"—") -> — | G48: =IF(AND(U422,22<=$C$10),B422,"— (not enough time / prereq blocked)") -> — (not enough time / prereq blocked) | L48: =IF(AND(U422,22<=$C$10),C422,"—") -> — | N48: =IF(AND(U422,22<=$C$10),D422,"—") -> — | O48: =IF(AND(U422,22<=$C$10),E422,"—") -> — | P48: =IF(AND(U422,22<=$C$10),F422,"—") -> — | Q48: =IF(AND(U422,22<=$C$10),T422,"—") -> — | R48: =IF(AND(U422,22<=$C$10),$M$24-T422,"—") -> — | S48: =IF(AND(U422,22<=$C$10),H422,"—") -> — | T48: — Keep | U48: =IFERROR(IF(AND(U422,22<=$C$10),INDEX('📆 Daily Schedule'!$Q$5:$Q$400,MATCH(B422,'📆 Daily Schedule'!$F$5:$F$400,0)),"—"),"—") -> —
B49: =IF(AND(U423,23<=$C$10),23,"") | C49: =IF(AND(U423,23<=$C$10),IF(P423,"🚨 MUST DO",IF(O423,"⏰ OVERDUE","")),"—") -> — | E49: =IF(AND(U423,23<=$C$10),G423,"—") -> — | G49: =IF(AND(U423,23<=$C$10),B423,"— (not enough time / prereq blocked)") -> — (not enough time / prereq blocked) | L49: =IF(AND(U423,23<=$C$10),C423,"—") -> — | N49: =IF(AND(U423,23<=$C$10),D423,"—") -> — | O49: =IF(AND(U423,23<=$C$10),E423,"—") -> — | P49: =IF(AND(U423,23<=$C$10),F423,"—") -> — | Q49: =IF(AND(U423,23<=$C$10),T423,"—") -> — | R49: =IF(AND(U423,23<=$C$10),$M$24-T423,"—") -> — | S49: =IF(AND(U423,23<=$C$10),H423,"—") -> — | T49: — Keep | U49: =IFERROR(IF(AND(U423,23<=$C$10),INDEX('📆 Daily Schedule'!$Q$5:$Q$400,MATCH(B423,'📆 Daily Schedule'!$F$5:$F$400,0)),"—"),"—") -> —
B50: =IF(AND(U424,24<=$C$10),24,"") | C50: =IF(AND(U424,24<=$C$10),IF(P424,"🚨 MUST DO",IF(O424,"⏰ OVERDUE","")),"—") -> — | E50: =IF(AND(U424,24<=$C$10),G424,"—") -> — | G50: =IF(AND(U424,24<=$C$10),B424,"— (not enough time / prereq blocked)") -> — (not enough time / prereq blocked) | L50: =IF(AND(U424,24<=$C$10),C424,"—") -> — | N50: =IF(AND(U424,24<=$C$10),D424,"—") -> — | O50: =IF(AND(U424,24<=$C$10),E424,"—") -> — | P50: =IF(AND(U424,24<=$C$10),F424,"—") -> — | Q50: =IF(AND(U424,24<=$C$10),T424,"—") -> — | R50: =IF(AND(U424,24<=$C$10),$M$24-T424,"—") -> — | S50: =IF(AND(U424,24<=$C$10),H424,"—") -> — | T50: — Keep | U50: =IFERROR(IF(AND(U424,24<=$C$10),INDEX('📆 Daily Schedule'!$Q$5:$Q$400,MATCH(B424,'📆 Daily Schedule'!$F$5:$F$400,0)),"—"),"—") -> —
B51: =IF(AND(U425,25<=$C$10),25,"") | C51: =IF(AND(U425,25<=$C$10),IF(P425,"🚨 MUST DO",IF(O425,"⏰ OVERDUE","")),"—") -> — | E51: =IF(AND(U425,25<=$C$10),G425,"—") -> — | G51: =IF(AND(U425,25<=$C$10),B425,"— (not enough time / prereq blocked)") -> — (not enough time / prereq blocked) | L51: =IF(AND(U425,25<=$C$10),C425,"—") -> — | N51: =IF(AND(U425,25<=$C$10),D425,"—") -> — | O51: =IF(AND(U425,25<=$C$10),E425,"—") -> — | P51: =IF(AND(U425,25<=$C$10),F425,"—") -> — | Q51: =IF(AND(U425,25<=$C$10),T425,"—") -> — | R51: =IF(AND(U425,25<=$C$10),$M$24-T425,"—") -> — | S51: =IF(AND(U425,25<=$C$10),H425,"—") -> — | T51: — Keep | U51: =IFERROR(IF(AND(U425,25<=$C$10),INDEX('📆 Daily Schedule'!$Q$5:$Q$400,MATCH(B425,'📆 Daily Schedule'!$F$5:$F$400,0)),"—"),"—") -> —
B52: =IF(AND(U426,26<=$C$10),26,"") | C52: =IF(AND(U426,26<=$C$10),IF(P426,"🚨 MUST DO",IF(O426,"⏰ OVERDUE","")),"—") -> — | E52: =IF(AND(U426,26<=$C$10),G426,"—") -> — | G52: =IF(AND(U426,26<=$C$10),B426,"— (not enough time / prereq blocked)") -> — (not enough time / prereq blocked) | L52: =IF(AND(U426,26<=$C$10),C426,"—") -> — | N52: =IF(AND(U426,26<=$C$10),D426,"—") -> — | O52: =IF(AND(U426,26<=$C$10),E426,"—") -> — | P52: =IF(AND(U426,26<=$C$10),F426,"—") -> — | Q52: =IF(AND(U426,26<=$C$10),T426,"—") -> — | R52: =IF(AND(U426,26<=$C$10),$M$24-T426,"—") -> — | S52: =IF(AND(U426,26<=$C$10),H426,"—") -> — | T52: — Keep | U52: =IFERROR(IF(AND(U426,26<=$C$10),INDEX('📆 Daily Schedule'!$Q$5:$Q$400,MATCH(B426,'📆 Daily Schedule'!$F$5:$F$400,0)),"—"),"—") -> —
B53: =IF(AND(U427,27<=$C$10),27,"") | C53: =IF(AND(U427,27<=$C$10),IF(P427,"🚨 MUST DO",IF(O427,"⏰ OVERDUE","")),"—") -> — | E53: =IF(AND(U427,27<=$C$10),G427,"—") -> — | G53: =IF(AND(U427,27<=$C$10),B427,"— (not enough time / prereq blocked)") -> — (not enough time / prereq blocked) | L53: =IF(AND(U427,27<=$C$10),C427,"—") -> — | N53: =IF(AND(U427,27<=$C$10),D427,"—") -> — | O53: =IF(AND(U427,27<=$C$10),E427,"—") -> — | P53: =IF(AND(U427,27<=$C$10),F427,"—") -> — | Q53: =IF(AND(U427,27<=$C$10),T427,"—") -> — | R53: =IF(AND(U427,27<=$C$10),$M$24-T427,"—") -> — | S53: =IF(AND(U427,27<=$C$10),H427,"—") -> — | T53: — Keep | U53: =IFERROR(IF(AND(U427,27<=$C$10),INDEX('📆 Daily Schedule'!$Q$5:$Q$400,MATCH(B427,'📆 Daily Schedule'!$F$5:$F$400,0)),"—"),"—") -> —
B54: =IF(AND(U428,28<=$C$10),28,"") | C54: =IF(AND(U428,28<=$C$10),IF(P428,"🚨 MUST DO",IF(O428,"⏰ OVERDUE","")),"—") -> — | E54: =IF(AND(U428,28<=$C$10),G428,"—") -> — | G54: =IF(AND(U428,28<=$C$10),B428,"— (not enough time / prereq blocked)") -> — (not enough time / prereq blocked) | L54: =IF(AND(U428,28<=$C$10),C428,"—") -> — | N54: =IF(AND(U428,28<=$C$10),D428,"—") -> — | O54: =IF(AND(U428,28<=$C$10),E428,"—") -> — | P54: =IF(AND(U428,28<=$C$10),F428,"—") -> — | Q54: =IF(AND(U428,28<=$C$10),T428,"—") -> — | R54: =IF(AND(U428,28<=$C$10),$M$24-T428,"—") -> — | S54: =IF(AND(U428,28<=$C$10),H428,"—") -> — | T54: — Keep | U54: =IFERROR(IF(AND(U428,28<=$C$10),INDEX('📆 Daily Schedule'!$Q$5:$Q$400,MATCH(B428,'📆 Daily Schedule'!$F$5:$F$400,0)),"—"),"—") -> —
B55: =IF(AND(U429,29<=$C$10),29,"") | C55: =IF(AND(U429,29<=$C$10),IF(P429,"🚨 MUST DO",IF(O429,"⏰ OVERDUE","")),"—") -> — | E55: =IF(AND(U429,29<=$C$10),G429,"—") -> — | G55: =IF(AND(U429,29<=$C$10),B429,"— (not enough time / prereq blocked)") -> — (not enough time / prereq blocked) | L55: =IF(AND(U429,29<=$C$10),C429,"—") -> — | N55: =IF(AND(U429,29<=$C$10),D429,"—") -> — | O55: =IF(AND(U429,29<=$C$10),E429,"—") -> — | P55: =IF(AND(U429,29<=$C$10),F429,"—") -> — | Q55: =IF(AND(U429,29<=$C$10),T429,"—") -> — | R55: =IF(AND(U429,29<=$C$10),$M$24-T429,"—") -> — | S55: =IF(AND(U429,29<=$C$10),H429,"—") -> — | T55: — Keep | U55: =IFERROR(IF(AND(U429,29<=$C$10),INDEX('📆 Daily Schedule'!$Q$5:$Q$400,MATCH(B429,'📆 Daily Schedule'!$F$5:$F$400,0)),"—"),"—") -> —
B56: =IF(AND(U430,30<=$C$10),30,"") | C56: =IF(AND(U430,30<=$C$10),IF(P430,"🚨 MUST DO",IF(O430,"⏰ OVERDUE","")),"—") -> — | E56: =IF(AND(U430,30<=$C$10),G430,"—") -> — | G56: =IF(AND(U430,30<=$C$10),B430,"— (not enough time / prereq blocked)") -> — (not enough time / prereq blocked) | L56: =IF(AND(U430,30<=$C$10),C430,"—") -> — | N56: =IF(AND(U430,30<=$C$10),D430,"—") -> — | O56: =IF(AND(U430,30<=$C$10),E430,"—") -> — | P56: =IF(AND(U430,30<=$C$10),F430,"—") -> — | Q56: =IF(AND(U430,30<=$C$10),T430,"—") -> — | R56: =IF(AND(U430,30<=$C$10),$M$24-T430,"—") -> — | S56: =IF(AND(U430,30<=$C$10),H430,"—") -> — | T56: — Keep | U56: =IFERROR(IF(AND(U430,30<=$C$10),INDEX('📆 Daily Schedule'!$Q$5:$Q$400,MATCH(B430,'📆 Daily Schedule'!$F$5:$F$400,0)),"—"),"—") -> —
B57: =IF(AND(U431,31<=$C$10),31,"") | C57: =IF(AND(U431,31<=$C$10),IF(P431,"🚨 MUST DO",IF(O431,"⏰ OVERDUE","")),"—") -> — | E57: =IF(AND(U431,31<=$C$10),G431,"—") -> — | G57: =IF(AND(U431,31<=$C$10),B431,"— (not enough time / prereq blocked)") -> — (not enough time / prereq blocked) | L57: =IF(AND(U431,31<=$C$10),C431,"—") -> — | N57: =IF(AND(U431,31<=$C$10),D431,"—") -> — | O57: =IF(AND(U431,31<=$C$10),E431,"—") -> — | P57: =IF(AND(U431,31<=$C$10),F431,"—") -> — | Q57: =IF(AND(U431,31<=$C$10),T431,"—") -> — | R57: =IF(AND(U431,31<=$C$10),$M$24-T431,"—") -> — | S57: =IF(AND(U431,31<=$C$10),H431,"—") -> — | T57: — Keep | U57: =IFERROR(IF(AND(U431,31<=$C$10),INDEX('📆 Daily Schedule'!$Q$5:$Q$400,MATCH(B431,'📆 Daily Schedule'!$F$5:$F$400,0)),"—"),"—") -> —
B58: =IF(AND(U432,32<=$C$10),32,"") | C58: =IF(AND(U432,32<=$C$10),IF(P432,"🚨 MUST DO",IF(O432,"⏰ OVERDUE","")),"—") -> — | E58: =IF(AND(U432,32<=$C$10),G432,"—") -> — | G58: =IF(AND(U432,32<=$C$10),B432,"— (not enough time / prereq blocked)") -> — (not enough time / prereq blocked) | L58: =IF(AND(U432,32<=$C$10),C432,"—") -> — | N58: =IF(AND(U432,32<=$C$10),D432,"—") -> — | O58: =IF(AND(U432,32<=$C$10),E432,"—") -> — | P58: =IF(AND(U432,32<=$C$10),F432,"—") -> — | Q58: =IF(AND(U432,32<=$C$10),T432,"—") -> — | R58: =IF(AND(U432,32<=$C$10),$M$24-T432,"—") -> — | S58: =IF(AND(U432,32<=$C$10),H432,"—") -> — | T58: — Keep | U58: =IFERROR(IF(AND(U432,32<=$C$10),INDEX('📆 Daily Schedule'!$Q$5:$Q$400,MATCH(B432,'📆 Daily Schedule'!$F$5:$F$400,0)),"—"),"—") -> —
B59: =IF(AND(U433,33<=$C$10),33,"") | C59: =IF(AND(U433,33<=$C$10),IF(P433,"🚨 MUST DO",IF(O433,"⏰ OVERDUE","")),"—") -> — | E59: =IF(AND(U433,33<=$C$10),G433,"—") -> — | G59: =IF(AND(U433,33<=$C$10),B433,"— (not enough time / prereq blocked)") -> — (not enough time / prereq blocked) | L59: =IF(AND(U433,33<=$C$10),C433,"—") -> — | N59: =IF(AND(U433,33<=$C$10),D433,"—") -> — | O59: =IF(AND(U433,33<=$C$10),E433,"—") -> — | P59: =IF(AND(U433,33<=$C$10),F433,"—") -> — | Q59: =IF(AND(U433,33<=$C$10),T433,"—") -> — | R59: =IF(AND(U433,33<=$C$10),$M$24-T433,"—") -> — | S59: =IF(AND(U433,33<=$C$10),H433,"—") -> — | T59: — Keep | U59: =IFERROR(IF(AND(U433,33<=$C$10),INDEX('📆 Daily Schedule'!$Q$5:$Q$400,MATCH(B433,'📆 Daily Schedule'!$F$5:$F$400,0)),"—"),"—") -> —
B60: =IF(AND(U434,34<=$C$10),34,"") | C60: =IF(AND(U434,34<=$C$10),IF(P434,"🚨 MUST DO",IF(O434,"⏰ OVERDUE","")),"—") -> — | E60: =IF(AND(U434,34<=$C$10),G434,"—") -> — | G60: =IF(AND(U434,34<=$C$10),B434,"— (not enough time / prereq blocked)") -> — (not enough time / prereq blocked) | L60: =IF(AND(U434,34<=$C$10),C434,"—") -> — | N60: =IF(AND(U434,34<=$C$10),D434,"—") -> — | O60: =IF(AND(U434,34<=$C$10),E434,"—") -> — | P60: =IF(AND(U434,34<=$C$10),F434,"—") -> — | Q60: =IF(AND(U434,34<=$C$10),T434,"—") -> — | R60: =IF(AND(U434,34<=$C$10),$M$24-T434,"—") -> — | S60: =IF(AND(U434,34<=$C$10),H434,"—") -> — | T60: — Keep | U60: =IFERROR(IF(AND(U434,34<=$C$10),INDEX('📆 Daily Schedule'!$Q$5:$Q$400,MATCH(B434,'📆 Daily Schedule'!$F$5:$F$400,0)),"—"),"—") -> —
B61: =IF(AND(U435,35<=$C$10),35,"") | C61: =IF(AND(U435,35<=$C$10),IF(P435,"🚨 MUST DO",IF(O435,"⏰ OVERDUE","")),"—") -> — | E61: =IF(AND(U435,35<=$C$10),G435,"—") -> — | G61: =IF(AND(U435,35<=$C$10),B435,"— (not enough time / prereq blocked)") -> — (not enough time / prereq blocked) | L61: =IF(AND(U435,35<=$C$10),C435,"—") -> — | N61: =IF(AND(U435,35<=$C$10),D435,"—") -> — | O61: =IF(AND(U435,35<=$C$10),E435,"—") -> — | P61: =IF(AND(U435,35<=$C$10),F435,"—") -> — | Q61: =IF(AND(U435,35<=$C$10),T435,"—") -> — | R61: =IF(AND(U435,35<=$C$10),$M$24-T435,"—") -> — | S61: =IF(AND(U435,35<=$C$10),H435,"—") -> — | T61: — Keep | U61: =IFERROR(IF(AND(U435,35<=$C$10),INDEX('📆 Daily Schedule'!$Q$5:$Q$400,MATCH(B435,'📆 Daily Schedule'!$F$5:$F$400,0)),"—"),"—") -> —
B62: =IF(AND(U436,36<=$C$10),36,"") | C62: =IF(AND(U436,36<=$C$10),IF(P436,"🚨 MUST DO",IF(O436,"⏰ OVERDUE","")),"—") -> — | E62: =IF(AND(U436,36<=$C$10),G436,"—") -> — | G62: =IF(AND(U436,36<=$C$10),B436,"— (not enough time / prereq blocked)") -> — (not enough time / prereq blocked) | L62: =IF(AND(U436,36<=$C$10),C436,"—") -> — | N62: =IF(AND(U436,36<=$C$10),D436,"—") -> — | O62: =IF(AND(U436,36<=$C$10),E436,"—") -> — | P62: =IF(AND(U436,36<=$C$10),F436,"—") -> — | Q62: =IF(AND(U436,36<=$C$10),T436,"—") -> — | R62: =IF(AND(U436,36<=$C$10),$M$24-T436,"—") -> — | S62: =IF(AND(U436,36<=$C$10),H436,"—") -> — | T62: — Keep | U62: =IFERROR(IF(AND(U436,36<=$C$10),INDEX('📆 Daily Schedule'!$Q$5:$Q$400,MATCH(B436,'📆 Daily Schedule'!$F$5:$F$400,0)),"—"),"—") -> —
B63: =IF(AND(U437,37<=$C$10),37,"") | C63: =IF(AND(U437,37<=$C$10),IF(P437,"🚨 MUST DO",IF(O437,"⏰ OVERDUE","")),"—") -> — | E63: =IF(AND(U437,37<=$C$10),G437,"—") -> — | G63: =IF(AND(U437,37<=$C$10),B437,"— (not enough time / prereq blocked)") -> — (not enough time / prereq blocked) | L63: =IF(AND(U437,37<=$C$10),C437,"—") -> — | N63: =IF(AND(U437,37<=$C$10),D437,"—") -> — | O63: =IF(AND(U437,37<=$C$10),E437,"—") -> — | P63: =IF(AND(U437,37<=$C$10),F437,"—") -> — | Q63: =IF(AND(U437,37<=$C$10),T437,"—") -> — | R63: =IF(AND(U437,37<=$C$10),$M$24-T437,"—") -> — | S63: =IF(AND(U437,37<=$C$10),H437,"—") -> — | T63: — Keep | U63: =IFERROR(IF(AND(U437,37<=$C$10),INDEX('📆 Daily Schedule'!$Q$5:$Q$400,MATCH(B437,'📆 Daily Schedule'!$F$5:$F$400,0)),"—"),"—") -> —
B64: =IF(AND(U438,38<=$C$10),38,"") | C64: =IF(AND(U438,38<=$C$10),IF(P438,"🚨 MUST DO",IF(O438,"⏰ OVERDUE","")),"—") -> — | E64: =IF(AND(U438,38<=$C$10),G438,"—") -> — | G64: =IF(AND(U438,38<=$C$10),B438,"— (not enough time / prereq blocked)") -> — (not enough time / prereq blocked) | L64: =IF(AND(U438,38<=$C$10),C438,"—") -> — | N64: =IF(AND(U438,38<=$C$10),D438,"—") -> — | O64: =IF(AND(U438,38<=$C$10),E438,"—") -> — | P64: =IF(AND(U438,38<=$C$10),F438,"—") -> — | Q64: =IF(AND(U438,38<=$C$10),T438,"—") -> — | R64: =IF(AND(U438,38<=$C$10),$M$24-T438,"—") -> — | S64: =IF(AND(U438,38<=$C$10),H438,"—") -> — | T64: — Keep | U64: =IFERROR(IF(AND(U438,38<=$C$10),INDEX('📆 Daily Schedule'!$Q$5:$Q$400,MATCH(B438,'📆 Daily Schedule'!$F$5:$F$400,0)),"—"),"—") -> —
B65: =IF(AND(U439,39<=$C$10),39,"") | C65: =IF(AND(U439,39<=$C$10),IF(P439,"🚨 MUST DO",IF(O439,"⏰ OVERDUE","")),"—") -> — | E65: =IF(AND(U439,39<=$C$10),G439,"—") -> — | G65: =IF(AND(U439,39<=$C$10),B439,"— (not enough time / prereq blocked)") -> — (not enough time / prereq blocked) | L65: =IF(AND(U439,39<=$C$10),C439,"—") -> — | N65: =IF(AND(U439,39<=$C$10),D439,"—") -> — | O65: =IF(AND(U439,39<=$C$10),E439,"—") -> — | P65: =IF(AND(U439,39<=$C$10),F439,"—") -> — | Q65: =IF(AND(U439,39<=$C$10),T439,"—") -> — | R65: =IF(AND(U439,39<=$C$10),$M$24-T439,"—") -> — | S65: =IF(AND(U439,39<=$C$10),H439,"—") -> — | T65: — Keep | U65: =IFERROR(IF(AND(U439,39<=$C$10),INDEX('📆 Daily Schedule'!$Q$5:$Q$400,MATCH(B439,'📆 Daily Schedule'!$F$5:$F$400,0)),"—"),"—") -> —
B66: =IF(AND(U440,40<=$C$10),40,"") | C66: =IF(AND(U440,40<=$C$10),IF(P440,"🚨 MUST DO",IF(O440,"⏰ OVERDUE","")),"—") -> — | E66: =IF(AND(U440,40<=$C$10),G440,"—") -> — | G66: =IF(AND(U440,40<=$C$10),B440,"— (not enough time / prereq blocked)") -> — (not enough time / prereq blocked) | L66: =IF(AND(U440,40<=$C$10),C440,"—") -> — | N66: =IF(AND(U440,40<=$C$10),D440,"—") -> — | O66: =IF(AND(U440,40<=$C$10),E440,"—") -> — | P66: =IF(AND(U440,40<=$C$10),F440,"—") -> — | Q66: =IF(AND(U440,40<=$C$10),T440,"—") -> — | R66: =IF(AND(U440,40<=$C$10),$M$24-T440,"—") -> — | S66: =IF(AND(U440,40<=$C$10),H440,"—") -> — | T66: — Keep | U66: =IFERROR(IF(AND(U440,40<=$C$10),INDEX('📆 Daily Schedule'!$Q$5:$Q$400,MATCH(B440,'📆 Daily Schedule'!$F$5:$F$400,0)),"—"),"—") -> —
B67: Total → | Q67: =IFERROR(SUMPRODUCT((U401:U440=TRUE())*E401:E440),0) -> 0 | R67: =IFERROR(COUNTIF(U401:U440,TRUE()),0) -> 0 | S67: ✅ Plan ready
A69: 🔄 SWAP PANEL — Flag a row above (🔄 SWAP ME) → pick replacement below. Pool mode = C14 setting. Locked rows (🔒) cannot be swapped.
B70: =IF($C$14="Option 1 — Same Month Only","📋 Pool: Same Month Only — showing topics from today's month (M"&$B$400&")","📋 Pool: Current + Next Week — showing W"&$A$400&" & W"&$A$400+1&" topics") -> 📋 Pool: Current + Next Week — showing W1 & W2 topics
B71: Pool ID | C71: Replacement Topic (available, same month / cur+next wk, not done) | M71: Phase | O71: Avg hrs | P71: Flag | R71: Times Swapped | S71: Lock Status | U71: Reason to Choose
B72: =IF(AND('🔄 Topic Pool'!P19<>"✅ Done",'🔄 Topic Pool'!M19="✅ YES",NOT(A460=2),NOT(AND(A460=1,OR('🔄 Topic Pool'!P19="❌ Missed",'🔄 Topic Pool'!P19="🔄 Partial"))),IF($C$14="Option 1 — Same Month Only",'🔄 Topic Pool'!B19=$B$400,OR(AND('🔄 Topic Pool'!B19=$B$400,ROUND(('🔄 Topic Pool'!A19-1)/7,0)=$A$400),AND('🔄 Topic Pool'!B19=$B$400,ROUND(('🔄 Topic Pool'!A19-1)/7,0)=$A$400+1)))),'🔄 Topic Pool'!A19,"—") -> — | C72: =IF(AND('🔄 Topic Pool'!P19<>"✅ Done",'🔄 Topic Pool'!M19="✅ YES",NOT(A460=2),NOT(AND(A460=1,OR('🔄 Topic Pool'!P19="❌ Missed",'🔄 Topic Pool'!P19="🔄 Partial"))),IF($C$14="Option 1 — Same Month Only",'🔄 Topic Pool'!B19=$B$400,OR(AND('🔄 Topic Pool'!B19=$B$400,ROUND(('🔄 Topic Pool'!A19-1)/7,0)=$A$400),AND('🔄 Topic Pool'!B19=$B$400,ROUND(('🔄 Topic Pool'!A19-1)/7,0)=$A$400+1)))),'🔄 Topic Pool'!D19,"—") -> — | M72: =IF(AND('🔄 Topic Pool'!P19<>"✅ Done",'🔄 Topic Pool'!M19="✅ YES",NOT(A460=2),NOT(AND(A460=1,OR('🔄 Topic Pool'!P19="❌ Missed",'🔄 Topic Pool'!P19="🔄 Partial"))),IF($C$14="Option 1 — Same Month Only",'🔄 Topic Pool'!B19=$B$400,OR(AND('🔄 Topic Pool'!B19=$B$400,ROUND(('🔄 Topic Pool'!A19-1)/7,0)=$A$400),AND('🔄 Topic Pool'!B19=$B$400,ROUND(('🔄 Topic Pool'!A19-1)/7,0)=$A$400+1)))),'🔄 Topic Pool'!E19,"—") -> — | O72: =IF(AND('🔄 Topic Pool'!P19<>"✅ Done",'🔄 Topic Pool'!M19="✅ YES",NOT(A460=2),NOT(AND(A460=1,OR('🔄 Topic Pool'!P19="❌ Missed",'🔄 Topic Pool'!P19="🔄 Partial"))),IF($C$14="Option 1 — Same Month Only",'🔄 Topic Pool'!B19=$B$400,OR(AND('🔄 Topic Pool'!B19=$B$400,ROUND(('🔄 Topic Pool'!A19-1)/7,0)=$A$400),AND('🔄 Topic Pool'!B19=$B$400,ROUND(('🔄 Topic Pool'!A19-1)/7,0)=$A$400+1)))),'🔄 Topic Pool'!G19,"—") -> — | P72: =IF(AND('🔄 Topic Pool'!P19<>"✅ Done",'🔄 Topic Pool'!M19="✅ YES",NOT(A460=2),NOT(AND(A460=1,OR('🔄 Topic Pool'!P19="❌ Missed",'🔄 Topic Pool'!P19="🔄 Partial"))),IF($C$14="Option 1 — Same Month Only",'🔄 Topic Pool'!B19=$B$400,OR(AND('🔄 Topic Pool'!B19=$B$400,ROUND(('🔄 Topic Pool'!A19-1)/7,0)=$A$400),AND('🔄 Topic Pool'!B19=$B$400,ROUND(('🔄 Topic Pool'!A19-1)/7,0)=$A$400+1)))),'🔄 Topic Pool'!J19,"—") -> — | R72: =IF(AND('🔄 Topic Pool'!P19<>"✅ Done",'🔄 Topic Pool'!M19="✅ YES",NOT(A460=2),NOT(AND(A460=1,OR('🔄 Topic Pool'!P19="❌ Missed",'🔄 Topic Pool'!P19="🔄 Partial"))),IF($C$14="Option 1 — Same Month Only",'🔄 Topic Pool'!B19=$B$400,OR(AND('🔄 Topic Pool'!B19=$B$400,ROUND(('🔄 Topic Pool'!A19-1)/7,0)=$A$400),AND('🔄 Topic Pool'!B19=$B$400,ROUND(('🔄 Topic Pool'!A19-1)/7,0)=$A$400+1)))),COUNTIF('📋 Swap History'!$F$4:$F$200,'🔄 Topic Pool'!D19),"—") -> — | S72: =IF(NOT(AND('🔄 Topic Pool'!P19<>"✅ Done",'🔄 Topic Pool'!M19="✅ YES",NOT(A460=2),NOT(AND(A460=1,OR('🔄 Topic Pool'!P19="❌ Missed",'🔄 Topic Pool'!P19="🔄 Partial"))),IF($C$14="Option 1 — Same Month Only",'🔄 Topic Pool'!B19=$B$400,OR(AND('🔄 Topic Pool'!B19=$B$400,ROUND(('🔄 Topic Pool'!A19-1)/7,0)=$A$400),AND('🔄 Topic Pool'!B19=$B$400,ROUND(('🔄 Topic Pool'!A19-1)/7,0)=$A$400+1))))),"🔒",IF('🔄 Topic Pool'!M19="🔒 NO","🔒",IF(COUNTIF('📋 Swap History'!$F$4:$F$200,'🔄 Topic Pool'!D19)>=$C$8,"🔒","✅"))) -> 🔒 | U72: =IF(AND('🔄 Topic Pool'!P19<>"✅ Done",'🔄 Topic Pool'!M19="✅ YES",NOT(A460=2),NOT(AND(A460=1,OR('🔄 Topic Pool'!P19="❌ Missed",'🔄 Topic Pool'!P19="🔄 Partial"))),IF($C$14="Option 1 — Same Month Only",'🔄 Topic Pool'!B19=$B$400,OR(AND('🔄 Topic Pool'!B19=$B$400,ROUND(('🔄 Topic Pool'!A19-1)/7,0)=$A$400),AND('🔄 Topic Pool'!B19=$B$400,ROUND(('🔄 Topic Pool'!A19-1)/7,0)=$A$400+1)))),'🔄 Topic Pool'!J19&" — Seq "&'🔄 Topic Pool'!C19&" in month","—") -> —
B73: =IF(AND('🔄 Topic Pool'!P23<>"✅ Done",'🔄 Topic Pool'!M23="✅ YES",NOT(A460=2),NOT(AND(A460=1,OR('🔄 Topic Pool'!P23="❌ Missed",'🔄 Topic Pool'!P23="🔄 Partial"))),IF($C$14="Option 1 — Same Month Only",'🔄 Topic Pool'!B23=$B$400,OR(AND('🔄 Topic Pool'!B23=$B$400,ROUND(('🔄 Topic Pool'!A23-1)/7,0)=$A$400),AND('🔄 Topic Pool'!B23=$B$400,ROUND(('🔄 Topic Pool'!A23-1)/7,0)=$A$400+1)))),'🔄 Topic Pool'!A23,"—") -> — | C73: =IF(AND('🔄 Topic Pool'!P23<>"✅ Done",'🔄 Topic Pool'!M23="✅ YES",NOT(A460=2),NOT(AND(A460=1,OR('🔄 Topic Pool'!P23="❌ Missed",'🔄 Topic Pool'!P23="🔄 Partial"))),IF($C$14="Option 1 — Same Month Only",'🔄 Topic Pool'!B23=$B$400,OR(AND('🔄 Topic Pool'!B23=$B$400,ROUND(('🔄 Topic Pool'!A23-1)/7,0)=$A$400),AND('🔄 Topic Pool'!B23=$B$400,ROUND(('🔄 Topic Pool'!A23-1)/7,0)=$A$400+1)))),'🔄 Topic Pool'!D23,"—") -> — | M73: =IF(AND('🔄 Topic Pool'!P23<>"✅ Done",'🔄 Topic Pool'!M23="✅ YES",NOT(A460=2),NOT(AND(A460=1,OR('🔄 Topic Pool'!P23="❌ Missed",'🔄 Topic Pool'!P23="🔄 Partial"))),IF($C$14="Option 1 — Same Month Only",'🔄 Topic Pool'!B23=$B$400,OR(AND('🔄 Topic Pool'!B23=$B$400,ROUND(('🔄 Topic Pool'!A23-1)/7,0)=$A$400),AND('🔄 Topic Pool'!B23=$B$400,ROUND(('🔄 Topic Pool'!A23-1)/7,0)=$A$400+1)))),'🔄 Topic Pool'!E23,"—") -> — | O73: =IF(AND('🔄 Topic Pool'!P23<>"✅ Done",'🔄 Topic Pool'!M23="✅ YES",NOT(A460=2),NOT(AND(A460=1,OR('🔄 Topic Pool'!P23="❌ Missed",'🔄 Topic Pool'!P23="🔄 Partial"))),IF($C$14="Option 1 — Same Month Only",'🔄 Topic Pool'!B23=$B$400,OR(AND('🔄 Topic Pool'!B23=$B$400,ROUND(('🔄 Topic Pool'!A23-1)/7,0)=$A$400),AND('🔄 Topic Pool'!B23=$B$400,ROUND(('🔄 Topic Pool'!A23-1)/7,0)=$A$400+1)))),'🔄 Topic Pool'!G23,"—") -> — | P73: =IF(AND('🔄 Topic Pool'!P23<>"✅ Done",'🔄 Topic Pool'!M23="✅ YES",NOT(A460=2),NOT(AND(A460=1,OR('🔄 Topic Pool'!P23="❌ Missed",'🔄 Topic Pool'!P23="🔄 Partial"))),IF($C$14="Option 1 — Same Month Only",'🔄 Topic Pool'!B23=$B$400,OR(AND('🔄 Topic Pool'!B23=$B$400,ROUND(('🔄 Topic Pool'!A23-1)/7,0)=$A$400),AND('🔄 Topic Pool'!B23=$B$400,ROUND(('🔄 Topic Pool'!A23-1)/7,0)=$A$400+1)))),'🔄 Topic Pool'!J23,"—") -> — | R73: =IF(AND('🔄 Topic Pool'!P23<>"✅ Done",'🔄 Topic Pool'!M23="✅ YES",NOT(A460=2),NOT(AND(A460=1,OR('🔄 Topic Pool'!P23="❌ Missed",'🔄 Topic Pool'!P23="🔄 Partial"))),IF($C$14="Option 1 — Same Month Only",'🔄 Topic Pool'!B23=$B$400,OR(AND('🔄 Topic Pool'!B23=$B$400,ROUND(('🔄 Topic Pool'!A23-1)/7,0)=$A$400),AND('🔄 Topic Pool'!B23=$B$400,ROUND(('🔄 Topic Pool'!A23-1)/7,0)=$A$400+1)))),COUNTIF('📋 Swap History'!$F$4:$F$200,'🔄 Topic Pool'!D23),"—") -> — | S73: =IF(NOT(AND('🔄 Topic Pool'!P23<>"✅ Done",'🔄 Topic Pool'!M23="✅ YES",NOT(A460=2),NOT(AND(A460=1,OR('🔄 Topic Pool'!P23="❌ Missed",'🔄 Topic Pool'!P23="🔄 Partial"))),IF($C$14="Option 1 — Same Month Only",'🔄 Topic Pool'!B23=$B$400,OR(AND('🔄 Topic Pool'!B23=$B$400,ROUND(('🔄 Topic Pool'!A23-1)/7,0)=$A$400),AND('🔄 Topic Pool'!B23=$B$400,ROUND(('🔄 Topic Pool'!A23-1)/7,0)=$A$400+1))))),"🔒",IF('🔄 Topic Pool'!M23="🔒 NO","🔒",IF(COUNTIF('📋 Swap History'!$F$4:$F$200,'🔄 Topic Pool'!D23)>=$C$8,"🔒","✅"))) -> 🔒 | U73: =IF(AND('🔄 Topic Pool'!P23<>"✅ Done",'🔄 Topic Pool'!M23="✅ YES",NOT(A460=2),NOT(AND(A460=1,OR('🔄 Topic Pool'!P23="❌ Missed",'🔄 Topic Pool'!P23="🔄 Partial"))),IF($C$14="Option 1 — Same Month Only",'🔄 Topic Pool'!B23=$B$400,OR(AND('🔄 Topic Pool'!B23=$B$400,ROUND(('🔄 Topic Pool'!A23-1)/7,0)=$A$400),AND('🔄 Topic Pool'!B23=$B$400,ROUND(('🔄 Topic Pool'!A23-1)/7,0)=$A$400+1)))),'🔄 Topic Pool'!J23&" — Seq "&'🔄 Topic Pool'!C23&" in month","—") -> —
B74: =IF(AND('🔄 Topic Pool'!P8<>"✅ Done",'🔄 Topic Pool'!M8="✅ YES",NOT(A460=2),NOT(AND(A460=1,OR('🔄 Topic Pool'!P8="❌ Missed",'🔄 Topic Pool'!P8="🔄 Partial"))),IF($C$14="Option 1 — Same Month Only",'🔄 Topic Pool'!B8=$B$400,OR(AND('🔄 Topic Pool'!B8=$B$400,ROUND(('🔄 Topic Pool'!A8-1)/7,0)=$A$400),AND('🔄 Topic Pool'!B8=$B$400,ROUND(('🔄 Topic Pool'!A8-1)/7,0)=$A$400+1)))),'🔄 Topic Pool'!A8,"—") -> — | C74: =IF(AND('🔄 Topic Pool'!P8<>"✅ Done",'🔄 Topic Pool'!M8="✅ YES",NOT(A460=2),NOT(AND(A460=1,OR('🔄 Topic Pool'!P8="❌ Missed",'🔄 Topic Pool'!P8="🔄 Partial"))),IF($C$14="Option 1 — Same Month Only",'🔄 Topic Pool'!B8=$B$400,OR(AND('🔄 Topic Pool'!B8=$B$400,ROUND(('🔄 Topic Pool'!A8-1)/7,0)=$A$400),AND('🔄 Topic Pool'!B8=$B$400,ROUND(('🔄 Topic Pool'!A8-1)/7,0)=$A$400+1)))),'🔄 Topic Pool'!D8,"—") -> — | M74: =IF(AND('🔄 Topic Pool'!P8<>"✅ Done",'🔄 Topic Pool'!M8="✅ YES",NOT(A460=2),NOT(AND(A460=1,OR('🔄 Topic Pool'!P8="❌ Missed",'🔄 Topic Pool'!P8="🔄 Partial"))),IF($C$14="Option 1 — Same Month Only",'🔄 Topic Pool'!B8=$B$400,OR(AND('🔄 Topic Pool'!B8=$B$400,ROUND(('🔄 Topic Pool'!A8-1)/7,0)=$A$400),AND('🔄 Topic Pool'!B8=$B$400,ROUND(('🔄 Topic Pool'!A8-1)/7,0)=$A$400+1)))),'🔄 Topic Pool'!E8,"—") -> — | O74: =IF(AND('🔄 Topic Pool'!P8<>"✅ Done",'🔄 Topic Pool'!M8="✅ YES",NOT(A460=2),NOT(AND(A460=1,OR('🔄 Topic Pool'!P8="❌ Missed",'🔄 Topic Pool'!P8="🔄 Partial"))),IF($C$14="Option 1 — Same Month Only",'🔄 Topic Pool'!B8=$B$400,OR(AND('🔄 Topic Pool'!B8=$B$400,ROUND(('🔄 Topic Pool'!A8-1)/7,0)=$A$400),AND('🔄 Topic Pool'!B8=$B$400,ROUND(('🔄 Topic Pool'!A8-1)/7,0)=$A$400+1)))),'🔄 Topic Pool'!G8,"—") -> — | P74: =IF(AND('🔄 Topic Pool'!P8<>"✅ Done",'🔄 Topic Pool'!M8="✅ YES",NOT(A460=2),NOT(AND(A460=1,OR('🔄 Topic Pool'!P8="❌ Missed",'🔄 Topic Pool'!P8="🔄 Partial"))),IF($C$14="Option 1 — Same Month Only",'🔄 Topic Pool'!B8=$B$400,OR(AND('🔄 Topic Pool'!B8=$B$400,ROUND(('🔄 Topic Pool'!A8-1)/7,0)=$A$400),AND('🔄 Topic Pool'!B8=$B$400,ROUND(('🔄 Topic Pool'!A8-1)/7,0)=$A$400+1)))),'🔄 Topic Pool'!J8,"—") -> — | R74: =IF(AND('🔄 Topic Pool'!P8<>"✅ Done",'🔄 Topic Pool'!M8="✅ YES",NOT(A460=2),NOT(AND(A460=1,OR('🔄 Topic Pool'!P8="❌ Missed",'🔄 Topic Pool'!P8="🔄 Partial"))),IF($C$14="Option 1 — Same Month Only",'🔄 Topic Pool'!B8=$B$400,OR(AND('🔄 Topic Pool'!B8=$B$400,ROUND(('🔄 Topic Pool'!A8-1)/7,0)=$A$400),AND('🔄 Topic Pool'!B8=$B$400,ROUND(('🔄 Topic Pool'!A8-1)/7,0)=$A$400+1)))),COUNTIF('📋 Swap History'!$F$4:$F$200,'🔄 Topic Pool'!D8),"—") -> — | S74: =IF(NOT(AND('🔄 Topic Pool'!P8<>"✅ Done",'🔄 Topic Pool'!M8="✅ YES",NOT(A460=2),NOT(AND(A460=1,OR('🔄 Topic Pool'!P8="❌ Missed",'🔄 Topic Pool'!P8="🔄 Partial"))),IF($C$14="Option 1 — Same Month Only",'🔄 Topic Pool'!B8=$B$400,OR(AND('🔄 Topic Pool'!B8=$B$400,ROUND(('🔄 Topic Pool'!A8-1)/7,0)=$A$400),AND('🔄 Topic Pool'!B8=$B$400,ROUND(('🔄 Topic Pool'!A8-1)/7,0)=$A$400+1))))),"🔒",IF('🔄 Topic Pool'!M8="🔒 NO","🔒",IF(COUNTIF('📋 Swap History'!$F$4:$F$200,'🔄 Topic Pool'!D8)>=$C$8,"🔒","✅"))) -> 🔒 | U74: =IF(AND('🔄 Topic Pool'!P8<>"✅ Done",'🔄 Topic Pool'!M8="✅ YES",NOT(A460=2),NOT(AND(A460=1,OR('🔄 Topic Pool'!P8="❌ Missed",'🔄 Topic Pool'!P8="🔄 Partial"))),IF($C$14="Option 1 — Same Month Only",'🔄 Topic Pool'!B8=$B$400,OR(AND('🔄 Topic Pool'!B8=$B$400,ROUND(('🔄 Topic Pool'!A8-1)/7,0)=$A$400),AND('🔄 Topic Pool'!B8=$B$400,ROUND(('🔄 Topic Pool'!A8-1)/7,0)=$A$400+1)))),'🔄 Topic Pool'!J8&" — Seq "&'🔄 Topic Pool'!C8&" in month","—") -> —
B75: =IF(A460=2,"🔒 ALL SWAPS LOCKED",IF(A460=1,"🟡 Overdue topics locked — others swappable",IF($C$14="Option 1 — Same Month Only","📋 Pool: Same Month — M"&$B$400&" topics","📋 Pool: Cur+Next Week — W"&$A$400&" & W"&($A$400+1)&" topics"))) -> 📋 Pool: Cur+Next Week — W1 & W2 topics | C75: =IF(AND('🔄 Topic Pool'!P15<>"✅ Done",'🔄 Topic Pool'!M15="✅ YES",NOT(A460=2),NOT(AND(A460=1,OR('🔄 Topic Pool'!P15="❌ Missed",'🔄 Topic Pool'!P15="🔄 Partial"))),IF($C$14="Option 1 — Same Month Only",'🔄 Topic Pool'!B15=$B$400,OR(AND('🔄 Topic Pool'!B15=$B$400,ROUND(('🔄 Topic Pool'!A15-1)/7,0)=$A$400),AND('🔄 Topic Pool'!B15=$B$400,ROUND(('🔄 Topic Pool'!A15-1)/7,0)=$A$400+1)))),'🔄 Topic Pool'!D15,"—") -> — | M75: =IF(AND('🔄 Topic Pool'!P15<>"✅ Done",'🔄 Topic Pool'!M15="✅ YES",NOT(A460=2),NOT(AND(A460=1,OR('🔄 Topic Pool'!P15="❌ Missed",'🔄 Topic Pool'!P15="🔄 Partial"))),IF($C$14="Option 1 — Same Month Only",'🔄 Topic Pool'!B15=$B$400,OR(AND('🔄 Topic Pool'!B15=$B$400,ROUND(('🔄 Topic Pool'!A15-1)/7,0)=$A$400),AND('🔄 Topic Pool'!B15=$B$400,ROUND(('🔄 Topic Pool'!A15-1)/7,0)=$A$400+1)))),'🔄 Topic Pool'!E15,"—") -> — | O75: =IF(AND('🔄 Topic Pool'!P15<>"✅ Done",'🔄 Topic Pool'!M15="✅ YES",NOT(A460=2),NOT(AND(A460=1,OR('🔄 Topic Pool'!P15="❌ Missed",'🔄 Topic Pool'!P15="🔄 Partial"))),IF($C$14="Option 1 — Same Month Only",'🔄 Topic Pool'!B15=$B$400,OR(AND('🔄 Topic Pool'!B15=$B$400,ROUND(('🔄 Topic Pool'!A15-1)/7,0)=$A$400),AND('🔄 Topic Pool'!B15=$B$400,ROUND(('🔄 Topic Pool'!A15-1)/7,0)=$A$400+1)))),'🔄 Topic Pool'!G15,"—") -> — | P75: =IF(AND('🔄 Topic Pool'!P15<>"✅ Done",'🔄 Topic Pool'!M15="✅ YES",NOT(A460=2),NOT(AND(A460=1,OR('🔄 Topic Pool'!P15="❌ Missed",'🔄 Topic Pool'!P15="🔄 Partial"))),IF($C$14="Option 1 — Same Month Only",'🔄 Topic Pool'!B15=$B$400,OR(AND('🔄 Topic Pool'!B15=$B$400,ROUND(('🔄 Topic Pool'!A15-1)/7,0)=$A$400),AND('🔄 Topic Pool'!B15=$B$400,ROUND(('🔄 Topic Pool'!A15-1)/7,0)=$A$400+1)))),'🔄 Topic Pool'!J15,"—") -> — | R75: =IF(AND('🔄 Topic Pool'!P15<>"✅ Done",'🔄 Topic Pool'!M15="✅ YES",NOT(A460=2),NOT(AND(A460=1,OR('🔄 Topic Pool'!P15="❌ Missed",'🔄 Topic Pool'!P15="🔄 Partial"))),IF($C$14="Option 1 — Same Month Only",'🔄 Topic Pool'!B15=$B$400,OR(AND('🔄 Topic Pool'!B15=$B$400,ROUND(('🔄 Topic Pool'!A15-1)/7,0)=$A$400),AND('🔄 Topic Pool'!B15=$B$400,ROUND(('🔄 Topic Pool'!A15-1)/7,0)=$A$400+1)))),COUNTIF('📋 Swap History'!$F$4:$F$200,'🔄 Topic Pool'!D15),"—") -> — | S75: =IF(NOT(AND('🔄 Topic Pool'!P15<>"✅ Done",'🔄 Topic Pool'!M15="✅ YES",NOT(A460=2),NOT(AND(A460=1,OR('🔄 Topic Pool'!P15="❌ Missed",'🔄 Topic Pool'!P15="🔄 Partial"))),IF($C$14="Option 1 — Same Month Only",'🔄 Topic Pool'!B15=$B$400,OR(AND('🔄 Topic Pool'!B15=$B$400,ROUND(('🔄 Topic Pool'!A15-1)/7,0)=$A$400),AND('🔄 Topic Pool'!B15=$B$400,ROUND(('🔄 Topic Pool'!A15-1)/7,0)=$A$400+1))))),"🔒",IF('🔄 Topic Pool'!M15="🔒 NO","🔒",IF(COUNTIF('📋 Swap History'!$F$4:$F$200,'🔄 Topic Pool'!D15)>=$C$8,"🔒","✅"))) -> 🔒 | U75: =IF(AND('🔄 Topic Pool'!P15<>"✅ Done",'🔄 Topic Pool'!M15="✅ YES",NOT(A460=2),NOT(AND(A460=1,OR('🔄 Topic Pool'!P15="❌ Missed",'🔄 Topic Pool'!P15="🔄 Partial"))),IF($C$14="Option 1 — Same Month Only",'🔄 Topic Pool'!B15=$B$400,OR(AND('🔄 Topic Pool'!B15=$B$400,ROUND(('🔄 Topic Pool'!A15-1)/7,0)=$A$400),AND('🔄 Topic Pool'!B15=$B$400,ROUND(('🔄 Topic Pool'!A15-1)/7,0)=$A$400+1)))),'🔄 Topic Pool'!J15&" — Seq "&'🔄 Topic Pool'!C15&" in month","—") -> —
B76: =IF(AND('🔄 Topic Pool'!P22<>"✅ Done",'🔄 Topic Pool'!M22="✅ YES",NOT(A460=2),NOT(AND(A460=1,OR('🔄 Topic Pool'!P22="❌ Missed",'🔄 Topic Pool'!P22="🔄 Partial"))),IF($C$14="Option 1 — Same Month Only",'🔄 Topic Pool'!B22=$B$400,OR(AND('🔄 Topic Pool'!B22=$B$400,ROUND(('🔄 Topic Pool'!A22-1)/7,0)=$A$400),AND('🔄 Topic Pool'!B22=$B$400,ROUND(('🔄 Topic Pool'!A22-1)/7,0)=$A$400+1)))),'🔄 Topic Pool'!A22,"—") -> — | C76: =IF(AND('🔄 Topic Pool'!P22<>"✅ Done",'🔄 Topic Pool'!M22="✅ YES",NOT(A460=2),NOT(AND(A460=1,OR('🔄 Topic Pool'!P22="❌ Missed",'🔄 Topic Pool'!P22="🔄 Partial"))),IF($C$14="Option 1 — Same Month Only",'🔄 Topic Pool'!B22=$B$400,OR(AND('🔄 Topic Pool'!B22=$B$400,ROUND(('🔄 Topic Pool'!A22-1)/7,0)=$A$400),AND('🔄 Topic Pool'!B22=$B$400,ROUND(('🔄 Topic Pool'!A22-1)/7,0)=$A$400+1)))),'🔄 Topic Pool'!D22,"—") -> — | M76: =IF(AND('🔄 Topic Pool'!P22<>"✅ Done",'🔄 Topic Pool'!M22="✅ YES",NOT(A460=2),NOT(AND(A460=1,OR('🔄 Topic Pool'!P22="❌ Missed",'🔄 Topic Pool'!P22="🔄 Partial"))),IF($C$14="Option 1 — Same Month Only",'🔄 Topic Pool'!B22=$B$400,OR(AND('🔄 Topic Pool'!B22=$B$400,ROUND(('🔄 Topic Pool'!A22-1)/7,0)=$A$400),AND('🔄 Topic Pool'!B22=$B$400,ROUND(('🔄 Topic Pool'!A22-1)/7,0)=$A$400+1)))),'🔄 Topic Pool'!E22,"—") -> — | O76: =IF(AND('🔄 Topic Pool'!P22<>"✅ Done",'🔄 Topic Pool'!M22="✅ YES",NOT(A460=2),NOT(AND(A460=1,OR('🔄 Topic Pool'!P22="❌ Missed",'🔄 Topic Pool'!P22="🔄 Partial"))),IF($C$14="Option 1 — Same Month Only",'🔄 Topic Pool'!B22=$B$400,OR(AND('🔄 Topic Pool'!B22=$B$400,ROUND(('🔄 Topic Pool'!A22-1)/7,0)=$A$400),AND('🔄 Topic Pool'!B22=$B$400,ROUND(('🔄 Topic Pool'!A22-1)/7,0)=$A$400+1)))),'🔄 Topic Pool'!G22,"—") -> — | P76: =IF(AND('🔄 Topic Pool'!P22<>"✅ Done",'🔄 Topic Pool'!M22="✅ YES",NOT(A460=2),NOT(AND(A460=1,OR('🔄 Topic Pool'!P22="❌ Missed",'🔄 Topic Pool'!P22="🔄 Partial"))),IF($C$14="Option 1 — Same Month Only",'🔄 Topic Pool'!B22=$B$400,OR(AND('🔄 Topic Pool'!B22=$B$400,ROUND(('🔄 Topic Pool'!A22-1)/7,0)=$A$400),AND('🔄 Topic Pool'!B22=$B$400,ROUND(('🔄 Topic Pool'!A22-1)/7,0)=$A$400+1)))),'🔄 Topic Pool'!J22,"—") -> — | R76: =IF(AND('🔄 Topic Pool'!P22<>"✅ Done",'🔄 Topic Pool'!M22="✅ YES",NOT(A460=2),NOT(AND(A460=1,OR('🔄 Topic Pool'!P22="❌ Missed",'🔄 Topic Pool'!P22="🔄 Partial"))),IF($C$14="Option 1 — Same Month Only",'🔄 Topic Pool'!B22=$B$400,OR(AND('🔄 Topic Pool'!B22=$B$400,ROUND(('🔄 Topic Pool'!A22-1)/7,0)=$A$400),AND('🔄 Topic Pool'!B22=$B$400,ROUND(('🔄 Topic Pool'!A22-1)/7,0)=$A$400+1)))),COUNTIF('📋 Swap History'!$F$4:$F$200,'🔄 Topic Pool'!D22),"—") -> — | S76: =IF(NOT(AND('🔄 Topic Pool'!P22<>"✅ Done",'🔄 Topic Pool'!M22="✅ YES",NOT(A460=2),NOT(AND(A460=1,OR('🔄 Topic Pool'!P22="❌ Missed",'🔄 Topic Pool'!P22="🔄 Partial"))),IF($C$14="Option 1 — Same Month Only",'🔄 Topic Pool'!B22=$B$400,OR(AND('🔄 Topic Pool'!B22=$B$400,ROUND(('🔄 Topic Pool'!A22-1)/7,0)=$A$400),AND('🔄 Topic Pool'!B22=$B$400,ROUND(('🔄 Topic Pool'!A22-1)/7,0)=$A$400+1))))),"🔒",IF('🔄 Topic Pool'!M22="🔒 NO","🔒",IF(COUNTIF('📋 Swap History'!$F$4:$F$200,'🔄 Topic Pool'!D22)>=$C$8,"🔒","✅"))) -> 🔒 | U76: =IF(AND('🔄 Topic Pool'!P22<>"✅ Done",'🔄 Topic Pool'!M22="✅ YES",NOT(A460=2),NOT(AND(A460=1,OR('🔄 Topic Pool'!P22="❌ Missed",'🔄 Topic Pool'!P22="🔄 Partial"))),IF($C$14="Option 1 — Same Month Only",'🔄 Topic Pool'!B22=$B$400,OR(AND('🔄 Topic Pool'!B22=$B$400,ROUND(('🔄 Topic Pool'!A22-1)/7,0)=$A$400),AND('🔄 Topic Pool'!B22=$B$400,ROUND(('🔄 Topic Pool'!A22-1)/7,0)=$A$400+1)))),'🔄 Topic Pool'!J22&" — Seq "&'🔄 Topic Pool'!C22&" in month","—") -> —
B77: =IF(AND('🔄 Topic Pool'!P29<>"✅ Done",'🔄 Topic Pool'!M29="✅ YES",NOT(A460=2),NOT(AND(A460=1,OR('🔄 Topic Pool'!P29="❌ Missed",'🔄 Topic Pool'!P29="🔄 Partial"))),IF($C$14="Option 1 — Same Month Only",'🔄 Topic Pool'!B29=$B$400,OR(AND('🔄 Topic Pool'!B29=$B$400,ROUND(('🔄 Topic Pool'!A29-1)/7,0)=$A$400),AND('🔄 Topic Pool'!B29=$B$400,ROUND(('🔄 Topic Pool'!A29-1)/7,0)=$A$400+1)))),'🔄 Topic Pool'!A29,"—") -> — | C77: =IF(AND('🔄 Topic Pool'!P29<>"✅ Done",'🔄 Topic Pool'!M29="✅ YES",NOT(A460=2),NOT(AND(A460=1,OR('🔄 Topic Pool'!P29="❌ Missed",'🔄 Topic Pool'!P29="🔄 Partial"))),IF($C$14="Option 1 — Same Month Only",'🔄 Topic Pool'!B29=$B$400,OR(AND('🔄 Topic Pool'!B29=$B$400,ROUND(('🔄 Topic Pool'!A29-1)/7,0)=$A$400),AND('🔄 Topic Pool'!B29=$B$400,ROUND(('🔄 Topic Pool'!A29-1)/7,0)=$A$400+1)))),'🔄 Topic Pool'!D29,"—") -> — | M77: =IF(AND('🔄 Topic Pool'!P29<>"✅ Done",'🔄 Topic Pool'!M29="✅ YES",NOT(A460=2),NOT(AND(A460=1,OR('🔄 Topic Pool'!P29="❌ Missed",'🔄 Topic Pool'!P29="🔄 Partial"))),IF($C$14="Option 1 — Same Month Only",'🔄 Topic Pool'!B29=$B$400,OR(AND('🔄 Topic Pool'!B29=$B$400,ROUND(('🔄 Topic Pool'!A29-1)/7,0)=$A$400),AND('🔄 Topic Pool'!B29=$B$400,ROUND(('🔄 Topic Pool'!A29-1)/7,0)=$A$400+1)))),'🔄 Topic Pool'!E29,"—") -> — | O77: =IF(AND('🔄 Topic Pool'!P29<>"✅ Done",'🔄 Topic Pool'!M29="✅ YES",NOT(A460=2),NOT(AND(A460=1,OR('🔄 Topic Pool'!P29="❌ Missed",'🔄 Topic Pool'!P29="🔄 Partial"))),IF($C$14="Option 1 — Same Month Only",'🔄 Topic Pool'!B29=$B$400,OR(AND('🔄 Topic Pool'!B29=$B$400,ROUND(('🔄 Topic Pool'!A29-1)/7,0)=$A$400),AND('🔄 Topic Pool'!B29=$B$400,ROUND(('🔄 Topic Pool'!A29-1)/7,0)=$A$400+1)))),'🔄 Topic Pool'!G29,"—") -> — | P77: =IF(AND('🔄 Topic Pool'!P29<>"✅ Done",'🔄 Topic Pool'!M29="✅ YES",NOT(A460=2),NOT(AND(A460=1,OR('🔄 Topic Pool'!P29="❌ Missed",'🔄 Topic Pool'!P29="🔄 Partial"))),IF($C$14="Option 1 — Same Month Only",'🔄 Topic Pool'!B29=$B$400,OR(AND('🔄 Topic Pool'!B29=$B$400,ROUND(('🔄 Topic Pool'!A29-1)/7,0)=$A$400),AND('🔄 Topic Pool'!B29=$B$400,ROUND(('🔄 Topic Pool'!A29-1)/7,0)=$A$400+1)))),'🔄 Topic Pool'!J29,"—") -> — | R77: =IF(AND('🔄 Topic Pool'!P29<>"✅ Done",'🔄 Topic Pool'!M29="✅ YES",NOT(A460=2),NOT(AND(A460=1,OR('🔄 Topic Pool'!P29="❌ Missed",'🔄 Topic Pool'!P29="🔄 Partial"))),IF($C$14="Option 1 — Same Month Only",'🔄 Topic Pool'!B29=$B$400,OR(AND('🔄 Topic Pool'!B29=$B$400,ROUND(('🔄 Topic Pool'!A29-1)/7,0)=$A$400),AND('🔄 Topic Pool'!B29=$B$400,ROUND(('🔄 Topic Pool'!A29-1)/7,0)=$A$400+1)))),COUNTIF('📋 Swap History'!$F$4:$F$200,'🔄 Topic Pool'!D29),"—") -> — | S77: =IF(NOT(AND('🔄 Topic Pool'!P29<>"✅ Done",'🔄 Topic Pool'!M29="✅ YES",NOT(A460=2),NOT(AND(A460=1,OR('🔄 Topic Pool'!P29="❌ Missed",'🔄 Topic Pool'!P29="🔄 Partial"))),IF($C$14="Option 1 — Same Month Only",'🔄 Topic Pool'!B29=$B$400,OR(AND('🔄 Topic Pool'!B29=$B$400,ROUND(('🔄 Topic Pool'!A29-1)/7,0)=$A$400),AND('🔄 Topic Pool'!B29=$B$400,ROUND(('🔄 Topic Pool'!A29-1)/7,0)=$A$400+1))))),"🔒",IF('🔄 Topic Pool'!M29="🔒 NO","🔒",IF(COUNTIF('📋 Swap History'!$F$4:$F$200,'🔄 Topic Pool'!D29)>=$C$8,"🔒","✅"))) -> 🔒 | U77: =IF(AND('🔄 Topic Pool'!P29<>"✅ Done",'🔄 Topic Pool'!M29="✅ YES",NOT(A460=2),NOT(AND(A460=1,OR('🔄 Topic Pool'!P29="❌ Missed",'🔄 Topic Pool'!P29="🔄 Partial"))),IF($C$14="Option 1 — Same Month Only",'🔄 Topic Pool'!B29=$B$400,OR(AND('🔄 Topic Pool'!B29=$B$400,ROUND(('🔄 Topic Pool'!A29-1)/7,0)=$A$400),AND('🔄 Topic Pool'!B29=$B$400,ROUND(('🔄 Topic Pool'!A29-1)/7,0)=$A$400+1)))),'🔄 Topic Pool'!J29&" — Seq "&'🔄 Topic Pool'!C29&" in month","—") -> —
B78: =IF(AND('🔄 Topic Pool'!P4<>"✅ Done",'🔄 Topic Pool'!M4="✅ YES",NOT(A460=2),NOT(AND(A460=1,OR('🔄 Topic Pool'!P4="❌ Missed",'🔄 Topic Pool'!P4="🔄 Partial"))),IF($C$14="Option 1 — Same Month Only",'🔄 Topic Pool'!B4=$B$400,OR(AND('🔄 Topic Pool'!B4=$B$400,ROUND(('🔄 Topic Pool'!A4-1)/7,0)=$A$400),AND('🔄 Topic Pool'!B4=$B$400,ROUND(('🔄 Topic Pool'!A4-1)/7,0)=$A$400+1)))),'🔄 Topic Pool'!A4,"—") -> — | C78: =IF(AND('🔄 Topic Pool'!P4<>"✅ Done",'🔄 Topic Pool'!M4="✅ YES",NOT(A460=2),NOT(AND(A460=1,OR('🔄 Topic Pool'!P4="❌ Missed",'🔄 Topic Pool'!P4="🔄 Partial"))),IF($C$14="Option 1 — Same Month Only",'🔄 Topic Pool'!B4=$B$400,OR(AND('🔄 Topic Pool'!B4=$B$400,ROUND(('🔄 Topic Pool'!A4-1)/7,0)=$A$400),AND('🔄 Topic Pool'!B4=$B$400,ROUND(('🔄 Topic Pool'!A4-1)/7,0)=$A$400+1)))),'🔄 Topic Pool'!D4,"—") -> — | M78: =IF(AND('🔄 Topic Pool'!P4<>"✅ Done",'🔄 Topic Pool'!M4="✅ YES",NOT(A460=2),NOT(AND(A460=1,OR('🔄 Topic Pool'!P4="❌ Missed",'🔄 Topic Pool'!P4="🔄 Partial"))),IF($C$14="Option 1 — Same Month Only",'🔄 Topic Pool'!B4=$B$400,OR(AND('🔄 Topic Pool'!B4=$B$400,ROUND(('🔄 Topic Pool'!A4-1)/7,0)=$A$400),AND('🔄 Topic Pool'!B4=$B$400,ROUND(('🔄 Topic Pool'!A4-1)/7,0)=$A$400+1)))),'🔄 Topic Pool'!E4,"—") -> — | O78: =IF(AND('🔄 Topic Pool'!P4<>"✅ Done",'🔄 Topic Pool'!M4="✅ YES",NOT(A460=2),NOT(AND(A460=1,OR('🔄 Topic Pool'!P4="❌ Missed",'🔄 Topic Pool'!P4="🔄 Partial"))),IF($C$14="Option 1 — Same Month Only",'🔄 Topic Pool'!B4=$B$400,OR(AND('🔄 Topic Pool'!B4=$B$400,ROUND(('🔄 Topic Pool'!A4-1)/7,0)=$A$400),AND('🔄 Topic Pool'!B4=$B$400,ROUND(('🔄 Topic Pool'!A4-1)/7,0)=$A$400+1)))),'🔄 Topic Pool'!G4,"—") -> — | P78: =IF(AND('🔄 Topic Pool'!P4<>"✅ Done",'🔄 Topic Pool'!M4="✅ YES",NOT(A460=2),NOT(AND(A460=1,OR('🔄 Topic Pool'!P4="❌ Missed",'🔄 Topic Pool'!P4="🔄 Partial"))),IF($C$14="Option 1 — Same Month Only",'🔄 Topic Pool'!B4=$B$400,OR(AND('🔄 Topic Pool'!B4=$B$400,ROUND(('🔄 Topic Pool'!A4-1)/7,0)=$A$400),AND('🔄 Topic Pool'!B4=$B$400,ROUND(('🔄 Topic Pool'!A4-1)/7,0)=$A$400+1)))),'🔄 Topic Pool'!J4,"—") -> — | R78: =IF(AND('🔄 Topic Pool'!P4<>"✅ Done",'🔄 Topic Pool'!M4="✅ YES",NOT(A460=2),NOT(AND(A460=1,OR('🔄 Topic Pool'!P4="❌ Missed",'🔄 Topic Pool'!P4="🔄 Partial"))),IF($C$14="Option 1 — Same Month Only",'🔄 Topic Pool'!B4=$B$400,OR(AND('🔄 Topic Pool'!B4=$B$400,ROUND(('🔄 Topic Pool'!A4-1)/7,0)=$A$400),AND('🔄 Topic Pool'!B4=$B$400,ROUND(('🔄 Topic Pool'!A4-1)/7,0)=$A$400+1)))),COUNTIF('📋 Swap History'!$F$4:$F$200,'🔄 Topic Pool'!D4),"—") -> — | S78: =IF(NOT(AND('🔄 Topic Pool'!P4<>"✅ Done",'🔄 Topic Pool'!M4="✅ YES",NOT(A460=2),NOT(AND(A460=1,OR('🔄 Topic Pool'!P4="❌ Missed",'🔄 Topic Pool'!P4="🔄 Partial"))),IF($C$14="Option 1 — Same Month Only",'🔄 Topic Pool'!B4=$B$400,OR(AND('🔄 Topic Pool'!B4=$B$400,ROUND(('🔄 Topic Pool'!A4-1)/7,0)=$A$400),AND('🔄 Topic Pool'!B4=$B$400,ROUND(('🔄 Topic Pool'!A4-1)/7,0)=$A$400+1))))),"🔒",IF('🔄 Topic Pool'!M4="🔒 NO","🔒",IF(COUNTIF('📋 Swap History'!$F$4:$F$200,'🔄 Topic Pool'!D4)>=$C$8,"🔒","✅"))) -> 🔒 | U78: =IF(AND('🔄 Topic Pool'!P4<>"✅ Done",'🔄 Topic Pool'!M4="✅ YES",NOT(A460=2),NOT(AND(A460=1,OR('🔄 Topic Pool'!P4="❌ Missed",'🔄 Topic Pool'!P4="🔄 Partial"))),IF($C$14="Option 1 — Same Month Only",'🔄 Topic Pool'!B4=$B$400,OR(AND('🔄 Topic Pool'!B4=$B$400,ROUND(('🔄 Topic Pool'!A4-1)/7,0)=$A$400),AND('🔄 Topic Pool'!B4=$B$400,ROUND(('🔄 Topic Pool'!A4-1)/7,0)=$A$400+1)))),'🔄 Topic Pool'!J4&" — Seq "&'🔄 Topic Pool'!C4&" in month","—") -> —
B79: =IF(AND('🔄 Topic Pool'!P5<>"✅ Done",'🔄 Topic Pool'!M5="✅ YES",NOT(A460=2),NOT(AND(A460=1,OR('🔄 Topic Pool'!P5="❌ Missed",'🔄 Topic Pool'!P5="🔄 Partial"))),IF($C$14="Option 1 — Same Month Only",'🔄 Topic Pool'!B5=$B$400,OR(AND('🔄 Topic Pool'!B5=$B$400,ROUND(('🔄 Topic Pool'!A5-1)/7,0)=$A$400),AND('🔄 Topic Pool'!B5=$B$400,ROUND(('🔄 Topic Pool'!A5-1)/7,0)=$A$400+1)))),'🔄 Topic Pool'!A5,"—") -> — | C79: =IF(AND('🔄 Topic Pool'!P5<>"✅ Done",'🔄 Topic Pool'!M5="✅ YES",NOT(A460=2),NOT(AND(A460=1,OR('🔄 Topic Pool'!P5="❌ Missed",'🔄 Topic Pool'!P5="🔄 Partial"))),IF($C$14="Option 1 — Same Month Only",'🔄 Topic Pool'!B5=$B$400,OR(AND('🔄 Topic Pool'!B5=$B$400,ROUND(('🔄 Topic Pool'!A5-1)/7,0)=$A$400),AND('🔄 Topic Pool'!B5=$B$400,ROUND(('🔄 Topic Pool'!A5-1)/7,0)=$A$400+1)))),'🔄 Topic Pool'!D5,"—") -> — | M79: =IF(AND('🔄 Topic Pool'!P5<>"✅ Done",'🔄 Topic Pool'!M5="✅ YES",NOT(A460=2),NOT(AND(A460=1,OR('🔄 Topic Pool'!P5="❌ Missed",'🔄 Topic Pool'!P5="🔄 Partial"))),IF($C$14="Option 1 — Same Month Only",'🔄 Topic Pool'!B5=$B$400,OR(AND('🔄 Topic Pool'!B5=$B$400,ROUND(('🔄 Topic Pool'!A5-1)/7,0)=$A$400),AND('🔄 Topic Pool'!B5=$B$400,ROUND(('🔄 Topic Pool'!A5-1)/7,0)=$A$400+1)))),'🔄 Topic Pool'!E5,"—") -> — | O79: =IF(AND('🔄 Topic Pool'!P5<>"✅ Done",'🔄 Topic Pool'!M5="✅ YES",NOT(A460=2),NOT(AND(A460=1,OR('🔄 Topic Pool'!P5="❌ Missed",'🔄 Topic Pool'!P5="🔄 Partial"))),IF($C$14="Option 1 — Same Month Only",'🔄 Topic Pool'!B5=$B$400,OR(AND('🔄 Topic Pool'!B5=$B$400,ROUND(('🔄 Topic Pool'!A5-1)/7,0)=$A$400),AND('🔄 Topic Pool'!B5=$B$400,ROUND(('🔄 Topic Pool'!A5-1)/7,0)=$A$400+1)))),'🔄 Topic Pool'!G5,"—") -> — | P79: =IF(AND('🔄 Topic Pool'!P5<>"✅ Done",'🔄 Topic Pool'!M5="✅ YES",NOT(A460=2),NOT(AND(A460=1,OR('🔄 Topic Pool'!P5="❌ Missed",'🔄 Topic Pool'!P5="🔄 Partial"))),IF($C$14="Option 1 — Same Month Only",'🔄 Topic Pool'!B5=$B$400,OR(AND('🔄 Topic Pool'!B5=$B$400,ROUND(('🔄 Topic Pool'!A5-1)/7,0)=$A$400),AND('🔄 Topic Pool'!B5=$B$400,ROUND(('🔄 Topic Pool'!A5-1)/7,0)=$A$400+1)))),'🔄 Topic Pool'!J5,"—") -> — | R79: =IF(AND('🔄 Topic Pool'!P5<>"✅ Done",'🔄 Topic Pool'!M5="✅ YES",NOT(A460=2),NOT(AND(A460=1,OR('🔄 Topic Pool'!P5="❌ Missed",'🔄 Topic Pool'!P5="🔄 Partial"))),IF($C$14="Option 1 — Same Month Only",'🔄 Topic Pool'!B5=$B$400,OR(AND('🔄 Topic Pool'!B5=$B$400,ROUND(('🔄 Topic Pool'!A5-1)/7,0)=$A$400),AND('🔄 Topic Pool'!B5=$B$400,ROUND(('🔄 Topic Pool'!A5-1)/7,0)=$A$400+1)))),COUNTIF('📋 Swap History'!$F$4:$F$200,'🔄 Topic Pool'!D5),"—") -> — | S79: =IF(NOT(AND('🔄 Topic Pool'!P5<>"✅ Done",'🔄 Topic Pool'!M5="✅ YES",NOT(A460=2),NOT(AND(A460=1,OR('🔄 Topic Pool'!P5="❌ Missed",'🔄 Topic Pool'!P5="🔄 Partial"))),IF($C$14="Option 1 — Same Month Only",'🔄 Topic Pool'!B5=$B$400,OR(AND('🔄 Topic Pool'!B5=$B$400,ROUND(('🔄 Topic Pool'!A5-1)/7,0)=$A$400),AND('🔄 Topic Pool'!B5=$B$400,ROUND(('🔄 Topic Pool'!A5-1)/7,0)=$A$400+1))))),"🔒",IF('🔄 Topic Pool'!M5="🔒 NO","🔒",IF(COUNTIF('📋 Swap History'!$F$4:$F$200,'🔄 Topic Pool'!D5)>=$C$8,"🔒","✅"))) -> 🔒 | U79: =IF(AND('🔄 Topic Pool'!P5<>"✅ Done",'🔄 Topic Pool'!M5="✅ YES",NOT(A460=2),NOT(AND(A460=1,OR('🔄 Topic Pool'!P5="❌ Missed",'🔄 Topic Pool'!P5="🔄 Partial"))),IF($C$14="Option 1 — Same Month Only",'🔄 Topic Pool'!B5=$B$400,OR(AND('🔄 Topic Pool'!B5=$B$400,ROUND(('🔄 Topic Pool'!A5-1)/7,0)=$A$400),AND('🔄 Topic Pool'!B5=$B$400,ROUND(('🔄 Topic Pool'!A5-1)/7,0)=$A$400+1)))),'🔄 Topic Pool'!J5&" — Seq "&'🔄 Topic Pool'!C5&" in month","—") -> —
B80: =IF(AND('🔄 Topic Pool'!P6<>"✅ Done",'🔄 Topic Pool'!M6="✅ YES",NOT(A460=2),NOT(AND(A460=1,OR('🔄 Topic Pool'!P6="❌ Missed",'🔄 Topic Pool'!P6="🔄 Partial"))),IF($C$14="Option 1 — Same Month Only",'🔄 Topic Pool'!B6=$B$400,OR(AND('🔄 Topic Pool'!B6=$B$400,ROUND(('🔄 Topic Pool'!A6-1)/7,0)=$A$400),AND('🔄 Topic Pool'!B6=$B$400,ROUND(('🔄 Topic Pool'!A6-1)/7,0)=$A$400+1)))),'🔄 Topic Pool'!A6,"—") -> — | C80: =IF(AND('🔄 Topic Pool'!P6<>"✅ Done",'🔄 Topic Pool'!M6="✅ YES",NOT(A460=2),NOT(AND(A460=1,OR('🔄 Topic Pool'!P6="❌ Missed",'🔄 Topic Pool'!P6="🔄 Partial"))),IF($C$14="Option 1 — Same Month Only",'🔄 Topic Pool'!B6=$B$400,OR(AND('🔄 Topic Pool'!B6=$B$400,ROUND(('🔄 Topic Pool'!A6-1)/7,0)=$A$400),AND('🔄 Topic Pool'!B6=$B$400,ROUND(('🔄 Topic Pool'!A6-1)/7,0)=$A$400+1)))),'🔄 Topic Pool'!D6,"—") -> — | M80: =IF(AND('🔄 Topic Pool'!P6<>"✅ Done",'🔄 Topic Pool'!M6="✅ YES",NOT(A460=2),NOT(AND(A460=1,OR('🔄 Topic Pool'!P6="❌ Missed",'🔄 Topic Pool'!P6="🔄 Partial"))),IF($C$14="Option 1 — Same Month Only",'🔄 Topic Pool'!B6=$B$400,OR(AND('🔄 Topic Pool'!B6=$B$400,ROUND(('🔄 Topic Pool'!A6-1)/7,0)=$A$400),AND('🔄 Topic Pool'!B6=$B$400,ROUND(('🔄 Topic Pool'!A6-1)/7,0)=$A$400+1)))),'🔄 Topic Pool'!E6,"—") -> — | O80: =IF(AND('🔄 Topic Pool'!P6<>"✅ Done",'🔄 Topic Pool'!M6="✅ YES",NOT(A460=2),NOT(AND(A460=1,OR('🔄 Topic Pool'!P6="❌ Missed",'🔄 Topic Pool'!P6="🔄 Partial"))),IF($C$14="Option 1 — Same Month Only",'🔄 Topic Pool'!B6=$B$400,OR(AND('🔄 Topic Pool'!B6=$B$400,ROUND(('🔄 Topic Pool'!A6-1)/7,0)=$A$400),AND('🔄 Topic Pool'!B6=$B$400,ROUND(('🔄 Topic Pool'!A6-1)/7,0)=$A$400+1)))),'🔄 Topic Pool'!G6,"—") -> — | P80: =IF(AND('🔄 Topic Pool'!P6<>"✅ Done",'🔄 Topic Pool'!M6="✅ YES",NOT(A460=2),NOT(AND(A460=1,OR('🔄 Topic Pool'!P6="❌ Missed",'🔄 Topic Pool'!P6="🔄 Partial"))),IF($C$14="Option 1 — Same Month Only",'🔄 Topic Pool'!B6=$B$400,OR(AND('🔄 Topic Pool'!B6=$B$400,ROUND(('🔄 Topic Pool'!A6-1)/7,0)=$A$400),AND('🔄 Topic Pool'!B6=$B$400,ROUND(('🔄 Topic Pool'!A6-1)/7,0)=$A$400+1)))),'🔄 Topic Pool'!J6,"—") -> — | R80: =IF(AND('🔄 Topic Pool'!P6<>"✅ Done",'🔄 Topic Pool'!M6="✅ YES",NOT(A460=2),NOT(AND(A460=1,OR('🔄 Topic Pool'!P6="❌ Missed",'🔄 Topic Pool'!P6="🔄 Partial"))),IF($C$14="Option 1 — Same Month Only",'🔄 Topic Pool'!B6=$B$400,OR(AND('🔄 Topic Pool'!B6=$B$400,ROUND(('🔄 Topic Pool'!A6-1)/7,0)=$A$400),AND('🔄 Topic Pool'!B6=$B$400,ROUND(('🔄 Topic Pool'!A6-1)/7,0)=$A$400+1)))),COUNTIF('📋 Swap History'!$F$4:$F$200,'🔄 Topic Pool'!D6),"—") -> — | S80: =IF(NOT(AND('🔄 Topic Pool'!P6<>"✅ Done",'🔄 Topic Pool'!M6="✅ YES",NOT(A460=2),NOT(AND(A460=1,OR('🔄 Topic Pool'!P6="❌ Missed",'🔄 Topic Pool'!P6="🔄 Partial"))),IF($C$14="Option 1 — Same Month Only",'🔄 Topic Pool'!B6=$B$400,OR(AND('🔄 Topic Pool'!B6=$B$400,ROUND(('🔄 Topic Pool'!A6-1)/7,0)=$A$400),AND('🔄 Topic Pool'!B6=$B$400,ROUND(('🔄 Topic Pool'!A6-1)/7,0)=$A$400+1))))),"🔒",IF('🔄 Topic Pool'!M6="🔒 NO","🔒",IF(COUNTIF('📋 Swap History'!$F$4:$F$200,'🔄 Topic Pool'!D6)>=$C$8,"🔒","✅"))) -> 🔒 | U80: =IF(AND('🔄 Topic Pool'!P6<>"✅ Done",'🔄 Topic Pool'!M6="✅ YES",NOT(A460=2),NOT(AND(A460=1,OR('🔄 Topic Pool'!P6="❌ Missed",'🔄 Topic Pool'!P6="🔄 Partial"))),IF($C$14="Option 1 — Same Month Only",'🔄 Topic Pool'!B6=$B$400,OR(AND('🔄 Topic Pool'!B6=$B$400,ROUND(('🔄 Topic Pool'!A6-1)/7,0)=$A$400),AND('🔄 Topic Pool'!B6=$B$400,ROUND(('🔄 Topic Pool'!A6-1)/7,0)=$A$400+1)))),'🔄 Topic Pool'!J6&" — Seq "&'🔄 Topic Pool'!C6&" in month","—") -> —
B81: =IF(AND('🔄 Topic Pool'!P7<>"✅ Done",'🔄 Topic Pool'!M7="✅ YES",NOT(A460=2),NOT(AND(A460=1,OR('🔄 Topic Pool'!P7="❌ Missed",'🔄 Topic Pool'!P7="🔄 Partial"))),IF($C$14="Option 1 — Same Month Only",'🔄 Topic Pool'!B7=$B$400,OR(AND('🔄 Topic Pool'!B7=$B$400,ROUND(('🔄 Topic Pool'!A7-1)/7,0)=$A$400),AND('🔄 Topic Pool'!B7=$B$400,ROUND(('🔄 Topic Pool'!A7-1)/7,0)=$A$400+1)))),'🔄 Topic Pool'!A7,"—") -> — | C81: =IF(AND('🔄 Topic Pool'!P7<>"✅ Done",'🔄 Topic Pool'!M7="✅ YES",NOT(A460=2),NOT(AND(A460=1,OR('🔄 Topic Pool'!P7="❌ Missed",'🔄 Topic Pool'!P7="🔄 Partial"))),IF($C$14="Option 1 — Same Month Only",'🔄 Topic Pool'!B7=$B$400,OR(AND('🔄 Topic Pool'!B7=$B$400,ROUND(('🔄 Topic Pool'!A7-1)/7,0)=$A$400),AND('🔄 Topic Pool'!B7=$B$400,ROUND(('🔄 Topic Pool'!A7-1)/7,0)=$A$400+1)))),'🔄 Topic Pool'!D7,"—") -> — | M81: =IF(AND('🔄 Topic Pool'!P7<>"✅ Done",'🔄 Topic Pool'!M7="✅ YES",NOT(A460=2),NOT(AND(A460=1,OR('🔄 Topic Pool'!P7="❌ Missed",'🔄 Topic Pool'!P7="🔄 Partial"))),IF($C$14="Option 1 — Same Month Only",'🔄 Topic Pool'!B7=$B$400,OR(AND('🔄 Topic Pool'!B7=$B$400,ROUND(('🔄 Topic Pool'!A7-1)/7,0)=$A$400),AND('🔄 Topic Pool'!B7=$B$400,ROUND(('🔄 Topic Pool'!A7-1)/7,0)=$A$400+1)))),'🔄 Topic Pool'!E7,"—") -> — | O81: =IF(AND('🔄 Topic Pool'!P7<>"✅ Done",'🔄 Topic Pool'!M7="✅ YES",NOT(A460=2),NOT(AND(A460=1,OR('🔄 Topic Pool'!P7="❌ Missed",'🔄 Topic Pool'!P7="🔄 Partial"))),IF($C$14="Option 1 — Same Month Only",'🔄 Topic Pool'!B7=$B$400,OR(AND('🔄 Topic Pool'!B7=$B$400,ROUND(('🔄 Topic Pool'!A7-1)/7,0)=$A$400),AND('🔄 Topic Pool'!B7=$B$400,ROUND(('🔄 Topic Pool'!A7-1)/7,0)=$A$400+1)))),'🔄 Topic Pool'!G7,"—") -> — | P81: =IF(AND('🔄 Topic Pool'!P7<>"✅ Done",'🔄 Topic Pool'!M7="✅ YES",NOT(A460=2),NOT(AND(A460=1,OR('🔄 Topic Pool'!P7="❌ Missed",'🔄 Topic Pool'!P7="🔄 Partial"))),IF($C$14="Option 1 — Same Month Only",'🔄 Topic Pool'!B7=$B$400,OR(AND('🔄 Topic Pool'!B7=$B$400,ROUND(('🔄 Topic Pool'!A7-1)/7,0)=$A$400),AND('🔄 Topic Pool'!B7=$B$400,ROUND(('🔄 Topic Pool'!A7-1)/7,0)=$A$400+1)))),'🔄 Topic Pool'!J7,"—") -> — | R81: =IF(AND('🔄 Topic Pool'!P7<>"✅ Done",'🔄 Topic Pool'!M7="✅ YES",NOT(A460=2),NOT(AND(A460=1,OR('🔄 Topic Pool'!P7="❌ Missed",'🔄 Topic Pool'!P7="🔄 Partial"))),IF($C$14="Option 1 — Same Month Only",'🔄 Topic Pool'!B7=$B$400,OR(AND('🔄 Topic Pool'!B7=$B$400,ROUND(('🔄 Topic Pool'!A7-1)/7,0)=$A$400),AND('🔄 Topic Pool'!B7=$B$400,ROUND(('🔄 Topic Pool'!A7-1)/7,0)=$A$400+1)))),COUNTIF('📋 Swap History'!$F$4:$F$200,'🔄 Topic Pool'!D7),"—") -> — | S81: =IF(NOT(AND('🔄 Topic Pool'!P7<>"✅ Done",'🔄 Topic Pool'!M7="✅ YES",NOT(A460=2),NOT(AND(A460=1,OR('🔄 Topic Pool'!P7="❌ Missed",'🔄 Topic Pool'!P7="🔄 Partial"))),IF($C$14="Option 1 — Same Month Only",'🔄 Topic Pool'!B7=$B$400,OR(AND('🔄 Topic Pool'!B7=$B$400,ROUND(('🔄 Topic Pool'!A7-1)/7,0)=$A$400),AND('🔄 Topic Pool'!B7=$B$400,ROUND(('🔄 Topic Pool'!A7-1)/7,0)=$A$400+1))))),"🔒",IF('🔄 Topic Pool'!M7="🔒 NO","🔒",IF(COUNTIF('📋 Swap History'!$F$4:$F$200,'🔄 Topic Pool'!D7)>=$C$8,"🔒","✅"))) -> 🔒 | U81: =IF(AND('🔄 Topic Pool'!P7<>"✅ Done",'🔄 Topic Pool'!M7="✅ YES",NOT(A460=2),NOT(AND(A460=1,OR('🔄 Topic Pool'!P7="❌ Missed",'🔄 Topic Pool'!P7="🔄 Partial"))),IF($C$14="Option 1 — Same Month Only",'🔄 Topic Pool'!B7=$B$400,OR(AND('🔄 Topic Pool'!B7=$B$400,ROUND(('🔄 Topic Pool'!A7-1)/7,0)=$A$400),AND('🔄 Topic Pool'!B7=$B$400,ROUND(('🔄 Topic Pool'!A7-1)/7,0)=$A$400+1)))),'🔄 Topic Pool'!J7&" — Seq "&'🔄 Topic Pool'!C7&" in month","—") -> —
B82: =IF(AND('🔄 Topic Pool'!P9<>"✅ Done",'🔄 Topic Pool'!M9="✅ YES",NOT(A460=2),NOT(AND(A460=1,OR('🔄 Topic Pool'!P9="❌ Missed",'🔄 Topic Pool'!P9="🔄 Partial"))),IF($C$14="Option 1 — Same Month Only",'🔄 Topic Pool'!B9=$B$400,OR(AND('🔄 Topic Pool'!B9=$B$400,ROUND(('🔄 Topic Pool'!A9-1)/7,0)=$A$400),AND('🔄 Topic Pool'!B9=$B$400,ROUND(('🔄 Topic Pool'!A9-1)/7,0)=$A$400+1)))),'🔄 Topic Pool'!A9,"—") -> — | C82: =IF(AND('🔄 Topic Pool'!P9<>"✅ Done",'🔄 Topic Pool'!M9="✅ YES",NOT(A460=2),NOT(AND(A460=1,OR('🔄 Topic Pool'!P9="❌ Missed",'🔄 Topic Pool'!P9="🔄 Partial"))),IF($C$14="Option 1 — Same Month Only",'🔄 Topic Pool'!B9=$B$400,OR(AND('🔄 Topic Pool'!B9=$B$400,ROUND(('🔄 Topic Pool'!A9-1)/7,0)=$A$400),AND('🔄 Topic Pool'!B9=$B$400,ROUND(('🔄 Topic Pool'!A9-1)/7,0)=$A$400+1)))),'🔄 Topic Pool'!D9,"—") -> — | M82: =IF(AND('🔄 Topic Pool'!P9<>"✅ Done",'🔄 Topic Pool'!M9="✅ YES",NOT(A460=2),NOT(AND(A460=1,OR('🔄 Topic Pool'!P9="❌ Missed",'🔄 Topic Pool'!P9="🔄 Partial"))),IF($C$14="Option 1 — Same Month Only",'🔄 Topic Pool'!B9=$B$400,OR(AND('🔄 Topic Pool'!B9=$B$400,ROUND(('🔄 Topic Pool'!A9-1)/7,0)=$A$400),AND('🔄 Topic Pool'!B9=$B$400,ROUND(('🔄 Topic Pool'!A9-1)/7,0)=$A$400+1)))),'🔄 Topic Pool'!E9,"—") -> — | O82: =IF(AND('🔄 Topic Pool'!P9<>"✅ Done",'🔄 Topic Pool'!M9="✅ YES",NOT(A460=2),NOT(AND(A460=1,OR('🔄 Topic Pool'!P9="❌ Missed",'🔄 Topic Pool'!P9="🔄 Partial"))),IF($C$14="Option 1 — Same Month Only",'🔄 Topic Pool'!B9=$B$400,OR(AND('🔄 Topic Pool'!B9=$B$400,ROUND(('🔄 Topic Pool'!A9-1)/7,0)=$A$400),AND('🔄 Topic Pool'!B9=$B$400,ROUND(('🔄 Topic Pool'!A9-1)/7,0)=$A$400+1)))),'🔄 Topic Pool'!G9,"—") -> — | P82: =IF(AND('🔄 Topic Pool'!P9<>"✅ Done",'🔄 Topic Pool'!M9="✅ YES",NOT(A460=2),NOT(AND(A460=1,OR('🔄 Topic Pool'!P9="❌ Missed",'🔄 Topic Pool'!P9="🔄 Partial"))),IF($C$14="Option 1 — Same Month Only",'🔄 Topic Pool'!B9=$B$400,OR(AND('🔄 Topic Pool'!B9=$B$400,ROUND(('🔄 Topic Pool'!A9-1)/7,0)=$A$400),AND('🔄 Topic Pool'!B9=$B$400,ROUND(('🔄 Topic Pool'!A9-1)/7,0)=$A$400+1)))),'🔄 Topic Pool'!J9,"—") -> — | R82: =IF(AND('🔄 Topic Pool'!P9<>"✅ Done",'🔄 Topic Pool'!M9="✅ YES",NOT(A460=2),NOT(AND(A460=1,OR('🔄 Topic Pool'!P9="❌ Missed",'🔄 Topic Pool'!P9="🔄 Partial"))),IF($C$14="Option 1 — Same Month Only",'🔄 Topic Pool'!B9=$B$400,OR(AND('🔄 Topic Pool'!B9=$B$400,ROUND(('🔄 Topic Pool'!A9-1)/7,0)=$A$400),AND('🔄 Topic Pool'!B9=$B$400,ROUND(('🔄 Topic Pool'!A9-1)/7,0)=$A$400+1)))),COUNTIF('📋 Swap History'!$F$4:$F$200,'🔄 Topic Pool'!D9),"—") -> — | S82: =IF(NOT(AND('🔄 Topic Pool'!P9<>"✅ Done",'🔄 Topic Pool'!M9="✅ YES",NOT(A460=2),NOT(AND(A460=1,OR('🔄 Topic Pool'!P9="❌ Missed",'🔄 Topic Pool'!P9="🔄 Partial"))),IF($C$14="Option 1 — Same Month Only",'🔄 Topic Pool'!B9=$B$400,OR(AND('🔄 Topic Pool'!B9=$B$400,ROUND(('🔄 Topic Pool'!A9-1)/7,0)=$A$400),AND('🔄 Topic Pool'!B9=$B$400,ROUND(('🔄 Topic Pool'!A9-1)/7,0)=$A$400+1))))),"🔒",IF('🔄 Topic Pool'!M9="🔒 NO","🔒",IF(COUNTIF('📋 Swap History'!$F$4:$F$200,'🔄 Topic Pool'!D9)>=$C$8,"🔒","✅"))) -> 🔒 | U82: =IF(AND('🔄 Topic Pool'!P9<>"✅ Done",'🔄 Topic Pool'!M9="✅ YES",NOT(A460=2),NOT(AND(A460=1,OR('🔄 Topic Pool'!P9="❌ Missed",'🔄 Topic Pool'!P9="🔄 Partial"))),IF($C$14="Option 1 — Same Month Only",'🔄 Topic Pool'!B9=$B$400,OR(AND('🔄 Topic Pool'!B9=$B$400,ROUND(('🔄 Topic Pool'!A9-1)/7,0)=$A$400),AND('🔄 Topic Pool'!B9=$B$400,ROUND(('🔄 Topic Pool'!A9-1)/7,0)=$A$400+1)))),'🔄 Topic Pool'!J9&" — Seq "&'🔄 Topic Pool'!C9&" in month","—") -> —
B83: =IF(AND('🔄 Topic Pool'!P11<>"✅ Done",'🔄 Topic Pool'!M11="✅ YES",NOT(A460=2),NOT(AND(A460=1,OR('🔄 Topic Pool'!P11="❌ Missed",'🔄 Topic Pool'!P11="🔄 Partial"))),IF($C$14="Option 1 — Same Month Only",'🔄 Topic Pool'!B11=$B$400,OR(AND('🔄 Topic Pool'!B11=$B$400,ROUND(('🔄 Topic Pool'!A11-1)/7,0)=$A$400),AND('🔄 Topic Pool'!B11=$B$400,ROUND(('🔄 Topic Pool'!A11-1)/7,0)=$A$400+1)))),'🔄 Topic Pool'!A11,"—") -> — | C83: =IF(AND('🔄 Topic Pool'!P11<>"✅ Done",'🔄 Topic Pool'!M11="✅ YES",NOT(A460=2),NOT(AND(A460=1,OR('🔄 Topic Pool'!P11="❌ Missed",'🔄 Topic Pool'!P11="🔄 Partial"))),IF($C$14="Option 1 — Same Month Only",'🔄 Topic Pool'!B11=$B$400,OR(AND('🔄 Topic Pool'!B11=$B$400,ROUND(('🔄 Topic Pool'!A11-1)/7,0)=$A$400),AND('🔄 Topic Pool'!B11=$B$400,ROUND(('🔄 Topic Pool'!A11-1)/7,0)=$A$400+1)))),'🔄 Topic Pool'!D11,"—") -> — | M83: =IF(AND('🔄 Topic Pool'!P11<>"✅ Done",'🔄 Topic Pool'!M11="✅ YES",NOT(A460=2),NOT(AND(A460=1,OR('🔄 Topic Pool'!P11="❌ Missed",'🔄 Topic Pool'!P11="🔄 Partial"))),IF($C$14="Option 1 — Same Month Only",'🔄 Topic Pool'!B11=$B$400,OR(AND('🔄 Topic Pool'!B11=$B$400,ROUND(('🔄 Topic Pool'!A11-1)/7,0)=$A$400),AND('🔄 Topic Pool'!B11=$B$400,ROUND(('🔄 Topic Pool'!A11-1)/7,0)=$A$400+1)))),'🔄 Topic Pool'!E11,"—") -> — | O83: =IF(AND('🔄 Topic Pool'!P11<>"✅ Done",'🔄 Topic Pool'!M11="✅ YES",NOT(A460=2),NOT(AND(A460=1,OR('🔄 Topic Pool'!P11="❌ Missed",'🔄 Topic Pool'!P11="🔄 Partial"))),IF($C$14="Option 1 — Same Month Only",'🔄 Topic Pool'!B11=$B$400,OR(AND('🔄 Topic Pool'!B11=$B$400,ROUND(('🔄 Topic Pool'!A11-1)/7,0)=$A$400),AND('🔄 Topic Pool'!B11=$B$400,ROUND(('🔄 Topic Pool'!A11-1)/7,0)=$A$400+1)))),'🔄 Topic Pool'!G11,"—") -> — | P83: =IF(AND('🔄 Topic Pool'!P11<>"✅ Done",'🔄 Topic Pool'!M11="✅ YES",NOT(A460=2),NOT(AND(A460=1,OR('🔄 Topic Pool'!P11="❌ Missed",'🔄 Topic Pool'!P11="🔄 Partial"))),IF($C$14="Option 1 — Same Month Only",'🔄 Topic Pool'!B11=$B$400,OR(AND('🔄 Topic Pool'!B11=$B$400,ROUND(('🔄 Topic Pool'!A11-1)/7,0)=$A$400),AND('🔄 Topic Pool'!B11=$B$400,ROUND(('🔄 Topic Pool'!A11-1)/7,0)=$A$400+1)))),'🔄 Topic Pool'!J11,"—") -> — | R83: =IF(AND('🔄 Topic Pool'!P11<>"✅ Done",'🔄 Topic Pool'!M11="✅ YES",NOT(A460=2),NOT(AND(A460=1,OR('🔄 Topic Pool'!P11="❌ Missed",'🔄 Topic Pool'!P11="🔄 Partial"))),IF($C$14="Option 1 — Same Month Only",'🔄 Topic Pool'!B11=$B$400,OR(AND('🔄 Topic Pool'!B11=$B$400,ROUND(('🔄 Topic Pool'!A11-1)/7,0)=$A$400),AND('🔄 Topic Pool'!B11=$B$400,ROUND(('🔄 Topic Pool'!A11-1)/7,0)=$A$400+1)))),COUNTIF('📋 Swap History'!$F$4:$F$200,'🔄 Topic Pool'!D11),"—") -> — | S83: =IF(NOT(AND('🔄 Topic Pool'!P11<>"✅ Done",'🔄 Topic Pool'!M11="✅ YES",NOT(A460=2),NOT(AND(A460=1,OR('🔄 Topic Pool'!P11="❌ Missed",'🔄 Topic Pool'!P11="🔄 Partial"))),IF($C$14="Option 1 — Same Month Only",'🔄 Topic Pool'!B11=$B$400,OR(AND('🔄 Topic Pool'!B11=$B$400,ROUND(('🔄 Topic Pool'!A11-1)/7,0)=$A$400),AND('🔄 Topic Pool'!B11=$B$400,ROUND(('🔄 Topic Pool'!A11-1)/7,0)=$A$400+1))))),"🔒",IF('🔄 Topic Pool'!M11="🔒 NO","🔒",IF(COUNTIF('📋 Swap History'!$F$4:$F$200,'🔄 Topic Pool'!D11)>=$C$8,"🔒","✅"))) -> 🔒 | U83: =IF(AND('🔄 Topic Pool'!P11<>"✅ Done",'🔄 Topic Pool'!M11="✅ YES",NOT(A460=2),NOT(AND(A460=1,OR('🔄 Topic Pool'!P11="❌ Missed",'🔄 Topic Pool'!P11="🔄 Partial"))),IF($C$14="Option 1 — Same Month Only",'🔄 Topic Pool'!B11=$B$400,OR(AND('🔄 Topic Pool'!B11=$B$400,ROUND(('🔄 Topic Pool'!A11-1)/7,0)=$A$400),AND('🔄 Topic Pool'!B11=$B$400,ROUND(('🔄 Topic Pool'!A11-1)/7,0)=$A$400+1)))),'🔄 Topic Pool'!J11&" — Seq "&'🔄 Topic Pool'!C11&" in month","—") -> —
B84: =IF(AND('🔄 Topic Pool'!P12<>"✅ Done",'🔄 Topic Pool'!M12="✅ YES",NOT(A460=2),NOT(AND(A460=1,OR('🔄 Topic Pool'!P12="❌ Missed",'🔄 Topic Pool'!P12="🔄 Partial"))),IF($C$14="Option 1 — Same Month Only",'🔄 Topic Pool'!B12=$B$400,OR(AND('🔄 Topic Pool'!B12=$B$400,ROUND(('🔄 Topic Pool'!A12-1)/7,0)=$A$400),AND('🔄 Topic Pool'!B12=$B$400,ROUND(('🔄 Topic Pool'!A12-1)/7,0)=$A$400+1)))),'🔄 Topic Pool'!A12,"—") -> — | C84: =IF(AND('🔄 Topic Pool'!P12<>"✅ Done",'🔄 Topic Pool'!M12="✅ YES",NOT(A460=2),NOT(AND(A460=1,OR('🔄 Topic Pool'!P12="❌ Missed",'🔄 Topic Pool'!P12="🔄 Partial"))),IF($C$14="Option 1 — Same Month Only",'🔄 Topic Pool'!B12=$B$400,OR(AND('🔄 Topic Pool'!B12=$B$400,ROUND(('🔄 Topic Pool'!A12-1)/7,0)=$A$400),AND('🔄 Topic Pool'!B12=$B$400,ROUND(('🔄 Topic Pool'!A12-1)/7,0)=$A$400+1)))),'🔄 Topic Pool'!D12,"—") -> — | M84: =IF(AND('🔄 Topic Pool'!P12<>"✅ Done",'🔄 Topic Pool'!M12="✅ YES",NOT(A460=2),NOT(AND(A460=1,OR('🔄 Topic Pool'!P12="❌ Missed",'🔄 Topic Pool'!P12="🔄 Partial"))),IF($C$14="Option 1 — Same Month Only",'🔄 Topic Pool'!B12=$B$400,OR(AND('🔄 Topic Pool'!B12=$B$400,ROUND(('🔄 Topic Pool'!A12-1)/7,0)=$A$400),AND('🔄 Topic Pool'!B12=$B$400,ROUND(('🔄 Topic Pool'!A12-1)/7,0)=$A$400+1)))),'🔄 Topic Pool'!E12,"—") -> — | O84: =IF(AND('🔄 Topic Pool'!P12<>"✅ Done",'🔄 Topic Pool'!M12="✅ YES",NOT(A460=2),NOT(AND(A460=1,OR('🔄 Topic Pool'!P12="❌ Missed",'🔄 Topic Pool'!P12="🔄 Partial"))),IF($C$14="Option 1 — Same Month Only",'🔄 Topic Pool'!B12=$B$400,OR(AND('🔄 Topic Pool'!B12=$B$400,ROUND(('🔄 Topic Pool'!A12-1)/7,0)=$A$400),AND('🔄 Topic Pool'!B12=$B$400,ROUND(('🔄 Topic Pool'!A12-1)/7,0)=$A$400+1)))),'🔄 Topic Pool'!G12,"—") -> — | P84: =IF(AND('🔄 Topic Pool'!P12<>"✅ Done",'🔄 Topic Pool'!M12="✅ YES",NOT(A460=2),NOT(AND(A460=1,OR('🔄 Topic Pool'!P12="❌ Missed",'🔄 Topic Pool'!P12="🔄 Partial"))),IF($C$14="Option 1 — Same Month Only",'🔄 Topic Pool'!B12=$B$400,OR(AND('🔄 Topic Pool'!B12=$B$400,ROUND(('🔄 Topic Pool'!A12-1)/7,0)=$A$400),AND('🔄 Topic Pool'!B12=$B$400,ROUND(('🔄 Topic Pool'!A12-1)/7,0)=$A$400+1)))),'🔄 Topic Pool'!J12,"—") -> — | R84: =IF(AND('🔄 Topic Pool'!P12<>"✅ Done",'🔄 Topic Pool'!M12="✅ YES",NOT(A460=2),NOT(AND(A460=1,OR('🔄 Topic Pool'!P12="❌ Missed",'🔄 Topic Pool'!P12="🔄 Partial"))),IF($C$14="Option 1 — Same Month Only",'🔄 Topic Pool'!B12=$B$400,OR(AND('🔄 Topic Pool'!B12=$B$400,ROUND(('🔄 Topic Pool'!A12-1)/7,0)=$A$400),AND('🔄 Topic Pool'!B12=$B$400,ROUND(('🔄 Topic Pool'!A12-1)/7,0)=$A$400+1)))),COUNTIF('📋 Swap History'!$F$4:$F$200,'🔄 Topic Pool'!D12),"—") -> — | S84: =IF(NOT(AND('🔄 Topic Pool'!P12<>"✅ Done",'🔄 Topic Pool'!M12="✅ YES",NOT(A460=2),NOT(AND(A460=1,OR('🔄 Topic Pool'!P12="❌ Missed",'🔄 Topic Pool'!P12="🔄 Partial"))),IF($C$14="Option 1 — Same Month Only",'🔄 Topic Pool'!B12=$B$400,OR(AND('🔄 Topic Pool'!B12=$B$400,ROUND(('🔄 Topic Pool'!A12-1)/7,0)=$A$400),AND('🔄 Topic Pool'!B12=$B$400,ROUND(('🔄 Topic Pool'!A12-1)/7,0)=$A$400+1))))),"🔒",IF('🔄 Topic Pool'!M12="🔒 NO","🔒",IF(COUNTIF('📋 Swap History'!$F$4:$F$200,'🔄 Topic Pool'!D12)>=$C$8,"🔒","✅"))) -> 🔒 | U84: =IF(AND('🔄 Topic Pool'!P12<>"✅ Done",'🔄 Topic Pool'!M12="✅ YES",NOT(A460=2),NOT(AND(A460=1,OR('🔄 Topic Pool'!P12="❌ Missed",'🔄 Topic Pool'!P12="🔄 Partial"))),IF($C$14="Option 1 — Same Month Only",'🔄 Topic Pool'!B12=$B$400,OR(AND('🔄 Topic Pool'!B12=$B$400,ROUND(('🔄 Topic Pool'!A12-1)/7,0)=$A$400),AND('🔄 Topic Pool'!B12=$B$400,ROUND(('🔄 Topic Pool'!A12-1)/7,0)=$A$400+1)))),'🔄 Topic Pool'!J12&" — Seq "&'🔄 Topic Pool'!C12&" in month","—") -> —
B85: =IF(AND('🔄 Topic Pool'!P13<>"✅ Done",'🔄 Topic Pool'!M13="✅ YES",NOT(A460=2),NOT(AND(A460=1,OR('🔄 Topic Pool'!P13="❌ Missed",'🔄 Topic Pool'!P13="🔄 Partial"))),IF($C$14="Option 1 — Same Month Only",'🔄 Topic Pool'!B13=$B$400,OR(AND('🔄 Topic Pool'!B13=$B$400,ROUND(('🔄 Topic Pool'!A13-1)/7,0)=$A$400),AND('🔄 Topic Pool'!B13=$B$400,ROUND(('🔄 Topic Pool'!A13-1)/7,0)=$A$400+1)))),'🔄 Topic Pool'!A13,"—") -> — | C85: =IF(AND('🔄 Topic Pool'!P13<>"✅ Done",'🔄 Topic Pool'!M13="✅ YES",NOT(A460=2),NOT(AND(A460=1,OR('🔄 Topic Pool'!P13="❌ Missed",'🔄 Topic Pool'!P13="🔄 Partial"))),IF($C$14="Option 1 — Same Month Only",'🔄 Topic Pool'!B13=$B$400,OR(AND('🔄 Topic Pool'!B13=$B$400,ROUND(('🔄 Topic Pool'!A13-1)/7,0)=$A$400),AND('🔄 Topic Pool'!B13=$B$400,ROUND(('🔄 Topic Pool'!A13-1)/7,0)=$A$400+1)))),'🔄 Topic Pool'!D13,"—") -> — | M85: =IF(AND('🔄 Topic Pool'!P13<>"✅ Done",'🔄 Topic Pool'!M13="✅ YES",NOT(A460=2),NOT(AND(A460=1,OR('🔄 Topic Pool'!P13="❌ Missed",'🔄 Topic Pool'!P13="🔄 Partial"))),IF($C$14="Option 1 — Same Month Only",'🔄 Topic Pool'!B13=$B$400,OR(AND('🔄 Topic Pool'!B13=$B$400,ROUND(('🔄 Topic Pool'!A13-1)/7,0)=$A$400),AND('🔄 Topic Pool'!B13=$B$400,ROUND(('🔄 Topic Pool'!A13-1)/7,0)=$A$400+1)))),'🔄 Topic Pool'!E13,"—") -> — | O85: =IF(AND('🔄 Topic Pool'!P13<>"✅ Done",'🔄 Topic Pool'!M13="✅ YES",NOT(A460=2),NOT(AND(A460=1,OR('🔄 Topic Pool'!P13="❌ Missed",'🔄 Topic Pool'!P13="🔄 Partial"))),IF($C$14="Option 1 — Same Month Only",'🔄 Topic Pool'!B13=$B$400,OR(AND('🔄 Topic Pool'!B13=$B$400,ROUND(('🔄 Topic Pool'!A13-1)/7,0)=$A$400),AND('🔄 Topic Pool'!B13=$B$400,ROUND(('🔄 Topic Pool'!A13-1)/7,0)=$A$400+1)))),'🔄 Topic Pool'!G13,"—") -> — | P85: =IF(AND('🔄 Topic Pool'!P13<>"✅ Done",'🔄 Topic Pool'!M13="✅ YES",NOT(A460=2),NOT(AND(A460=1,OR('🔄 Topic Pool'!P13="❌ Missed",'🔄 Topic Pool'!P13="🔄 Partial"))),IF($C$14="Option 1 — Same Month Only",'🔄 Topic Pool'!B13=$B$400,OR(AND('🔄 Topic Pool'!B13=$B$400,ROUND(('🔄 Topic Pool'!A13-1)/7,0)=$A$400),AND('🔄 Topic Pool'!B13=$B$400,ROUND(('🔄 Topic Pool'!A13-1)/7,0)=$A$400+1)))),'🔄 Topic Pool'!J13,"—") -> — | R85: =IF(AND('🔄 Topic Pool'!P13<>"✅ Done",'🔄 Topic Pool'!M13="✅ YES",NOT(A460=2),NOT(AND(A460=1,OR('🔄 Topic Pool'!P13="❌ Missed",'🔄 Topic Pool'!P13="🔄 Partial"))),IF($C$14="Option 1 — Same Month Only",'🔄 Topic Pool'!B13=$B$400,OR(AND('🔄 Topic Pool'!B13=$B$400,ROUND(('🔄 Topic Pool'!A13-1)/7,0)=$A$400),AND('🔄 Topic Pool'!B13=$B$400,ROUND(('🔄 Topic Pool'!A13-1)/7,0)=$A$400+1)))),COUNTIF('📋 Swap History'!$F$4:$F$200,'🔄 Topic Pool'!D13),"—") -> — | S85: =IF(NOT(AND('🔄 Topic Pool'!P13<>"✅ Done",'🔄 Topic Pool'!M13="✅ YES",NOT(A460=2),NOT(AND(A460=1,OR('🔄 Topic Pool'!P13="❌ Missed",'🔄 Topic Pool'!P13="🔄 Partial"))),IF($C$14="Option 1 — Same Month Only",'🔄 Topic Pool'!B13=$B$400,OR(AND('🔄 Topic Pool'!B13=$B$400,ROUND(('🔄 Topic Pool'!A13-1)/7,0)=$A$400),AND('🔄 Topic Pool'!B13=$B$400,ROUND(('🔄 Topic Pool'!A13-1)/7,0)=$A$400+1))))),"🔒",IF('🔄 Topic Pool'!M13="🔒 NO","🔒",IF(COUNTIF('📋 Swap History'!$F$4:$F$200,'🔄 Topic Pool'!D13)>=$C$8,"🔒","✅"))) -> 🔒 | U85: =IF(AND('🔄 Topic Pool'!P13<>"✅ Done",'🔄 Topic Pool'!M13="✅ YES",NOT(A460=2),NOT(AND(A460=1,OR('🔄 Topic Pool'!P13="❌ Missed",'🔄 Topic Pool'!P13="🔄 Partial"))),IF($C$14="Option 1 — Same Month Only",'🔄 Topic Pool'!B13=$B$400,OR(AND('🔄 Topic Pool'!B13=$B$400,ROUND(('🔄 Topic Pool'!A13-1)/7,0)=$A$400),AND('🔄 Topic Pool'!B13=$B$400,ROUND(('🔄 Topic Pool'!A13-1)/7,0)=$A$400+1)))),'🔄 Topic Pool'!J13&" — Seq "&'🔄 Topic Pool'!C13&" in month","—") -> —
B86: =IF(AND('🔄 Topic Pool'!P14<>"✅ Done",'🔄 Topic Pool'!M14="✅ YES",NOT(A460=2),NOT(AND(A460=1,OR('🔄 Topic Pool'!P14="❌ Missed",'🔄 Topic Pool'!P14="🔄 Partial"))),IF($C$14="Option 1 — Same Month Only",'🔄 Topic Pool'!B14=$B$400,OR(AND('🔄 Topic Pool'!B14=$B$400,ROUND(('🔄 Topic Pool'!A14-1)/7,0)=$A$400),AND('🔄 Topic Pool'!B14=$B$400,ROUND(('🔄 Topic Pool'!A14-1)/7,0)=$A$400+1)))),'🔄 Topic Pool'!A14,"—") -> — | C86: =IF(AND('🔄 Topic Pool'!P14<>"✅ Done",'🔄 Topic Pool'!M14="✅ YES",NOT(A460=2),NOT(AND(A460=1,OR('🔄 Topic Pool'!P14="❌ Missed",'🔄 Topic Pool'!P14="🔄 Partial"))),IF($C$14="Option 1 — Same Month Only",'🔄 Topic Pool'!B14=$B$400,OR(AND('🔄 Topic Pool'!B14=$B$400,ROUND(('🔄 Topic Pool'!A14-1)/7,0)=$A$400),AND('🔄 Topic Pool'!B14=$B$400,ROUND(('🔄 Topic Pool'!A14-1)/7,0)=$A$400+1)))),'🔄 Topic Pool'!D14,"—") -> — | M86: =IF(AND('🔄 Topic Pool'!P14<>"✅ Done",'🔄 Topic Pool'!M14="✅ YES",NOT(A460=2),NOT(AND(A460=1,OR('🔄 Topic Pool'!P14="❌ Missed",'🔄 Topic Pool'!P14="🔄 Partial"))),IF($C$14="Option 1 — Same Month Only",'🔄 Topic Pool'!B14=$B$400,OR(AND('🔄 Topic Pool'!B14=$B$400,ROUND(('🔄 Topic Pool'!A14-1)/7,0)=$A$400),AND('🔄 Topic Pool'!B14=$B$400,ROUND(('🔄 Topic Pool'!A14-1)/7,0)=$A$400+1)))),'🔄 Topic Pool'!E14,"—") -> — | O86: =IF(AND('🔄 Topic Pool'!P14<>"✅ Done",'🔄 Topic Pool'!M14="✅ YES",NOT(A460=2),NOT(AND(A460=1,OR('🔄 Topic Pool'!P14="❌ Missed",'🔄 Topic Pool'!P14="🔄 Partial"))),IF($C$14="Option 1 — Same Month Only",'🔄 Topic Pool'!B14=$B$400,OR(AND('🔄 Topic Pool'!B14=$B$400,ROUND(('🔄 Topic Pool'!A14-1)/7,0)=$A$400),AND('🔄 Topic Pool'!B14=$B$400,ROUND(('🔄 Topic Pool'!A14-1)/7,0)=$A$400+1)))),'🔄 Topic Pool'!G14,"—") -> — | P86: =IF(AND('🔄 Topic Pool'!P14<>"✅ Done",'🔄 Topic Pool'!M14="✅ YES",NOT(A460=2),NOT(AND(A460=1,OR('🔄 Topic Pool'!P14="❌ Missed",'🔄 Topic Pool'!P14="🔄 Partial"))),IF($C$14="Option 1 — Same Month Only",'🔄 Topic Pool'!B14=$B$400,OR(AND('🔄 Topic Pool'!B14=$B$400,ROUND(('🔄 Topic Pool'!A14-1)/7,0)=$A$400),AND('🔄 Topic Pool'!B14=$B$400,ROUND(('🔄 Topic Pool'!A14-1)/7,0)=$A$400+1)))),'🔄 Topic Pool'!J14,"—") -> — | R86: =IF(AND('🔄 Topic Pool'!P14<>"✅ Done",'🔄 Topic Pool'!M14="✅ YES",NOT(A460=2),NOT(AND(A460=1,OR('🔄 Topic Pool'!P14="❌ Missed",'🔄 Topic Pool'!P14="🔄 Partial"))),IF($C$14="Option 1 — Same Month Only",'🔄 Topic Pool'!B14=$B$400,OR(AND('🔄 Topic Pool'!B14=$B$400,ROUND(('🔄 Topic Pool'!A14-1)/7,0)=$A$400),AND('🔄 Topic Pool'!B14=$B$400,ROUND(('🔄 Topic Pool'!A14-1)/7,0)=$A$400+1)))),COUNTIF('📋 Swap History'!$F$4:$F$200,'🔄 Topic Pool'!D14),"—") -> — | S86: =IF(NOT(AND('🔄 Topic Pool'!P14<>"✅ Done",'🔄 Topic Pool'!M14="✅ YES",NOT(A460=2),NOT(AND(A460=1,OR('🔄 Topic Pool'!P14="❌ Missed",'🔄 Topic Pool'!P14="🔄 Partial"))),IF($C$14="Option 1 — Same Month Only",'🔄 Topic Pool'!B14=$B$400,OR(AND('🔄 Topic Pool'!B14=$B$400,ROUND(('🔄 Topic Pool'!A14-1)/7,0)=$A$400),AND('🔄 Topic Pool'!B14=$B$400,ROUND(('🔄 Topic Pool'!A14-1)/7,0)=$A$400+1))))),"🔒",IF('🔄 Topic Pool'!M14="🔒 NO","🔒",IF(COUNTIF('📋 Swap History'!$F$4:$F$200,'🔄 Topic Pool'!D14)>=$C$8,"🔒","✅"))) -> 🔒 | U86: =IF(AND('🔄 Topic Pool'!P14<>"✅ Done",'🔄 Topic Pool'!M14="✅ YES",NOT(A460=2),NOT(AND(A460=1,OR('🔄 Topic Pool'!P14="❌ Missed",'🔄 Topic Pool'!P14="🔄 Partial"))),IF($C$14="Option 1 — Same Month Only",'🔄 Topic Pool'!B14=$B$400,OR(AND('🔄 Topic Pool'!B14=$B$400,ROUND(('🔄 Topic Pool'!A14-1)/7,0)=$A$400),AND('🔄 Topic Pool'!B14=$B$400,ROUND(('🔄 Topic Pool'!A14-1)/7,0)=$A$400+1)))),'🔄 Topic Pool'!J14&" — Seq "&'🔄 Topic Pool'!C14&" in month","—") -> —
B87: =IF(AND('🔄 Topic Pool'!P16<>"✅ Done",'🔄 Topic Pool'!M16="✅ YES",NOT(A460=2),NOT(AND(A460=1,OR('🔄 Topic Pool'!P16="❌ Missed",'🔄 Topic Pool'!P16="🔄 Partial"))),IF($C$14="Option 1 — Same Month Only",'🔄 Topic Pool'!B16=$B$400,OR(AND('🔄 Topic Pool'!B16=$B$400,ROUND(('🔄 Topic Pool'!A16-1)/7,0)=$A$400),AND('🔄 Topic Pool'!B16=$B$400,ROUND(('🔄 Topic Pool'!A16-1)/7,0)=$A$400+1)))),'🔄 Topic Pool'!A16,"—") -> — | C87: =IF(AND('🔄 Topic Pool'!P16<>"✅ Done",'🔄 Topic Pool'!M16="✅ YES",NOT(A460=2),NOT(AND(A460=1,OR('🔄 Topic Pool'!P16="❌ Missed",'🔄 Topic Pool'!P16="🔄 Partial"))),IF($C$14="Option 1 — Same Month Only",'🔄 Topic Pool'!B16=$B$400,OR(AND('🔄 Topic Pool'!B16=$B$400,ROUND(('🔄 Topic Pool'!A16-1)/7,0)=$A$400),AND('🔄 Topic Pool'!B16=$B$400,ROUND(('🔄 Topic Pool'!A16-1)/7,0)=$A$400+1)))),'🔄 Topic Pool'!D16,"—") -> — | M87: =IF(AND('🔄 Topic Pool'!P16<>"✅ Done",'🔄 Topic Pool'!M16="✅ YES",NOT(A460=2),NOT(AND(A460=1,OR('🔄 Topic Pool'!P16="❌ Missed",'🔄 Topic Pool'!P16="🔄 Partial"))),IF($C$14="Option 1 — Same Month Only",'🔄 Topic Pool'!B16=$B$400,OR(AND('🔄 Topic Pool'!B16=$B$400,ROUND(('🔄 Topic Pool'!A16-1)/7,0)=$A$400),AND('🔄 Topic Pool'!B16=$B$400,ROUND(('🔄 Topic Pool'!A16-1)/7,0)=$A$400+1)))),'🔄 Topic Pool'!E16,"—") -> — | O87: =IF(AND('🔄 Topic Pool'!P16<>"✅ Done",'🔄 Topic Pool'!M16="✅ YES",NOT(A460=2),NOT(AND(A460=1,OR('🔄 Topic Pool'!P16="❌ Missed",'🔄 Topic Pool'!P16="🔄 Partial"))),IF($C$14="Option 1 — Same Month Only",'🔄 Topic Pool'!B16=$B$400,OR(AND('🔄 Topic Pool'!B16=$B$400,ROUND(('🔄 Topic Pool'!A16-1)/7,0)=$A$400),AND('🔄 Topic Pool'!B16=$B$400,ROUND(('🔄 Topic Pool'!A16-1)/7,0)=$A$400+1)))),'🔄 Topic Pool'!G16,"—") -> — | P87: =IF(AND('🔄 Topic Pool'!P16<>"✅ Done",'🔄 Topic Pool'!M16="✅ YES",NOT(A460=2),NOT(AND(A460=1,OR('🔄 Topic Pool'!P16="❌ Missed",'🔄 Topic Pool'!P16="🔄 Partial"))),IF($C$14="Option 1 — Same Month Only",'🔄 Topic Pool'!B16=$B$400,OR(AND('🔄 Topic Pool'!B16=$B$400,ROUND(('🔄 Topic Pool'!A16-1)/7,0)=$A$400),AND('🔄 Topic Pool'!B16=$B$400,ROUND(('🔄 Topic Pool'!A16-1)/7,0)=$A$400+1)))),'🔄 Topic Pool'!J16,"—") -> — | R87: =IF(AND('🔄 Topic Pool'!P16<>"✅ Done",'🔄 Topic Pool'!M16="✅ YES",NOT(A460=2),NOT(AND(A460=1,OR('🔄 Topic Pool'!P16="❌ Missed",'🔄 Topic Pool'!P16="🔄 Partial"))),IF($C$14="Option 1 — Same Month Only",'🔄 Topic Pool'!B16=$B$400,OR(AND('🔄 Topic Pool'!B16=$B$400,ROUND(('🔄 Topic Pool'!A16-1)/7,0)=$A$400),AND('🔄 Topic Pool'!B16=$B$400,ROUND(('🔄 Topic Pool'!A16-1)/7,0)=$A$400+1)))),COUNTIF('📋 Swap History'!$F$4:$F$200,'🔄 Topic Pool'!D16),"—") -> — | S87: =IF(NOT(AND('🔄 Topic Pool'!P16<>"✅ Done",'🔄 Topic Pool'!M16="✅ YES",NOT(A460=2),NOT(AND(A460=1,OR('🔄 Topic Pool'!P16="❌ Missed",'🔄 Topic Pool'!P16="🔄 Partial"))),IF($C$14="Option 1 — Same Month Only",'🔄 Topic Pool'!B16=$B$400,OR(AND('🔄 Topic Pool'!B16=$B$400,ROUND(('🔄 Topic Pool'!A16-1)/7,0)=$A$400),AND('🔄 Topic Pool'!B16=$B$400,ROUND(('🔄 Topic Pool'!A16-1)/7,0)=$A$400+1))))),"🔒",IF('🔄 Topic Pool'!M16="🔒 NO","🔒",IF(COUNTIF('📋 Swap History'!$F$4:$F$200,'🔄 Topic Pool'!D16)>=$C$8,"🔒","✅"))) -> 🔒 | U87: =IF(AND('🔄 Topic Pool'!P16<>"✅ Done",'🔄 Topic Pool'!M16="✅ YES",NOT(A460=2),NOT(AND(A460=1,OR('🔄 Topic Pool'!P16="❌ Missed",'🔄 Topic Pool'!P16="🔄 Partial"))),IF($C$14="Option 1 — Same Month Only",'🔄 Topic Pool'!B16=$B$400,OR(AND('🔄 Topic Pool'!B16=$B$400,ROUND(('🔄 Topic Pool'!A16-1)/7,0)=$A$400),AND('🔄 Topic Pool'!B16=$B$400,ROUND(('🔄 Topic Pool'!A16-1)/7,0)=$A$400+1)))),'🔄 Topic Pool'!J16&" — Seq "&'🔄 Topic Pool'!C16&" in month","—") -> —
B88: =IF(AND('🔄 Topic Pool'!P18<>"✅ Done",'🔄 Topic Pool'!M18="✅ YES",NOT(A460=2),NOT(AND(A460=1,OR('🔄 Topic Pool'!P18="❌ Missed",'🔄 Topic Pool'!P18="🔄 Partial"))),IF($C$14="Option 1 — Same Month Only",'🔄 Topic Pool'!B18=$B$400,OR(AND('🔄 Topic Pool'!B18=$B$400,ROUND(('🔄 Topic Pool'!A18-1)/7,0)=$A$400),AND('🔄 Topic Pool'!B18=$B$400,ROUND(('🔄 Topic Pool'!A18-1)/7,0)=$A$400+1)))),'🔄 Topic Pool'!A18,"—") -> — | C88: =IF(AND('🔄 Topic Pool'!P18<>"✅ Done",'🔄 Topic Pool'!M18="✅ YES",NOT(A460=2),NOT(AND(A460=1,OR('🔄 Topic Pool'!P18="❌ Missed",'🔄 Topic Pool'!P18="🔄 Partial"))),IF($C$14="Option 1 — Same Month Only",'🔄 Topic Pool'!B18=$B$400,OR(AND('🔄 Topic Pool'!B18=$B$400,ROUND(('🔄 Topic Pool'!A18-1)/7,0)=$A$400),AND('🔄 Topic Pool'!B18=$B$400,ROUND(('🔄 Topic Pool'!A18-1)/7,0)=$A$400+1)))),'🔄 Topic Pool'!D18,"—") -> — | M88: =IF(AND('🔄 Topic Pool'!P18<>"✅ Done",'🔄 Topic Pool'!M18="✅ YES",NOT(A460=2),NOT(AND(A460=1,OR('🔄 Topic Pool'!P18="❌ Missed",'🔄 Topic Pool'!P18="🔄 Partial"))),IF($C$14="Option 1 — Same Month Only",'🔄 Topic Pool'!B18=$B$400,OR(AND('🔄 Topic Pool'!B18=$B$400,ROUND(('🔄 Topic Pool'!A18-1)/7,0)=$A$400),AND('🔄 Topic Pool'!B18=$B$400,ROUND(('🔄 Topic Pool'!A18-1)/7,0)=$A$400+1)))),'🔄 Topic Pool'!E18,"—") -> — | O88: =IF(AND('🔄 Topic Pool'!P18<>"✅ Done",'🔄 Topic Pool'!M18="✅ YES",NOT(A460=2),NOT(AND(A460=1,OR('🔄 Topic Pool'!P18="❌ Missed",'🔄 Topic Pool'!P18="🔄 Partial"))),IF($C$14="Option 1 — Same Month Only",'🔄 Topic Pool'!B18=$B$400,OR(AND('🔄 Topic Pool'!B18=$B$400,ROUND(('🔄 Topic Pool'!A18-1)/7,0)=$A$400),AND('🔄 Topic Pool'!B18=$B$400,ROUND(('🔄 Topic Pool'!A18-1)/7,0)=$A$400+1)))),'🔄 Topic Pool'!G18,"—") -> — | P88: =IF(AND('🔄 Topic Pool'!P18<>"✅ Done",'🔄 Topic Pool'!M18="✅ YES",NOT(A460=2),NOT(AND(A460=1,OR('🔄 Topic Pool'!P18="❌ Missed",'🔄 Topic Pool'!P18="🔄 Partial"))),IF($C$14="Option 1 — Same Month Only",'🔄 Topic Pool'!B18=$B$400,OR(AND('🔄 Topic Pool'!B18=$B$400,ROUND(('🔄 Topic Pool'!A18-1)/7,0)=$A$400),AND('🔄 Topic Pool'!B18=$B$400,ROUND(('🔄 Topic Pool'!A18-1)/7,0)=$A$400+1)))),'🔄 Topic Pool'!J18,"—") -> — | R88: =IF(AND('🔄 Topic Pool'!P18<>"✅ Done",'🔄 Topic Pool'!M18="✅ YES",NOT(A460=2),NOT(AND(A460=1,OR('🔄 Topic Pool'!P18="❌ Missed",'🔄 Topic Pool'!P18="🔄 Partial"))),IF($C$14="Option 1 — Same Month Only",'🔄 Topic Pool'!B18=$B$400,OR(AND('🔄 Topic Pool'!B18=$B$400,ROUND(('🔄 Topic Pool'!A18-1)/7,0)=$A$400),AND('🔄 Topic Pool'!B18=$B$400,ROUND(('🔄 Topic Pool'!A18-1)/7,0)=$A$400+1)))),COUNTIF('📋 Swap History'!$F$4:$F$200,'🔄 Topic Pool'!D18),"—") -> — | S88: =IF(NOT(AND('🔄 Topic Pool'!P18<>"✅ Done",'🔄 Topic Pool'!M18="✅ YES",NOT(A460=2),NOT(AND(A460=1,OR('🔄 Topic Pool'!P18="❌ Missed",'🔄 Topic Pool'!P18="🔄 Partial"))),IF($C$14="Option 1 — Same Month Only",'🔄 Topic Pool'!B18=$B$400,OR(AND('🔄 Topic Pool'!B18=$B$400,ROUND(('🔄 Topic Pool'!A18-1)/7,0)=$A$400),AND('🔄 Topic Pool'!B18=$B$400,ROUND(('🔄 Topic Pool'!A18-1)/7,0)=$A$400+1))))),"🔒",IF('🔄 Topic Pool'!M18="🔒 NO","🔒",IF(COUNTIF('📋 Swap History'!$F$4:$F$200,'🔄 Topic Pool'!D18)>=$C$8,"🔒","✅"))) -> 🔒 | U88: =IF(AND('🔄 Topic Pool'!P18<>"✅ Done",'🔄 Topic Pool'!M18="✅ YES",NOT(A460=2),NOT(AND(A460=1,OR('🔄 Topic Pool'!P18="❌ Missed",'🔄 Topic Pool'!P18="🔄 Partial"))),IF($C$14="Option 1 — Same Month Only",'🔄 Topic Pool'!B18=$B$400,OR(AND('🔄 Topic Pool'!B18=$B$400,ROUND(('🔄 Topic Pool'!A18-1)/7,0)=$A$400),AND('🔄 Topic Pool'!B18=$B$400,ROUND(('🔄 Topic Pool'!A18-1)/7,0)=$A$400+1)))),'🔄 Topic Pool'!J18&" — Seq "&'🔄 Topic Pool'!C18&" in month","—") -> —
B89: =IF(AND('🔄 Topic Pool'!P20<>"✅ Done",'🔄 Topic Pool'!M20="✅ YES",NOT(A460=2),NOT(AND(A460=1,OR('🔄 Topic Pool'!P20="❌ Missed",'🔄 Topic Pool'!P20="🔄 Partial"))),IF($C$14="Option 1 — Same Month Only",'🔄 Topic Pool'!B20=$B$400,OR(AND('🔄 Topic Pool'!B20=$B$400,ROUND(('🔄 Topic Pool'!A20-1)/7,0)=$A$400),AND('🔄 Topic Pool'!B20=$B$400,ROUND(('🔄 Topic Pool'!A20-1)/7,0)=$A$400+1)))),'🔄 Topic Pool'!A20,"—") -> — | C89: =IF(AND('🔄 Topic Pool'!P20<>"✅ Done",'🔄 Topic Pool'!M20="✅ YES",NOT(A460=2),NOT(AND(A460=1,OR('🔄 Topic Pool'!P20="❌ Missed",'🔄 Topic Pool'!P20="🔄 Partial"))),IF($C$14="Option 1 — Same Month Only",'🔄 Topic Pool'!B20=$B$400,OR(AND('🔄 Topic Pool'!B20=$B$400,ROUND(('🔄 Topic Pool'!A20-1)/7,0)=$A$400),AND('🔄 Topic Pool'!B20=$B$400,ROUND(('🔄 Topic Pool'!A20-1)/7,0)=$A$400+1)))),'🔄 Topic Pool'!D20,"—") -> — | M89: =IF(AND('🔄 Topic Pool'!P20<>"✅ Done",'🔄 Topic Pool'!M20="✅ YES",NOT(A460=2),NOT(AND(A460=1,OR('🔄 Topic Pool'!P20="❌ Missed",'🔄 Topic Pool'!P20="🔄 Partial"))),IF($C$14="Option 1 — Same Month Only",'🔄 Topic Pool'!B20=$B$400,OR(AND('🔄 Topic Pool'!B20=$B$400,ROUND(('🔄 Topic Pool'!A20-1)/7,0)=$A$400),AND('🔄 Topic Pool'!B20=$B$400,ROUND(('🔄 Topic Pool'!A20-1)/7,0)=$A$400+1)))),'🔄 Topic Pool'!E20,"—") -> — | O89: =IF(AND('🔄 Topic Pool'!P20<>"✅ Done",'🔄 Topic Pool'!M20="✅ YES",NOT(A460=2),NOT(AND(A460=1,OR('🔄 Topic Pool'!P20="❌ Missed",'🔄 Topic Pool'!P20="🔄 Partial"))),IF($C$14="Option 1 — Same Month Only",'🔄 Topic Pool'!B20=$B$400,OR(AND('🔄 Topic Pool'!B20=$B$400,ROUND(('🔄 Topic Pool'!A20-1)/7,0)=$A$400),AND('🔄 Topic Pool'!B20=$B$400,ROUND(('🔄 Topic Pool'!A20-1)/7,0)=$A$400+1)))),'🔄 Topic Pool'!G20,"—") -> — | P89: =IF(AND('🔄 Topic Pool'!P20<>"✅ Done",'🔄 Topic Pool'!M20="✅ YES",NOT(A460=2),NOT(AND(A460=1,OR('🔄 Topic Pool'!P20="❌ Missed",'🔄 Topic Pool'!P20="🔄 Partial"))),IF($C$14="Option 1 — Same Month Only",'🔄 Topic Pool'!B20=$B$400,OR(AND('🔄 Topic Pool'!B20=$B$400,ROUND(('🔄 Topic Pool'!A20-1)/7,0)=$A$400),AND('🔄 Topic Pool'!B20=$B$400,ROUND(('🔄 Topic Pool'!A20-1)/7,0)=$A$400+1)))),'🔄 Topic Pool'!J20,"—") -> — | R89: =IF(AND('🔄 Topic Pool'!P20<>"✅ Done",'🔄 Topic Pool'!M20="✅ YES",NOT(A460=2),NOT(AND(A460=1,OR('🔄 Topic Pool'!P20="❌ Missed",'🔄 Topic Pool'!P20="🔄 Partial"))),IF($C$14="Option 1 — Same Month Only",'🔄 Topic Pool'!B20=$B$400,OR(AND('🔄 Topic Pool'!B20=$B$400,ROUND(('🔄 Topic Pool'!A20-1)/7,0)=$A$400),AND('🔄 Topic Pool'!B20=$B$400,ROUND(('🔄 Topic Pool'!A20-1)/7,0)=$A$400+1)))),COUNTIF('📋 Swap History'!$F$4:$F$200,'🔄 Topic Pool'!D20),"—") -> — | S89: =IF(NOT(AND('🔄 Topic Pool'!P20<>"✅ Done",'🔄 Topic Pool'!M20="✅ YES",NOT(A460=2),NOT(AND(A460=1,OR('🔄 Topic Pool'!P20="❌ Missed",'🔄 Topic Pool'!P20="🔄 Partial"))),IF($C$14="Option 1 — Same Month Only",'🔄 Topic Pool'!B20=$B$400,OR(AND('🔄 Topic Pool'!B20=$B$400,ROUND(('🔄 Topic Pool'!A20-1)/7,0)=$A$400),AND('🔄 Topic Pool'!B20=$B$400,ROUND(('🔄 Topic Pool'!A20-1)/7,0)=$A$400+1))))),"🔒",IF('🔄 Topic Pool'!M20="🔒 NO","🔒",IF(COUNTIF('📋 Swap History'!$F$4:$F$200,'🔄 Topic Pool'!D20)>=$C$8,"🔒","✅"))) -> 🔒 | U89: =IF(AND('🔄 Topic Pool'!P20<>"✅ Done",'🔄 Topic Pool'!M20="✅ YES",NOT(A460=2),NOT(AND(A460=1,OR('🔄 Topic Pool'!P20="❌ Missed",'🔄 Topic Pool'!P20="🔄 Partial"))),IF($C$14="Option 1 — Same Month Only",'🔄 Topic Pool'!B20=$B$400,OR(AND('🔄 Topic Pool'!B20=$B$400,ROUND(('🔄 Topic Pool'!A20-1)/7,0)=$A$400),AND('🔄 Topic Pool'!B20=$B$400,ROUND(('🔄 Topic Pool'!A20-1)/7,0)=$A$400+1)))),'🔄 Topic Pool'!J20&" — Seq "&'🔄 Topic Pool'!C20&" in month","—") -> —
B90: =IF(AND('🔄 Topic Pool'!P21<>"✅ Done",'🔄 Topic Pool'!M21="✅ YES",NOT(A460=2),NOT(AND(A460=1,OR('🔄 Topic Pool'!P21="❌ Missed",'🔄 Topic Pool'!P21="🔄 Partial"))),IF($C$14="Option 1 — Same Month Only",'🔄 Topic Pool'!B21=$B$400,OR(AND('🔄 Topic Pool'!B21=$B$400,ROUND(('🔄 Topic Pool'!A21-1)/7,0)=$A$400),AND('🔄 Topic Pool'!B21=$B$400,ROUND(('🔄 Topic Pool'!A21-1)/7,0)=$A$400+1)))),'🔄 Topic Pool'!A21,"—") -> — | C90: =IF(AND('🔄 Topic Pool'!P21<>"✅ Done",'🔄 Topic Pool'!M21="✅ YES",NOT(A460=2),NOT(AND(A460=1,OR('🔄 Topic Pool'!P21="❌ Missed",'🔄 Topic Pool'!P21="🔄 Partial"))),IF($C$14="Option 1 — Same Month Only",'🔄 Topic Pool'!B21=$B$400,OR(AND('🔄 Topic Pool'!B21=$B$400,ROUND(('🔄 Topic Pool'!A21-1)/7,0)=$A$400),AND('🔄 Topic Pool'!B21=$B$400,ROUND(('🔄 Topic Pool'!A21-1)/7,0)=$A$400+1)))),'🔄 Topic Pool'!D21,"—") -> — | M90: =IF(AND('🔄 Topic Pool'!P21<>"✅ Done",'🔄 Topic Pool'!M21="✅ YES",NOT(A460=2),NOT(AND(A460=1,OR('🔄 Topic Pool'!P21="❌ Missed",'🔄 Topic Pool'!P21="🔄 Partial"))),IF($C$14="Option 1 — Same Month Only",'🔄 Topic Pool'!B21=$B$400,OR(AND('🔄 Topic Pool'!B21=$B$400,ROUND(('🔄 Topic Pool'!A21-1)/7,0)=$A$400),AND('🔄 Topic Pool'!B21=$B$400,ROUND(('🔄 Topic Pool'!A21-1)/7,0)=$A$400+1)))),'🔄 Topic Pool'!E21,"—") -> — | O90: =IF(AND('🔄 Topic Pool'!P21<>"✅ Done",'🔄 Topic Pool'!M21="✅ YES",NOT(A460=2),NOT(AND(A460=1,OR('🔄 Topic Pool'!P21="❌ Missed",'🔄 Topic Pool'!P21="🔄 Partial"))),IF($C$14="Option 1 — Same Month Only",'🔄 Topic Pool'!B21=$B$400,OR(AND('🔄 Topic Pool'!B21=$B$400,ROUND(('🔄 Topic Pool'!A21-1)/7,0)=$A$400),AND('🔄 Topic Pool'!B21=$B$400,ROUND(('🔄 Topic Pool'!A21-1)/7,0)=$A$400+1)))),'🔄 Topic Pool'!G21,"—") -> — | P90: =IF(AND('🔄 Topic Pool'!P21<>"✅ Done",'🔄 Topic Pool'!M21="✅ YES",NOT(A460=2),NOT(AND(A460=1,OR('🔄 Topic Pool'!P21="❌ Missed",'🔄 Topic Pool'!P21="🔄 Partial"))),IF($C$14="Option 1 — Same Month Only",'🔄 Topic Pool'!B21=$B$400,OR(AND('🔄 Topic Pool'!B21=$B$400,ROUND(('🔄 Topic Pool'!A21-1)/7,0)=$A$400),AND('🔄 Topic Pool'!B21=$B$400,ROUND(('🔄 Topic Pool'!A21-1)/7,0)=$A$400+1)))),'🔄 Topic Pool'!J21,"—") -> — | R90: =IF(AND('🔄 Topic Pool'!P21<>"✅ Done",'🔄 Topic Pool'!M21="✅ YES",NOT(A460=2),NOT(AND(A460=1,OR('🔄 Topic Pool'!P21="❌ Missed",'🔄 Topic Pool'!P21="🔄 Partial"))),IF($C$14="Option 1 — Same Month Only",'🔄 Topic Pool'!B21=$B$400,OR(AND('🔄 Topic Pool'!B21=$B$400,ROUND(('🔄 Topic Pool'!A21-1)/7,0)=$A$400),AND('🔄 Topic Pool'!B21=$B$400,ROUND(('🔄 Topic Pool'!A21-1)/7,0)=$A$400+1)))),COUNTIF('📋 Swap History'!$F$4:$F$200,'🔄 Topic Pool'!D21),"—") -> — | S90: =IF(NOT(AND('🔄 Topic Pool'!P21<>"✅ Done",'🔄 Topic Pool'!M21="✅ YES",NOT(A460=2),NOT(AND(A460=1,OR('🔄 Topic Pool'!P21="❌ Missed",'🔄 Topic Pool'!P21="🔄 Partial"))),IF($C$14="Option 1 — Same Month Only",'🔄 Topic Pool'!B21=$B$400,OR(AND('🔄 Topic Pool'!B21=$B$400,ROUND(('🔄 Topic Pool'!A21-1)/7,0)=$A$400),AND('🔄 Topic Pool'!B21=$B$400,ROUND(('🔄 Topic Pool'!A21-1)/7,0)=$A$400+1))))),"🔒",IF('🔄 Topic Pool'!M21="🔒 NO","🔒",IF(COUNTIF('📋 Swap History'!$F$4:$F$200,'🔄 Topic Pool'!D21)>=$C$8,"🔒","✅"))) -> 🔒 | U90: =IF(AND('🔄 Topic Pool'!P21<>"✅ Done",'🔄 Topic Pool'!M21="✅ YES",NOT(A460=2),NOT(AND(A460=1,OR('🔄 Topic Pool'!P21="❌ Missed",'🔄 Topic Pool'!P21="🔄 Partial"))),IF($C$14="Option 1 — Same Month Only",'🔄 Topic Pool'!B21=$B$400,OR(AND('🔄 Topic Pool'!B21=$B$400,ROUND(('🔄 Topic Pool'!A21-1)/7,0)=$A$400),AND('🔄 Topic Pool'!B21=$B$400,ROUND(('🔄 Topic Pool'!A21-1)/7,0)=$A$400+1)))),'🔄 Topic Pool'!J21&" — Seq "&'🔄 Topic Pool'!C21&" in month","—") -> —
B91: =IF(AND('🔄 Topic Pool'!P25<>"✅ Done",'🔄 Topic Pool'!M25="✅ YES",NOT(A460=2),NOT(AND(A460=1,OR('🔄 Topic Pool'!P25="❌ Missed",'🔄 Topic Pool'!P25="🔄 Partial"))),IF($C$14="Option 1 — Same Month Only",'🔄 Topic Pool'!B25=$B$400,OR(AND('🔄 Topic Pool'!B25=$B$400,ROUND(('🔄 Topic Pool'!A25-1)/7,0)=$A$400),AND('🔄 Topic Pool'!B25=$B$400,ROUND(('🔄 Topic Pool'!A25-1)/7,0)=$A$400+1)))),'🔄 Topic Pool'!A25,"—") -> — | C91: =IF(AND('🔄 Topic Pool'!P25<>"✅ Done",'🔄 Topic Pool'!M25="✅ YES",NOT(A460=2),NOT(AND(A460=1,OR('🔄 Topic Pool'!P25="❌ Missed",'🔄 Topic Pool'!P25="🔄 Partial"))),IF($C$14="Option 1 — Same Month Only",'🔄 Topic Pool'!B25=$B$400,OR(AND('🔄 Topic Pool'!B25=$B$400,ROUND(('🔄 Topic Pool'!A25-1)/7,0)=$A$400),AND('🔄 Topic Pool'!B25=$B$400,ROUND(('🔄 Topic Pool'!A25-1)/7,0)=$A$400+1)))),'🔄 Topic Pool'!D25,"—") -> — | M91: =IF(AND('🔄 Topic Pool'!P25<>"✅ Done",'🔄 Topic Pool'!M25="✅ YES",NOT(A460=2),NOT(AND(A460=1,OR('🔄 Topic Pool'!P25="❌ Missed",'🔄 Topic Pool'!P25="🔄 Partial"))),IF($C$14="Option 1 — Same Month Only",'🔄 Topic Pool'!B25=$B$400,OR(AND('🔄 Topic Pool'!B25=$B$400,ROUND(('🔄 Topic Pool'!A25-1)/7,0)=$A$400),AND('🔄 Topic Pool'!B25=$B$400,ROUND(('🔄 Topic Pool'!A25-1)/7,0)=$A$400+1)))),'🔄 Topic Pool'!E25,"—") -> — | O91: =IF(AND('🔄 Topic Pool'!P25<>"✅ Done",'🔄 Topic Pool'!M25="✅ YES",NOT(A460=2),NOT(AND(A460=1,OR('🔄 Topic Pool'!P25="❌ Missed",'🔄 Topic Pool'!P25="🔄 Partial"))),IF($C$14="Option 1 — Same Month Only",'🔄 Topic Pool'!B25=$B$400,OR(AND('🔄 Topic Pool'!B25=$B$400,ROUND(('🔄 Topic Pool'!A25-1)/7,0)=$A$400),AND('🔄 Topic Pool'!B25=$B$400,ROUND(('🔄 Topic Pool'!A25-1)/7,0)=$A$400+1)))),'🔄 Topic Pool'!G25,"—") -> — | P91: =IF(AND('🔄 Topic Pool'!P25<>"✅ Done",'🔄 Topic Pool'!M25="✅ YES",NOT(A460=2),NOT(AND(A460=1,OR('🔄 Topic Pool'!P25="❌ Missed",'🔄 Topic Pool'!P25="🔄 Partial"))),IF($C$14="Option 1 — Same Month Only",'🔄 Topic Pool'!B25=$B$400,OR(AND('🔄 Topic Pool'!B25=$B$400,ROUND(('🔄 Topic Pool'!A25-1)/7,0)=$A$400),AND('🔄 Topic Pool'!B25=$B$400,ROUND(('🔄 Topic Pool'!A25-1)/7,0)=$A$400+1)))),'🔄 Topic Pool'!J25,"—") -> — | R91: =IF(AND('🔄 Topic Pool'!P25<>"✅ Done",'🔄 Topic Pool'!M25="✅ YES",NOT(A460=2),NOT(AND(A460=1,OR('🔄 Topic Pool'!P25="❌ Missed",'🔄 Topic Pool'!P25="🔄 Partial"))),IF($C$14="Option 1 — Same Month Only",'🔄 Topic Pool'!B25=$B$400,OR(AND('🔄 Topic Pool'!B25=$B$400,ROUND(('🔄 Topic Pool'!A25-1)/7,0)=$A$400),AND('🔄 Topic Pool'!B25=$B$400,ROUND(('🔄 Topic Pool'!A25-1)/7,0)=$A$400+1)))),COUNTIF('📋 Swap History'!$F$4:$F$200,'🔄 Topic Pool'!D25),"—") -> — | S91: =IF(NOT(AND('🔄 Topic Pool'!P25<>"✅ Done",'🔄 Topic Pool'!M25="✅ YES",NOT(A460=2),NOT(AND(A460=1,OR('🔄 Topic Pool'!P25="❌ Missed",'🔄 Topic Pool'!P25="🔄 Partial"))),IF($C$14="Option 1 — Same Month Only",'🔄 Topic Pool'!B25=$B$400,OR(AND('🔄 Topic Pool'!B25=$B$400,ROUND(('🔄 Topic Pool'!A25-1)/7,0)=$A$400),AND('🔄 Topic Pool'!B25=$B$400,ROUND(('🔄 Topic Pool'!A25-1)/7,0)=$A$400+1))))),"🔒",IF('🔄 Topic Pool'!M25="🔒 NO","🔒",IF(COUNTIF('📋 Swap History'!$F$4:$F$200,'🔄 Topic Pool'!D25)>=$C$8,"🔒","✅"))) -> 🔒 | U91: =IF(AND('🔄 Topic Pool'!P25<>"✅ Done",'🔄 Topic Pool'!M25="✅ YES",NOT(A460=2),NOT(AND(A460=1,OR('🔄 Topic Pool'!P25="❌ Missed",'🔄 Topic Pool'!P25="🔄 Partial"))),IF($C$14="Option 1 — Same Month Only",'🔄 Topic Pool'!B25=$B$400,OR(AND('🔄 Topic Pool'!B25=$B$400,ROUND(('🔄 Topic Pool'!A25-1)/7,0)=$A$400),AND('🔄 Topic Pool'!B25=$B$400,ROUND(('🔄 Topic Pool'!A25-1)/7,0)=$A$400+1)))),'🔄 Topic Pool'!J25&" — Seq "&'🔄 Topic Pool'!C25&" in month","—") -> —
B92: =IF(AND('🔄 Topic Pool'!P26<>"✅ Done",'🔄 Topic Pool'!M26="✅ YES",NOT(A460=2),NOT(AND(A460=1,OR('🔄 Topic Pool'!P26="❌ Missed",'🔄 Topic Pool'!P26="🔄 Partial"))),IF($C$14="Option 1 — Same Month Only",'🔄 Topic Pool'!B26=$B$400,OR(AND('🔄 Topic Pool'!B26=$B$400,ROUND(('🔄 Topic Pool'!A26-1)/7,0)=$A$400),AND('🔄 Topic Pool'!B26=$B$400,ROUND(('🔄 Topic Pool'!A26-1)/7,0)=$A$400+1)))),'🔄 Topic Pool'!A26,"—") -> — | C92: =IF(AND('🔄 Topic Pool'!P26<>"✅ Done",'🔄 Topic Pool'!M26="✅ YES",NOT(A460=2),NOT(AND(A460=1,OR('🔄 Topic Pool'!P26="❌ Missed",'🔄 Topic Pool'!P26="🔄 Partial"))),IF($C$14="Option 1 — Same Month Only",'🔄 Topic Pool'!B26=$B$400,OR(AND('🔄 Topic Pool'!B26=$B$400,ROUND(('🔄 Topic Pool'!A26-1)/7,0)=$A$400),AND('🔄 Topic Pool'!B26=$B$400,ROUND(('🔄 Topic Pool'!A26-1)/7,0)=$A$400+1)))),'🔄 Topic Pool'!D26,"—") -> — | M92: =IF(AND('🔄 Topic Pool'!P26<>"✅ Done",'🔄 Topic Pool'!M26="✅ YES",NOT(A460=2),NOT(AND(A460=1,OR('🔄 Topic Pool'!P26="❌ Missed",'🔄 Topic Pool'!P26="🔄 Partial"))),IF($C$14="Option 1 — Same Month Only",'🔄 Topic Pool'!B26=$B$400,OR(AND('🔄 Topic Pool'!B26=$B$400,ROUND(('🔄 Topic Pool'!A26-1)/7,0)=$A$400),AND('🔄 Topic Pool'!B26=$B$400,ROUND(('🔄 Topic Pool'!A26-1)/7,0)=$A$400+1)))),'🔄 Topic Pool'!E26,"—") -> — | O92: =IF(AND('🔄 Topic Pool'!P26<>"✅ Done",'🔄 Topic Pool'!M26="✅ YES",NOT(A460=2),NOT(AND(A460=1,OR('🔄 Topic Pool'!P26="❌ Missed",'🔄 Topic Pool'!P26="🔄 Partial"))),IF($C$14="Option 1 — Same Month Only",'🔄 Topic Pool'!B26=$B$400,OR(AND('🔄 Topic Pool'!B26=$B$400,ROUND(('🔄 Topic Pool'!A26-1)/7,0)=$A$400),AND('🔄 Topic Pool'!B26=$B$400,ROUND(('🔄 Topic Pool'!A26-1)/7,0)=$A$400+1)))),'🔄 Topic Pool'!G26,"—") -> — | P92: =IF(AND('🔄 Topic Pool'!P26<>"✅ Done",'🔄 Topic Pool'!M26="✅ YES",NOT(A460=2),NOT(AND(A460=1,OR('🔄 Topic Pool'!P26="❌ Missed",'🔄 Topic Pool'!P26="🔄 Partial"))),IF($C$14="Option 1 — Same Month Only",'🔄 Topic Pool'!B26=$B$400,OR(AND('🔄 Topic Pool'!B26=$B$400,ROUND(('🔄 Topic Pool'!A26-1)/7,0)=$A$400),AND('🔄 Topic Pool'!B26=$B$400,ROUND(('🔄 Topic Pool'!A26-1)/7,0)=$A$400+1)))),'🔄 Topic Pool'!J26,"—") -> — | R92: =IF(AND('🔄 Topic Pool'!P26<>"✅ Done",'🔄 Topic Pool'!M26="✅ YES",NOT(A460=2),NOT(AND(A460=1,OR('🔄 Topic Pool'!P26="❌ Missed",'🔄 Topic Pool'!P26="🔄 Partial"))),IF($C$14="Option 1 — Same Month Only",'🔄 Topic Pool'!B26=$B$400,OR(AND('🔄 Topic Pool'!B26=$B$400,ROUND(('🔄 Topic Pool'!A26-1)/7,0)=$A$400),AND('🔄 Topic Pool'!B26=$B$400,ROUND(('🔄 Topic Pool'!A26-1)/7,0)=$A$400+1)))),COUNTIF('📋 Swap History'!$F$4:$F$200,'🔄 Topic Pool'!D26),"—") -> — | S92: =IF(NOT(AND('🔄 Topic Pool'!P26<>"✅ Done",'🔄 Topic Pool'!M26="✅ YES",NOT(A460=2),NOT(AND(A460=1,OR('🔄 Topic Pool'!P26="❌ Missed",'🔄 Topic Pool'!P26="🔄 Partial"))),IF($C$14="Option 1 — Same Month Only",'🔄 Topic Pool'!B26=$B$400,OR(AND('🔄 Topic Pool'!B26=$B$400,ROUND(('🔄 Topic Pool'!A26-1)/7,0)=$A$400),AND('🔄 Topic Pool'!B26=$B$400,ROUND(('🔄 Topic Pool'!A26-1)/7,0)=$A$400+1))))),"🔒",IF('🔄 Topic Pool'!M26="🔒 NO","🔒",IF(COUNTIF('📋 Swap History'!$F$4:$F$200,'🔄 Topic Pool'!D26)>=$C$8,"🔒","✅"))) -> 🔒 | U92: =IF(AND('🔄 Topic Pool'!P26<>"✅ Done",'🔄 Topic Pool'!M26="✅ YES",NOT(A460=2),NOT(AND(A460=1,OR('🔄 Topic Pool'!P26="❌ Missed",'🔄 Topic Pool'!P26="🔄 Partial"))),IF($C$14="Option 1 — Same Month Only",'🔄 Topic Pool'!B26=$B$400,OR(AND('🔄 Topic Pool'!B26=$B$400,ROUND(('🔄 Topic Pool'!A26-1)/7,0)=$A$400),AND('🔄 Topic Pool'!B26=$B$400,ROUND(('🔄 Topic Pool'!A26-1)/7,0)=$A$400+1)))),'🔄 Topic Pool'!J26&" — Seq "&'🔄 Topic Pool'!C26&" in month","—") -> —
B93: =IF(AND('🔄 Topic Pool'!P27<>"✅ Done",'🔄 Topic Pool'!M27="✅ YES",NOT(A460=2),NOT(AND(A460=1,OR('🔄 Topic Pool'!P27="❌ Missed",'🔄 Topic Pool'!P27="🔄 Partial"))),IF($C$14="Option 1 — Same Month Only",'🔄 Topic Pool'!B27=$B$400,OR(AND('🔄 Topic Pool'!B27=$B$400,ROUND(('🔄 Topic Pool'!A27-1)/7,0)=$A$400),AND('🔄 Topic Pool'!B27=$B$400,ROUND(('🔄 Topic Pool'!A27-1)/7,0)=$A$400+1)))),'🔄 Topic Pool'!A27,"—") -> — | C93: =IF(AND('🔄 Topic Pool'!P27<>"✅ Done",'🔄 Topic Pool'!M27="✅ YES",NOT(A460=2),NOT(AND(A460=1,OR('🔄 Topic Pool'!P27="❌ Missed",'🔄 Topic Pool'!P27="🔄 Partial"))),IF($C$14="Option 1 — Same Month Only",'🔄 Topic Pool'!B27=$B$400,OR(AND('🔄 Topic Pool'!B27=$B$400,ROUND(('🔄 Topic Pool'!A27-1)/7,0)=$A$400),AND('🔄 Topic Pool'!B27=$B$400,ROUND(('🔄 Topic Pool'!A27-1)/7,0)=$A$400+1)))),'🔄 Topic Pool'!D27,"—") -> — | M93: =IF(AND('🔄 Topic Pool'!P27<>"✅ Done",'🔄 Topic Pool'!M27="✅ YES",NOT(A460=2),NOT(AND(A460=1,OR('🔄 Topic Pool'!P27="❌ Missed",'🔄 Topic Pool'!P27="🔄 Partial"))),IF($C$14="Option 1 — Same Month Only",'🔄 Topic Pool'!B27=$B$400,OR(AND('🔄 Topic Pool'!B27=$B$400,ROUND(('🔄 Topic Pool'!A27-1)/7,0)=$A$400),AND('🔄 Topic Pool'!B27=$B$400,ROUND(('🔄 Topic Pool'!A27-1)/7,0)=$A$400+1)))),'🔄 Topic Pool'!E27,"—") -> — | O93: =IF(AND('🔄 Topic Pool'!P27<>"✅ Done",'🔄 Topic Pool'!M27="✅ YES",NOT(A460=2),NOT(AND(A460=1,OR('🔄 Topic Pool'!P27="❌ Missed",'🔄 Topic Pool'!P27="🔄 Partial"))),IF($C$14="Option 1 — Same Month Only",'🔄 Topic Pool'!B27=$B$400,OR(AND('🔄 Topic Pool'!B27=$B$400,ROUND(('🔄 Topic Pool'!A27-1)/7,0)=$A$400),AND('🔄 Topic Pool'!B27=$B$400,ROUND(('🔄 Topic Pool'!A27-1)/7,0)=$A$400+1)))),'🔄 Topic Pool'!G27,"—") -> — | P93: =IF(AND('🔄 Topic Pool'!P27<>"✅ Done",'🔄 Topic Pool'!M27="✅ YES",NOT(A460=2),NOT(AND(A460=1,OR('🔄 Topic Pool'!P27="❌ Missed",'🔄 Topic Pool'!P27="🔄 Partial"))),IF($C$14="Option 1 — Same Month Only",'🔄 Topic Pool'!B27=$B$400,OR(AND('🔄 Topic Pool'!B27=$B$400,ROUND(('🔄 Topic Pool'!A27-1)/7,0)=$A$400),AND('🔄 Topic Pool'!B27=$B$400,ROUND(('🔄 Topic Pool'!A27-1)/7,0)=$A$400+1)))),'🔄 Topic Pool'!J27,"—") -> — | R93: =IF(AND('🔄 Topic Pool'!P27<>"✅ Done",'🔄 Topic Pool'!M27="✅ YES",NOT(A460=2),NOT(AND(A460=1,OR('🔄 Topic Pool'!P27="❌ Missed",'🔄 Topic Pool'!P27="🔄 Partial"))),IF($C$14="Option 1 — Same Month Only",'🔄 Topic Pool'!B27=$B$400,OR(AND('🔄 Topic Pool'!B27=$B$400,ROUND(('🔄 Topic Pool'!A27-1)/7,0)=$A$400),AND('🔄 Topic Pool'!B27=$B$400,ROUND(('🔄 Topic Pool'!A27-1)/7,0)=$A$400+1)))),COUNTIF('📋 Swap History'!$F$4:$F$200,'🔄 Topic Pool'!D27),"—") -> — | S93: =IF(NOT(AND('🔄 Topic Pool'!P27<>"✅ Done",'🔄 Topic Pool'!M27="✅ YES",NOT(A460=2),NOT(AND(A460=1,OR('🔄 Topic Pool'!P27="❌ Missed",'🔄 Topic Pool'!P27="🔄 Partial"))),IF($C$14="Option 1 — Same Month Only",'🔄 Topic Pool'!B27=$B$400,OR(AND('🔄 Topic Pool'!B27=$B$400,ROUND(('🔄 Topic Pool'!A27-1)/7,0)=$A$400),AND('🔄 Topic Pool'!B27=$B$400,ROUND(('🔄 Topic Pool'!A27-1)/7,0)=$A$400+1))))),"🔒",IF('🔄 Topic Pool'!M27="🔒 NO","🔒",IF(COUNTIF('📋 Swap History'!$F$4:$F$200,'🔄 Topic Pool'!D27)>=$C$8,"🔒","✅"))) -> 🔒 | U93: =IF(AND('🔄 Topic Pool'!P27<>"✅ Done",'🔄 Topic Pool'!M27="✅ YES",NOT(A460=2),NOT(AND(A460=1,OR('🔄 Topic Pool'!P27="❌ Missed",'🔄 Topic Pool'!P27="🔄 Partial"))),IF($C$14="Option 1 — Same Month Only",'🔄 Topic Pool'!B27=$B$400,OR(AND('🔄 Topic Pool'!B27=$B$400,ROUND(('🔄 Topic Pool'!A27-1)/7,0)=$A$400),AND('🔄 Topic Pool'!B27=$B$400,ROUND(('🔄 Topic Pool'!A27-1)/7,0)=$A$400+1)))),'🔄 Topic Pool'!J27&" — Seq "&'🔄 Topic Pool'!C27&" in month","—") -> —
B94: =IF(AND('🔄 Topic Pool'!P28<>"✅ Done",'🔄 Topic Pool'!M28="✅ YES",NOT(A460=2),NOT(AND(A460=1,OR('🔄 Topic Pool'!P28="❌ Missed",'🔄 Topic Pool'!P28="🔄 Partial"))),IF($C$14="Option 1 — Same Month Only",'🔄 Topic Pool'!B28=$B$400,OR(AND('🔄 Topic Pool'!B28=$B$400,ROUND(('🔄 Topic Pool'!A28-1)/7,0)=$A$400),AND('🔄 Topic Pool'!B28=$B$400,ROUND(('🔄 Topic Pool'!A28-1)/7,0)=$A$400+1)))),'🔄 Topic Pool'!A28,"—") -> — | C94: =IF(AND('🔄 Topic Pool'!P28<>"✅ Done",'🔄 Topic Pool'!M28="✅ YES",NOT(A460=2),NOT(AND(A460=1,OR('🔄 Topic Pool'!P28="❌ Missed",'🔄 Topic Pool'!P28="🔄 Partial"))),IF($C$14="Option 1 — Same Month Only",'🔄 Topic Pool'!B28=$B$400,OR(AND('🔄 Topic Pool'!B28=$B$400,ROUND(('🔄 Topic Pool'!A28-1)/7,0)=$A$400),AND('🔄 Topic Pool'!B28=$B$400,ROUND(('🔄 Topic Pool'!A28-1)/7,0)=$A$400+1)))),'🔄 Topic Pool'!D28,"—") -> — | M94: =IF(AND('🔄 Topic Pool'!P28<>"✅ Done",'🔄 Topic Pool'!M28="✅ YES",NOT(A460=2),NOT(AND(A460=1,OR('🔄 Topic Pool'!P28="❌ Missed",'🔄 Topic Pool'!P28="🔄 Partial"))),IF($C$14="Option 1 — Same Month Only",'🔄 Topic Pool'!B28=$B$400,OR(AND('🔄 Topic Pool'!B28=$B$400,ROUND(('🔄 Topic Pool'!A28-1)/7,0)=$A$400),AND('🔄 Topic Pool'!B28=$B$400,ROUND(('🔄 Topic Pool'!A28-1)/7,0)=$A$400+1)))),'🔄 Topic Pool'!E28,"—") -> — | O94: =IF(AND('🔄 Topic Pool'!P28<>"✅ Done",'🔄 Topic Pool'!M28="✅ YES",NOT(A460=2),NOT(AND(A460=1,OR('🔄 Topic Pool'!P28="❌ Missed",'🔄 Topic Pool'!P28="🔄 Partial"))),IF($C$14="Option 1 — Same Month Only",'🔄 Topic Pool'!B28=$B$400,OR(AND('🔄 Topic Pool'!B28=$B$400,ROUND(('🔄 Topic Pool'!A28-1)/7,0)=$A$400),AND('🔄 Topic Pool'!B28=$B$400,ROUND(('🔄 Topic Pool'!A28-1)/7,0)=$A$400+1)))),'🔄 Topic Pool'!G28,"—") -> — | P94: =IF(AND('🔄 Topic Pool'!P28<>"✅ Done",'🔄 Topic Pool'!M28="✅ YES",NOT(A460=2),NOT(AND(A460=1,OR('🔄 Topic Pool'!P28="❌ Missed",'🔄 Topic Pool'!P28="🔄 Partial"))),IF($C$14="Option 1 — Same Month Only",'🔄 Topic Pool'!B28=$B$400,OR(AND('🔄 Topic Pool'!B28=$B$400,ROUND(('🔄 Topic Pool'!A28-1)/7,0)=$A$400),AND('🔄 Topic Pool'!B28=$B$400,ROUND(('🔄 Topic Pool'!A28-1)/7,0)=$A$400+1)))),'🔄 Topic Pool'!J28,"—") -> — | R94: =IF(AND('🔄 Topic Pool'!P28<>"✅ Done",'🔄 Topic Pool'!M28="✅ YES",NOT(A460=2),NOT(AND(A460=1,OR('🔄 Topic Pool'!P28="❌ Missed",'🔄 Topic Pool'!P28="🔄 Partial"))),IF($C$14="Option 1 — Same Month Only",'🔄 Topic Pool'!B28=$B$400,OR(AND('🔄 Topic Pool'!B28=$B$400,ROUND(('🔄 Topic Pool'!A28-1)/7,0)=$A$400),AND('🔄 Topic Pool'!B28=$B$400,ROUND(('🔄 Topic Pool'!A28-1)/7,0)=$A$400+1)))),COUNTIF('📋 Swap History'!$F$4:$F$200,'🔄 Topic Pool'!D28),"—") -> — | S94: =IF(NOT(AND('🔄 Topic Pool'!P28<>"✅ Done",'🔄 Topic Pool'!M28="✅ YES",NOT(A460=2),NOT(AND(A460=1,OR('🔄 Topic Pool'!P28="❌ Missed",'🔄 Topic Pool'!P28="🔄 Partial"))),IF($C$14="Option 1 — Same Month Only",'🔄 Topic Pool'!B28=$B$400,OR(AND('🔄 Topic Pool'!B28=$B$400,ROUND(('🔄 Topic Pool'!A28-1)/7,0)=$A$400),AND('🔄 Topic Pool'!B28=$B$400,ROUND(('🔄 Topic Pool'!A28-1)/7,0)=$A$400+1))))),"🔒",IF('🔄 Topic Pool'!M28="🔒 NO","🔒",IF(COUNTIF('📋 Swap History'!$F$4:$F$200,'🔄 Topic Pool'!D28)>=$C$8,"🔒","✅"))) -> 🔒 | U94: =IF(AND('🔄 Topic Pool'!P28<>"✅ Done",'🔄 Topic Pool'!M28="✅ YES",NOT(A460=2),NOT(AND(A460=1,OR('🔄 Topic Pool'!P28="❌ Missed",'🔄 Topic Pool'!P28="🔄 Partial"))),IF($C$14="Option 1 — Same Month Only",'🔄 Topic Pool'!B28=$B$400,OR(AND('🔄 Topic Pool'!B28=$B$400,ROUND(('🔄 Topic Pool'!A28-1)/7,0)=$A$400),AND('🔄 Topic Pool'!B28=$B$400,ROUND(('🔄 Topic Pool'!A28-1)/7,0)=$A$400+1)))),'🔄 Topic Pool'!J28&" — Seq "&'🔄 Topic Pool'!C28&" in month","—") -> —
B95: =IF(AND('🔄 Topic Pool'!P30<>"✅ Done",'🔄 Topic Pool'!M30="✅ YES",NOT(A460=2),NOT(AND(A460=1,OR('🔄 Topic Pool'!P30="❌ Missed",'🔄 Topic Pool'!P30="🔄 Partial"))),IF($C$14="Option 1 — Same Month Only",'🔄 Topic Pool'!B30=$B$400,OR(AND('🔄 Topic Pool'!B30=$B$400,ROUND(('🔄 Topic Pool'!A30-1)/7,0)=$A$400),AND('🔄 Topic Pool'!B30=$B$400,ROUND(('🔄 Topic Pool'!A30-1)/7,0)=$A$400+1)))),'🔄 Topic Pool'!A30,"—") -> — | C95: =IF(AND('🔄 Topic Pool'!P30<>"✅ Done",'🔄 Topic Pool'!M30="✅ YES",NOT(A460=2),NOT(AND(A460=1,OR('🔄 Topic Pool'!P30="❌ Missed",'🔄 Topic Pool'!P30="🔄 Partial"))),IF($C$14="Option 1 — Same Month Only",'🔄 Topic Pool'!B30=$B$400,OR(AND('🔄 Topic Pool'!B30=$B$400,ROUND(('🔄 Topic Pool'!A30-1)/7,0)=$A$400),AND('🔄 Topic Pool'!B30=$B$400,ROUND(('🔄 Topic Pool'!A30-1)/7,0)=$A$400+1)))),'🔄 Topic Pool'!D30,"—") -> — | M95: =IF(AND('🔄 Topic Pool'!P30<>"✅ Done",'🔄 Topic Pool'!M30="✅ YES",NOT(A460=2),NOT(AND(A460=1,OR('🔄 Topic Pool'!P30="❌ Missed",'🔄 Topic Pool'!P30="🔄 Partial"))),IF($C$14="Option 1 — Same Month Only",'🔄 Topic Pool'!B30=$B$400,OR(AND('🔄 Topic Pool'!B30=$B$400,ROUND(('🔄 Topic Pool'!A30-1)/7,0)=$A$400),AND('🔄 Topic Pool'!B30=$B$400,ROUND(('🔄 Topic Pool'!A30-1)/7,0)=$A$400+1)))),'🔄 Topic Pool'!E30,"—") -> — | O95: =IF(AND('🔄 Topic Pool'!P30<>"✅ Done",'🔄 Topic Pool'!M30="✅ YES",NOT(A460=2),NOT(AND(A460=1,OR('🔄 Topic Pool'!P30="❌ Missed",'🔄 Topic Pool'!P30="🔄 Partial"))),IF($C$14="Option 1 — Same Month Only",'🔄 Topic Pool'!B30=$B$400,OR(AND('🔄 Topic Pool'!B30=$B$400,ROUND(('🔄 Topic Pool'!A30-1)/7,0)=$A$400),AND('🔄 Topic Pool'!B30=$B$400,ROUND(('🔄 Topic Pool'!A30-1)/7,0)=$A$400+1)))),'🔄 Topic Pool'!G30,"—") -> — | P95: =IF(AND('🔄 Topic Pool'!P30<>"✅ Done",'🔄 Topic Pool'!M30="✅ YES",NOT(A460=2),NOT(AND(A460=1,OR('🔄 Topic Pool'!P30="❌ Missed",'🔄 Topic Pool'!P30="🔄 Partial"))),IF($C$14="Option 1 — Same Month Only",'🔄 Topic Pool'!B30=$B$400,OR(AND('🔄 Topic Pool'!B30=$B$400,ROUND(('🔄 Topic Pool'!A30-1)/7,0)=$A$400),AND('🔄 Topic Pool'!B30=$B$400,ROUND(('🔄 Topic Pool'!A30-1)/7,0)=$A$400+1)))),'🔄 Topic Pool'!J30,"—") -> — | R95: =IF(AND('🔄 Topic Pool'!P30<>"✅ Done",'🔄 Topic Pool'!M30="✅ YES",NOT(A460=2),NOT(AND(A460=1,OR('🔄 Topic Pool'!P30="❌ Missed",'🔄 Topic Pool'!P30="🔄 Partial"))),IF($C$14="Option 1 — Same Month Only",'🔄 Topic Pool'!B30=$B$400,OR(AND('🔄 Topic Pool'!B30=$B$400,ROUND(('🔄 Topic Pool'!A30-1)/7,0)=$A$400),AND('🔄 Topic Pool'!B30=$B$400,ROUND(('🔄 Topic Pool'!A30-1)/7,0)=$A$400+1)))),COUNTIF('📋 Swap History'!$F$4:$F$200,'🔄 Topic Pool'!D30),"—") -> — | S95: =IF(NOT(AND('🔄 Topic Pool'!P30<>"✅ Done",'🔄 Topic Pool'!M30="✅ YES",NOT(A460=2),NOT(AND(A460=1,OR('🔄 Topic Pool'!P30="❌ Missed",'🔄 Topic Pool'!P30="🔄 Partial"))),IF($C$14="Option 1 — Same Month Only",'🔄 Topic Pool'!B30=$B$400,OR(AND('🔄 Topic Pool'!B30=$B$400,ROUND(('🔄 Topic Pool'!A30-1)/7,0)=$A$400),AND('🔄 Topic Pool'!B30=$B$400,ROUND(('🔄 Topic Pool'!A30-1)/7,0)=$A$400+1))))),"🔒",IF('🔄 Topic Pool'!M30="🔒 NO","🔒",IF(COUNTIF('📋 Swap History'!$F$4:$F$200,'🔄 Topic Pool'!D30)>=$C$8,"🔒","✅"))) -> 🔒 | U95: =IF(AND('🔄 Topic Pool'!P30<>"✅ Done",'🔄 Topic Pool'!M30="✅ YES",NOT(A460=2),NOT(AND(A460=1,OR('🔄 Topic Pool'!P30="❌ Missed",'🔄 Topic Pool'!P30="🔄 Partial"))),IF($C$14="Option 1 — Same Month Only",'🔄 Topic Pool'!B30=$B$400,OR(AND('🔄 Topic Pool'!B30=$B$400,ROUND(('🔄 Topic Pool'!A30-1)/7,0)=$A$400),AND('🔄 Topic Pool'!B30=$B$400,ROUND(('🔄 Topic Pool'!A30-1)/7,0)=$A$400+1)))),'🔄 Topic Pool'!J30&" — Seq "&'🔄 Topic Pool'!C30&" in month","—") -> —
B96: =IF(AND('🔄 Topic Pool'!P10<>"✅ Done",'🔄 Topic Pool'!M10="✅ YES",NOT(A460=2),NOT(AND(A460=1,OR('🔄 Topic Pool'!P10="❌ Missed",'🔄 Topic Pool'!P10="🔄 Partial"))),IF($C$14="Option 1 — Same Month Only",'🔄 Topic Pool'!B10=$B$400,OR(AND('🔄 Topic Pool'!B10=$B$400,ROUND(('🔄 Topic Pool'!A10-1)/7,0)=$A$400),AND('🔄 Topic Pool'!B10=$B$400,ROUND(('🔄 Topic Pool'!A10-1)/7,0)=$A$400+1)))),'🔄 Topic Pool'!A10,"—") -> — | C96: =IF(AND('🔄 Topic Pool'!P10<>"✅ Done",'🔄 Topic Pool'!M10="✅ YES",NOT(A460=2),NOT(AND(A460=1,OR('🔄 Topic Pool'!P10="❌ Missed",'🔄 Topic Pool'!P10="🔄 Partial"))),IF($C$14="Option 1 — Same Month Only",'🔄 Topic Pool'!B10=$B$400,OR(AND('🔄 Topic Pool'!B10=$B$400,ROUND(('🔄 Topic Pool'!A10-1)/7,0)=$A$400),AND('🔄 Topic Pool'!B10=$B$400,ROUND(('🔄 Topic Pool'!A10-1)/7,0)=$A$400+1)))),'🔄 Topic Pool'!D10,"—") -> — | M96: =IF(AND('🔄 Topic Pool'!P10<>"✅ Done",'🔄 Topic Pool'!M10="✅ YES",NOT(A460=2),NOT(AND(A460=1,OR('🔄 Topic Pool'!P10="❌ Missed",'🔄 Topic Pool'!P10="🔄 Partial"))),IF($C$14="Option 1 — Same Month Only",'🔄 Topic Pool'!B10=$B$400,OR(AND('🔄 Topic Pool'!B10=$B$400,ROUND(('🔄 Topic Pool'!A10-1)/7,0)=$A$400),AND('🔄 Topic Pool'!B10=$B$400,ROUND(('🔄 Topic Pool'!A10-1)/7,0)=$A$400+1)))),'🔄 Topic Pool'!E10,"—") -> — | O96: =IF(AND('🔄 Topic Pool'!P10<>"✅ Done",'🔄 Topic Pool'!M10="✅ YES",NOT(A460=2),NOT(AND(A460=1,OR('🔄 Topic Pool'!P10="❌ Missed",'🔄 Topic Pool'!P10="🔄 Partial"))),IF($C$14="Option 1 — Same Month Only",'🔄 Topic Pool'!B10=$B$400,OR(AND('🔄 Topic Pool'!B10=$B$400,ROUND(('🔄 Topic Pool'!A10-1)/7,0)=$A$400),AND('🔄 Topic Pool'!B10=$B$400,ROUND(('🔄 Topic Pool'!A10-1)/7,0)=$A$400+1)))),'🔄 Topic Pool'!G10,"—") -> — | P96: =IF(AND('🔄 Topic Pool'!P10<>"✅ Done",'🔄 Topic Pool'!M10="✅ YES",NOT(A460=2),NOT(AND(A460=1,OR('🔄 Topic Pool'!P10="❌ Missed",'🔄 Topic Pool'!P10="🔄 Partial"))),IF($C$14="Option 1 — Same Month Only",'🔄 Topic Pool'!B10=$B$400,OR(AND('🔄 Topic Pool'!B10=$B$400,ROUND(('🔄 Topic Pool'!A10-1)/7,0)=$A$400),AND('🔄 Topic Pool'!B10=$B$400,ROUND(('🔄 Topic Pool'!A10-1)/7,0)=$A$400+1)))),'🔄 Topic Pool'!J10,"—") -> — | R96: =IF(AND('🔄 Topic Pool'!P10<>"✅ Done",'🔄 Topic Pool'!M10="✅ YES",NOT(A460=2),NOT(AND(A460=1,OR('🔄 Topic Pool'!P10="❌ Missed",'🔄 Topic Pool'!P10="🔄 Partial"))),IF($C$14="Option 1 — Same Month Only",'🔄 Topic Pool'!B10=$B$400,OR(AND('🔄 Topic Pool'!B10=$B$400,ROUND(('🔄 Topic Pool'!A10-1)/7,0)=$A$400),AND('🔄 Topic Pool'!B10=$B$400,ROUND(('🔄 Topic Pool'!A10-1)/7,0)=$A$400+1)))),COUNTIF('📋 Swap History'!$F$4:$F$200,'🔄 Topic Pool'!D10),"—") -> — | S96: =IF(NOT(AND('🔄 Topic Pool'!P10<>"✅ Done",'🔄 Topic Pool'!M10="✅ YES",NOT(A460=2),NOT(AND(A460=1,OR('🔄 Topic Pool'!P10="❌ Missed",'🔄 Topic Pool'!P10="🔄 Partial"))),IF($C$14="Option 1 — Same Month Only",'🔄 Topic Pool'!B10=$B$400,OR(AND('🔄 Topic Pool'!B10=$B$400,ROUND(('🔄 Topic Pool'!A10-1)/7,0)=$A$400),AND('🔄 Topic Pool'!B10=$B$400,ROUND(('🔄 Topic Pool'!A10-1)/7,0)=$A$400+1))))),"🔒",IF('🔄 Topic Pool'!M10="🔒 NO","🔒",IF(COUNTIF('📋 Swap History'!$F$4:$F$200,'🔄 Topic Pool'!D10)>=$C$8,"🔒","✅"))) -> 🔒 | U96: =IF(AND('🔄 Topic Pool'!P10<>"✅ Done",'🔄 Topic Pool'!M10="✅ YES",NOT(A460=2),NOT(AND(A460=1,OR('🔄 Topic Pool'!P10="❌ Missed",'🔄 Topic Pool'!P10="🔄 Partial"))),IF($C$14="Option 1 — Same Month Only",'🔄 Topic Pool'!B10=$B$400,OR(AND('🔄 Topic Pool'!B10=$B$400,ROUND(('🔄 Topic Pool'!A10-1)/7,0)=$A$400),AND('🔄 Topic Pool'!B10=$B$400,ROUND(('🔄 Topic Pool'!A10-1)/7,0)=$A$400+1)))),'🔄 Topic Pool'!J10&" — Seq "&'🔄 Topic Pool'!C10&" in month","—") -> —
B97: =IF(AND('🔄 Topic Pool'!P17<>"✅ Done",'🔄 Topic Pool'!M17="✅ YES",NOT(A460=2),NOT(AND(A460=1,OR('🔄 Topic Pool'!P17="❌ Missed",'🔄 Topic Pool'!P17="🔄 Partial"))),IF($C$14="Option 1 — Same Month Only",'🔄 Topic Pool'!B17=$B$400,OR(AND('🔄 Topic Pool'!B17=$B$400,ROUND(('🔄 Topic Pool'!A17-1)/7,0)=$A$400),AND('🔄 Topic Pool'!B17=$B$400,ROUND(('🔄 Topic Pool'!A17-1)/7,0)=$A$400+1)))),'🔄 Topic Pool'!A17,"—") -> — | C97: =IF(AND('🔄 Topic Pool'!P17<>"✅ Done",'🔄 Topic Pool'!M17="✅ YES",NOT(A460=2),NOT(AND(A460=1,OR('🔄 Topic Pool'!P17="❌ Missed",'🔄 Topic Pool'!P17="🔄 Partial"))),IF($C$14="Option 1 — Same Month Only",'🔄 Topic Pool'!B17=$B$400,OR(AND('🔄 Topic Pool'!B17=$B$400,ROUND(('🔄 Topic Pool'!A17-1)/7,0)=$A$400),AND('🔄 Topic Pool'!B17=$B$400,ROUND(('🔄 Topic Pool'!A17-1)/7,0)=$A$400+1)))),'🔄 Topic Pool'!D17,"—") -> — | M97: =IF(AND('🔄 Topic Pool'!P17<>"✅ Done",'🔄 Topic Pool'!M17="✅ YES",NOT(A460=2),NOT(AND(A460=1,OR('🔄 Topic Pool'!P17="❌ Missed",'🔄 Topic Pool'!P17="🔄 Partial"))),IF($C$14="Option 1 — Same Month Only",'🔄 Topic Pool'!B17=$B$400,OR(AND('🔄 Topic Pool'!B17=$B$400,ROUND(('🔄 Topic Pool'!A17-1)/7,0)=$A$400),AND('🔄 Topic Pool'!B17=$B$400,ROUND(('🔄 Topic Pool'!A17-1)/7,0)=$A$400+1)))),'🔄 Topic Pool'!E17,"—") -> — | O97: =IF(AND('🔄 Topic Pool'!P17<>"✅ Done",'🔄 Topic Pool'!M17="✅ YES",NOT(A460=2),NOT(AND(A460=1,OR('🔄 Topic Pool'!P17="❌ Missed",'🔄 Topic Pool'!P17="🔄 Partial"))),IF($C$14="Option 1 — Same Month Only",'🔄 Topic Pool'!B17=$B$400,OR(AND('🔄 Topic Pool'!B17=$B$400,ROUND(('🔄 Topic Pool'!A17-1)/7,0)=$A$400),AND('🔄 Topic Pool'!B17=$B$400,ROUND(('🔄 Topic Pool'!A17-1)/7,0)=$A$400+1)))),'🔄 Topic Pool'!G17,"—") -> — | P97: =IF(AND('🔄 Topic Pool'!P17<>"✅ Done",'🔄 Topic Pool'!M17="✅ YES",NOT(A460=2),NOT(AND(A460=1,OR('🔄 Topic Pool'!P17="❌ Missed",'🔄 Topic Pool'!P17="🔄 Partial"))),IF($C$14="Option 1 — Same Month Only",'🔄 Topic Pool'!B17=$B$400,OR(AND('🔄 Topic Pool'!B17=$B$400,ROUND(('🔄 Topic Pool'!A17-1)/7,0)=$A$400),AND('🔄 Topic Pool'!B17=$B$400,ROUND(('🔄 Topic Pool'!A17-1)/7,0)=$A$400+1)))),'🔄 Topic Pool'!J17,"—") -> — | R97: =IF(AND('🔄 Topic Pool'!P17<>"✅ Done",'🔄 Topic Pool'!M17="✅ YES",NOT(A460=2),NOT(AND(A460=1,OR('🔄 Topic Pool'!P17="❌ Missed",'🔄 Topic Pool'!P17="🔄 Partial"))),IF($C$14="Option 1 — Same Month Only",'🔄 Topic Pool'!B17=$B$400,OR(AND('🔄 Topic Pool'!B17=$B$400,ROUND(('🔄 Topic Pool'!A17-1)/7,0)=$A$400),AND('🔄 Topic Pool'!B17=$B$400,ROUND(('🔄 Topic Pool'!A17-1)/7,0)=$A$400+1)))),COUNTIF('📋 Swap History'!$F$4:$F$200,'🔄 Topic Pool'!D17),"—") -> — | S97: =IF(NOT(AND('🔄 Topic Pool'!P17<>"✅ Done",'🔄 Topic Pool'!M17="✅ YES",NOT(A460=2),NOT(AND(A460=1,OR('🔄 Topic Pool'!P17="❌ Missed",'🔄 Topic Pool'!P17="🔄 Partial"))),IF($C$14="Option 1 — Same Month Only",'🔄 Topic Pool'!B17=$B$400,OR(AND('🔄 Topic Pool'!B17=$B$400,ROUND(('🔄 Topic Pool'!A17-1)/7,0)=$A$400),AND('🔄 Topic Pool'!B17=$B$400,ROUND(('🔄 Topic Pool'!A17-1)/7,0)=$A$400+1))))),"🔒",IF('🔄 Topic Pool'!M17="🔒 NO","🔒",IF(COUNTIF('📋 Swap History'!$F$4:$F$200,'🔄 Topic Pool'!D17)>=$C$8,"🔒","✅"))) -> 🔒 | U97: =IF(AND('🔄 Topic Pool'!P17<>"✅ Done",'🔄 Topic Pool'!M17="✅ YES",NOT(A460=2),NOT(AND(A460=1,OR('🔄 Topic Pool'!P17="❌ Missed",'🔄 Topic Pool'!P17="🔄 Partial"))),IF($C$14="Option 1 — Same Month Only",'🔄 Topic Pool'!B17=$B$400,OR(AND('🔄 Topic Pool'!B17=$B$400,ROUND(('🔄 Topic Pool'!A17-1)/7,0)=$A$400),AND('🔄 Topic Pool'!B17=$B$400,ROUND(('🔄 Topic Pool'!A17-1)/7,0)=$A$400+1)))),'🔄 Topic Pool'!J17&" — Seq "&'🔄 Topic Pool'!C17&" in month","—") -> —
B98: =IF(AND('🔄 Topic Pool'!P24<>"✅ Done",'🔄 Topic Pool'!M24="✅ YES",NOT(A460=2),NOT(AND(A460=1,OR('🔄 Topic Pool'!P24="❌ Missed",'🔄 Topic Pool'!P24="🔄 Partial"))),IF($C$14="Option 1 — Same Month Only",'🔄 Topic Pool'!B24=$B$400,OR(AND('🔄 Topic Pool'!B24=$B$400,ROUND(('🔄 Topic Pool'!A24-1)/7,0)=$A$400),AND('🔄 Topic Pool'!B24=$B$400,ROUND(('🔄 Topic Pool'!A24-1)/7,0)=$A$400+1)))),'🔄 Topic Pool'!A24,"—") -> — | C98: =IF(AND('🔄 Topic Pool'!P24<>"✅ Done",'🔄 Topic Pool'!M24="✅ YES",NOT(A460=2),NOT(AND(A460=1,OR('🔄 Topic Pool'!P24="❌ Missed",'🔄 Topic Pool'!P24="🔄 Partial"))),IF($C$14="Option 1 — Same Month Only",'🔄 Topic Pool'!B24=$B$400,OR(AND('🔄 Topic Pool'!B24=$B$400,ROUND(('🔄 Topic Pool'!A24-1)/7,0)=$A$400),AND('🔄 Topic Pool'!B24=$B$400,ROUND(('🔄 Topic Pool'!A24-1)/7,0)=$A$400+1)))),'🔄 Topic Pool'!D24,"—") -> — | M98: =IF(AND('🔄 Topic Pool'!P24<>"✅ Done",'🔄 Topic Pool'!M24="✅ YES",NOT(A460=2),NOT(AND(A460=1,OR('🔄 Topic Pool'!P24="❌ Missed",'🔄 Topic Pool'!P24="🔄 Partial"))),IF($C$14="Option 1 — Same Month Only",'🔄 Topic Pool'!B24=$B$400,OR(AND('🔄 Topic Pool'!B24=$B$400,ROUND(('🔄 Topic Pool'!A24-1)/7,0)=$A$400),AND('🔄 Topic Pool'!B24=$B$400,ROUND(('🔄 Topic Pool'!A24-1)/7,0)=$A$400+1)))),'🔄 Topic Pool'!E24,"—") -> — | O98: =IF(AND('🔄 Topic Pool'!P24<>"✅ Done",'🔄 Topic Pool'!M24="✅ YES",NOT(A460=2),NOT(AND(A460=1,OR('🔄 Topic Pool'!P24="❌ Missed",'🔄 Topic Pool'!P24="🔄 Partial"))),IF($C$14="Option 1 — Same Month Only",'🔄 Topic Pool'!B24=$B$400,OR(AND('🔄 Topic Pool'!B24=$B$400,ROUND(('🔄 Topic Pool'!A24-1)/7,0)=$A$400),AND('🔄 Topic Pool'!B24=$B$400,ROUND(('🔄 Topic Pool'!A24-1)/7,0)=$A$400+1)))),'🔄 Topic Pool'!G24,"—") -> — | P98: =IF(AND('🔄 Topic Pool'!P24<>"✅ Done",'🔄 Topic Pool'!M24="✅ YES",NOT(A460=2),NOT(AND(A460=1,OR('🔄 Topic Pool'!P24="❌ Missed",'🔄 Topic Pool'!P24="🔄 Partial"))),IF($C$14="Option 1 — Same Month Only",'🔄 Topic Pool'!B24=$B$400,OR(AND('🔄 Topic Pool'!B24=$B$400,ROUND(('🔄 Topic Pool'!A24-1)/7,0)=$A$400),AND('🔄 Topic Pool'!B24=$B$400,ROUND(('🔄 Topic Pool'!A24-1)/7,0)=$A$400+1)))),'🔄 Topic Pool'!J24,"—") -> — | R98: =IF(AND('🔄 Topic Pool'!P24<>"✅ Done",'🔄 Topic Pool'!M24="✅ YES",NOT(A460=2),NOT(AND(A460=1,OR('🔄 Topic Pool'!P24="❌ Missed",'🔄 Topic Pool'!P24="🔄 Partial"))),IF($C$14="Option 1 — Same Month Only",'🔄 Topic Pool'!B24=$B$400,OR(AND('🔄 Topic Pool'!B24=$B$400,ROUND(('🔄 Topic Pool'!A24-1)/7,0)=$A$400),AND('🔄 Topic Pool'!B24=$B$400,ROUND(('🔄 Topic Pool'!A24-1)/7,0)=$A$400+1)))),COUNTIF('📋 Swap History'!$F$4:$F$200,'🔄 Topic Pool'!D24),"—") -> — | S98: =IF(NOT(AND('🔄 Topic Pool'!P24<>"✅ Done",'🔄 Topic Pool'!M24="✅ YES",NOT(A460=2),NOT(AND(A460=1,OR('🔄 Topic Pool'!P24="❌ Missed",'🔄 Topic Pool'!P24="🔄 Partial"))),IF($C$14="Option 1 — Same Month Only",'🔄 Topic Pool'!B24=$B$400,OR(AND('🔄 Topic Pool'!B24=$B$400,ROUND(('🔄 Topic Pool'!A24-1)/7,0)=$A$400),AND('🔄 Topic Pool'!B24=$B$400,ROUND(('🔄 Topic Pool'!A24-1)/7,0)=$A$400+1))))),"🔒",IF('🔄 Topic Pool'!M24="🔒 NO","🔒",IF(COUNTIF('📋 Swap History'!$F$4:$F$200,'🔄 Topic Pool'!D24)>=$C$8,"🔒","✅"))) -> 🔒 | U98: =IF(AND('🔄 Topic Pool'!P24<>"✅ Done",'🔄 Topic Pool'!M24="✅ YES",NOT(A460=2),NOT(AND(A460=1,OR('🔄 Topic Pool'!P24="❌ Missed",'🔄 Topic Pool'!P24="🔄 Partial"))),IF($C$14="Option 1 — Same Month Only",'🔄 Topic Pool'!B24=$B$400,OR(AND('🔄 Topic Pool'!B24=$B$400,ROUND(('🔄 Topic Pool'!A24-1)/7,0)=$A$400),AND('🔄 Topic Pool'!B24=$B$400,ROUND(('🔄 Topic Pool'!A24-1)/7,0)=$A$400+1)))),'🔄 Topic Pool'!J24&" — Seq "&'🔄 Topic Pool'!C24&" in month","—") -> —
B99: =IF(AND('🔄 Topic Pool'!P31<>"✅ Done",'🔄 Topic Pool'!M31="✅ YES",NOT(A460=2),NOT(AND(A460=1,OR('🔄 Topic Pool'!P31="❌ Missed",'🔄 Topic Pool'!P31="🔄 Partial"))),IF($C$14="Option 1 — Same Month Only",'🔄 Topic Pool'!B31=$B$400,OR(AND('🔄 Topic Pool'!B31=$B$400,ROUND(('🔄 Topic Pool'!A31-1)/7,0)=$A$400),AND('🔄 Topic Pool'!B31=$B$400,ROUND(('🔄 Topic Pool'!A31-1)/7,0)=$A$400+1)))),'🔄 Topic Pool'!A31,"—") -> — | C99: =IF(AND('🔄 Topic Pool'!P31<>"✅ Done",'🔄 Topic Pool'!M31="✅ YES",NOT(A460=2),NOT(AND(A460=1,OR('🔄 Topic Pool'!P31="❌ Missed",'🔄 Topic Pool'!P31="🔄 Partial"))),IF($C$14="Option 1 — Same Month Only",'🔄 Topic Pool'!B31=$B$400,OR(AND('🔄 Topic Pool'!B31=$B$400,ROUND(('🔄 Topic Pool'!A31-1)/7,0)=$A$400),AND('🔄 Topic Pool'!B31=$B$400,ROUND(('🔄 Topic Pool'!A31-1)/7,0)=$A$400+1)))),'🔄 Topic Pool'!D31,"—") -> — | M99: =IF(AND('🔄 Topic Pool'!P31<>"✅ Done",'🔄 Topic Pool'!M31="✅ YES",NOT(A460=2),NOT(AND(A460=1,OR('🔄 Topic Pool'!P31="❌ Missed",'🔄 Topic Pool'!P31="🔄 Partial"))),IF($C$14="Option 1 — Same Month Only",'🔄 Topic Pool'!B31=$B$400,OR(AND('🔄 Topic Pool'!B31=$B$400,ROUND(('🔄 Topic Pool'!A31-1)/7,0)=$A$400),AND('🔄 Topic Pool'!B31=$B$400,ROUND(('🔄 Topic Pool'!A31-1)/7,0)=$A$400+1)))),'🔄 Topic Pool'!E31,"—") -> — | O99: =IF(AND('🔄 Topic Pool'!P31<>"✅ Done",'🔄 Topic Pool'!M31="✅ YES",NOT(A460=2),NOT(AND(A460=1,OR('🔄 Topic Pool'!P31="❌ Missed",'🔄 Topic Pool'!P31="🔄 Partial"))),IF($C$14="Option 1 — Same Month Only",'🔄 Topic Pool'!B31=$B$400,OR(AND('🔄 Topic Pool'!B31=$B$400,ROUND(('🔄 Topic Pool'!A31-1)/7,0)=$A$400),AND('🔄 Topic Pool'!B31=$B$400,ROUND(('🔄 Topic Pool'!A31-1)/7,0)=$A$400+1)))),'🔄 Topic Pool'!G31,"—") -> — | P99: =IF(AND('🔄 Topic Pool'!P31<>"✅ Done",'🔄 Topic Pool'!M31="✅ YES",NOT(A460=2),NOT(AND(A460=1,OR('🔄 Topic Pool'!P31="❌ Missed",'🔄 Topic Pool'!P31="🔄 Partial"))),IF($C$14="Option 1 — Same Month Only",'🔄 Topic Pool'!B31=$B$400,OR(AND('🔄 Topic Pool'!B31=$B$400,ROUND(('🔄 Topic Pool'!A31-1)/7,0)=$A$400),AND('🔄 Topic Pool'!B31=$B$400,ROUND(('🔄 Topic Pool'!A31-1)/7,0)=$A$400+1)))),'🔄 Topic Pool'!J31,"—") -> — | R99: =IF(AND('🔄 Topic Pool'!P31<>"✅ Done",'🔄 Topic Pool'!M31="✅ YES",NOT(A460=2),NOT(AND(A460=1,OR('🔄 Topic Pool'!P31="❌ Missed",'🔄 Topic Pool'!P31="🔄 Partial"))),IF($C$14="Option 1 — Same Month Only",'🔄 Topic Pool'!B31=$B$400,OR(AND('🔄 Topic Pool'!B31=$B$400,ROUND(('🔄 Topic Pool'!A31-1)/7,0)=$A$400),AND('🔄 Topic Pool'!B31=$B$400,ROUND(('🔄 Topic Pool'!A31-1)/7,0)=$A$400+1)))),COUNTIF('📋 Swap History'!$F$4:$F$200,'🔄 Topic Pool'!D31),"—") -> — | S99: =IF(NOT(AND('🔄 Topic Pool'!P31<>"✅ Done",'🔄 Topic Pool'!M31="✅ YES",NOT(A460=2),NOT(AND(A460=1,OR('🔄 Topic Pool'!P31="❌ Missed",'🔄 Topic Pool'!P31="🔄 Partial"))),IF($C$14="Option 1 — Same Month Only",'🔄 Topic Pool'!B31=$B$400,OR(AND('🔄 Topic Pool'!B31=$B$400,ROUND(('🔄 Topic Pool'!A31-1)/7,0)=$A$400),AND('🔄 Topic Pool'!B31=$B$400,ROUND(('🔄 Topic Pool'!A31-1)/7,0)=$A$400+1))))),"🔒",IF('🔄 Topic Pool'!M31="🔒 NO","🔒",IF(COUNTIF('📋 Swap History'!$F$4:$F$200,'🔄 Topic Pool'!D31)>=$C$8,"🔒","✅"))) -> 🔒 | U99: =IF(AND('🔄 Topic Pool'!P31<>"✅ Done",'🔄 Topic Pool'!M31="✅ YES",NOT(A460=2),NOT(AND(A460=1,OR('🔄 Topic Pool'!P31="❌ Missed",'🔄 Topic Pool'!P31="🔄 Partial"))),IF($C$14="Option 1 — Same Month Only",'🔄 Topic Pool'!B31=$B$400,OR(AND('🔄 Topic Pool'!B31=$B$400,ROUND(('🔄 Topic Pool'!A31-1)/7,0)=$A$400),AND('🔄 Topic Pool'!B31=$B$400,ROUND(('🔄 Topic Pool'!A31-1)/7,0)=$A$400+1)))),'🔄 Topic Pool'!J31&" — Seq "&'🔄 Topic Pool'!C31&" in month","—") -> —
B100: =IF(AND('🔄 Topic Pool'!P32<>"✅ Done",'🔄 Topic Pool'!M32="✅ YES",NOT(A460=2),NOT(AND(A460=1,OR('🔄 Topic Pool'!P32="❌ Missed",'🔄 Topic Pool'!P32="🔄 Partial"))),IF($C$14="Option 1 — Same Month Only",'🔄 Topic Pool'!B32=$B$400,OR(AND('🔄 Topic Pool'!B32=$B$400,ROUND(('🔄 Topic Pool'!A32-1)/7,0)=$A$400),AND('🔄 Topic Pool'!B32=$B$400,ROUND(('🔄 Topic Pool'!A32-1)/7,0)=$A$400+1)))),'🔄 Topic Pool'!A32,"—") -> — | C100: =IF(AND('🔄 Topic Pool'!P32<>"✅ Done",'🔄 Topic Pool'!M32="✅ YES",NOT(A460=2),NOT(AND(A460=1,OR('🔄 Topic Pool'!P32="❌ Missed",'🔄 Topic Pool'!P32="🔄 Partial"))),IF($C$14="Option 1 — Same Month Only",'🔄 Topic Pool'!B32=$B$400,OR(AND('🔄 Topic Pool'!B32=$B$400,ROUND(('🔄 Topic Pool'!A32-1)/7,0)=$A$400),AND('🔄 Topic Pool'!B32=$B$400,ROUND(('🔄 Topic Pool'!A32-1)/7,0)=$A$400+1)))),'🔄 Topic Pool'!D32,"—") -> — | M100: =IF(AND('🔄 Topic Pool'!P32<>"✅ Done",'🔄 Topic Pool'!M32="✅ YES",NOT(A460=2),NOT(AND(A460=1,OR('🔄 Topic Pool'!P32="❌ Missed",'🔄 Topic Pool'!P32="🔄 Partial"))),IF($C$14="Option 1 — Same Month Only",'🔄 Topic Pool'!B32=$B$400,OR(AND('🔄 Topic Pool'!B32=$B$400,ROUND(('🔄 Topic Pool'!A32-1)/7,0)=$A$400),AND('🔄 Topic Pool'!B32=$B$400,ROUND(('🔄 Topic Pool'!A32-1)/7,0)=$A$400+1)))),'🔄 Topic Pool'!E32,"—") -> — | O100: =IF(AND('🔄 Topic Pool'!P32<>"✅ Done",'🔄 Topic Pool'!M32="✅ YES",NOT(A460=2),NOT(AND(A460=1,OR('🔄 Topic Pool'!P32="❌ Missed",'🔄 Topic Pool'!P32="🔄 Partial"))),IF($C$14="Option 1 — Same Month Only",'🔄 Topic Pool'!B32=$B$400,OR(AND('🔄 Topic Pool'!B32=$B$400,ROUND(('🔄 Topic Pool'!A32-1)/7,0)=$A$400),AND('🔄 Topic Pool'!B32=$B$400,ROUND(('🔄 Topic Pool'!A32-1)/7,0)=$A$400+1)))),'🔄 Topic Pool'!G32,"—") -> — | P100: =IF(AND('🔄 Topic Pool'!P32<>"✅ Done",'🔄 Topic Pool'!M32="✅ YES",NOT(A460=2),NOT(AND(A460=1,OR('🔄 Topic Pool'!P32="❌ Missed",'🔄 Topic Pool'!P32="🔄 Partial"))),IF($C$14="Option 1 — Same Month Only",'🔄 Topic Pool'!B32=$B$400,OR(AND('🔄 Topic Pool'!B32=$B$400,ROUND(('🔄 Topic Pool'!A32-1)/7,0)=$A$400),AND('🔄 Topic Pool'!B32=$B$400,ROUND(('🔄 Topic Pool'!A32-1)/7,0)=$A$400+1)))),'🔄 Topic Pool'!J32,"—") -> — | R100: =IF(AND('🔄 Topic Pool'!P32<>"✅ Done",'🔄 Topic Pool'!M32="✅ YES",NOT(A460=2),NOT(AND(A460=1,OR('🔄 Topic Pool'!P32="❌ Missed",'🔄 Topic Pool'!P32="🔄 Partial"))),IF($C$14="Option 1 — Same Month Only",'🔄 Topic Pool'!B32=$B$400,OR(AND('🔄 Topic Pool'!B32=$B$400,ROUND(('🔄 Topic Pool'!A32-1)/7,0)=$A$400),AND('🔄 Topic Pool'!B32=$B$400,ROUND(('🔄 Topic Pool'!A32-1)/7,0)=$A$400+1)))),COUNTIF('📋 Swap History'!$F$4:$F$200,'🔄 Topic Pool'!D32),"—") -> — | S100: =IF(NOT(AND('🔄 Topic Pool'!P32<>"✅ Done",'🔄 Topic Pool'!M32="✅ YES",NOT(A460=2),NOT(AND(A460=1,OR('🔄 Topic Pool'!P32="❌ Missed",'🔄 Topic Pool'!P32="🔄 Partial"))),IF($C$14="Option 1 — Same Month Only",'🔄 Topic Pool'!B32=$B$400,OR(AND('🔄 Topic Pool'!B32=$B$400,ROUND(('🔄 Topic Pool'!A32-1)/7,0)=$A$400),AND('🔄 Topic Pool'!B32=$B$400,ROUND(('🔄 Topic Pool'!A32-1)/7,0)=$A$400+1))))),"🔒",IF('🔄 Topic Pool'!M32="🔒 NO","🔒",IF(COUNTIF('📋 Swap History'!$F$4:$F$200,'🔄 Topic Pool'!D32)>=$C$8,"🔒","✅"))) -> 🔒 | U100: =IF(AND('🔄 Topic Pool'!P32<>"✅ Done",'🔄 Topic Pool'!M32="✅ YES",NOT(A460=2),NOT(AND(A460=1,OR('🔄 Topic Pool'!P32="❌ Missed",'🔄 Topic Pool'!P32="🔄 Partial"))),IF($C$14="Option 1 — Same Month Only",'🔄 Topic Pool'!B32=$B$400,OR(AND('🔄 Topic Pool'!B32=$B$400,ROUND(('🔄 Topic Pool'!A32-1)/7,0)=$A$400),AND('🔄 Topic Pool'!B32=$B$400,ROUND(('🔄 Topic Pool'!A32-1)/7,0)=$A$400+1)))),'🔄 Topic Pool'!J32&" — Seq "&'🔄 Topic Pool'!C32&" in month","—") -> —
B101: =IF(AND('🔄 Topic Pool'!P33<>"✅ Done",'🔄 Topic Pool'!M33="✅ YES",NOT(A460=2),NOT(AND(A460=1,OR('🔄 Topic Pool'!P33="❌ Missed",'🔄 Topic Pool'!P33="🔄 Partial"))),IF($C$14="Option 1 — Same Month Only",'🔄 Topic Pool'!B33=$B$400,OR(AND('🔄 Topic Pool'!B33=$B$400,ROUND(('🔄 Topic Pool'!A33-1)/7,0)=$A$400),AND('🔄 Topic Pool'!B33=$B$400,ROUND(('🔄 Topic Pool'!A33-1)/7,0)=$A$400+1)))),'🔄 Topic Pool'!A33,"—") -> — | C101: =IF(AND('🔄 Topic Pool'!P33<>"✅ Done",'🔄 Topic Pool'!M33="✅ YES",NOT(A460=2),NOT(AND(A460=1,OR('🔄 Topic Pool'!P33="❌ Missed",'🔄 Topic Pool'!P33="🔄 Partial"))),IF($C$14="Option 1 — Same Month Only",'🔄 Topic Pool'!B33=$B$400,OR(AND('🔄 Topic Pool'!B33=$B$400,ROUND(('🔄 Topic Pool'!A33-1)/7,0)=$A$400),AND('🔄 Topic Pool'!B33=$B$400,ROUND(('🔄 Topic Pool'!A33-1)/7,0)=$A$400+1)))),'🔄 Topic Pool'!D33,"—") -> — | M101: =IF(AND('🔄 Topic Pool'!P33<>"✅ Done",'🔄 Topic Pool'!M33="✅ YES",NOT(A460=2),NOT(AND(A460=1,OR('🔄 Topic Pool'!P33="❌ Missed",'🔄 Topic Pool'!P33="🔄 Partial"))),IF($C$14="Option 1 — Same Month Only",'🔄 Topic Pool'!B33=$B$400,OR(AND('🔄 Topic Pool'!B33=$B$400,ROUND(('🔄 Topic Pool'!A33-1)/7,0)=$A$400),AND('🔄 Topic Pool'!B33=$B$400,ROUND(('🔄 Topic Pool'!A33-1)/7,0)=$A$400+1)))),'🔄 Topic Pool'!E33,"—") -> — | O101: =IF(AND('🔄 Topic Pool'!P33<>"✅ Done",'🔄 Topic Pool'!M33="✅ YES",NOT(A460=2),NOT(AND(A460=1,OR('🔄 Topic Pool'!P33="❌ Missed",'🔄 Topic Pool'!P33="🔄 Partial"))),IF($C$14="Option 1 — Same Month Only",'🔄 Topic Pool'!B33=$B$400,OR(AND('🔄 Topic Pool'!B33=$B$400,ROUND(('🔄 Topic Pool'!A33-1)/7,0)=$A$400),AND('🔄 Topic Pool'!B33=$B$400,ROUND(('🔄 Topic Pool'!A33-1)/7,0)=$A$400+1)))),'🔄 Topic Pool'!G33,"—") -> — | P101: =IF(AND('🔄 Topic Pool'!P33<>"✅ Done",'🔄 Topic Pool'!M33="✅ YES",NOT(A460=2),NOT(AND(A460=1,OR('🔄 Topic Pool'!P33="❌ Missed",'🔄 Topic Pool'!P33="🔄 Partial"))),IF($C$14="Option 1 — Same Month Only",'🔄 Topic Pool'!B33=$B$400,OR(AND('🔄 Topic Pool'!B33=$B$400,ROUND(('🔄 Topic Pool'!A33-1)/7,0)=$A$400),AND('🔄 Topic Pool'!B33=$B$400,ROUND(('🔄 Topic Pool'!A33-1)/7,0)=$A$400+1)))),'🔄 Topic Pool'!J33,"—") -> — | R101: =IF(AND('🔄 Topic Pool'!P33<>"✅ Done",'🔄 Topic Pool'!M33="✅ YES",NOT(A460=2),NOT(AND(A460=1,OR('🔄 Topic Pool'!P33="❌ Missed",'🔄 Topic Pool'!P33="🔄 Partial"))),IF($C$14="Option 1 — Same Month Only",'🔄 Topic Pool'!B33=$B$400,OR(AND('🔄 Topic Pool'!B33=$B$400,ROUND(('🔄 Topic Pool'!A33-1)/7,0)=$A$400),AND('🔄 Topic Pool'!B33=$B$400,ROUND(('🔄 Topic Pool'!A33-1)/7,0)=$A$400+1)))),COUNTIF('📋 Swap History'!$F$4:$F$200,'🔄 Topic Pool'!D33),"—") -> — | S101: =IF(NOT(AND('🔄 Topic Pool'!P33<>"✅ Done",'🔄 Topic Pool'!M33="✅ YES",NOT(A460=2),NOT(AND(A460=1,OR('🔄 Topic Pool'!P33="❌ Missed",'🔄 Topic Pool'!P33="🔄 Partial"))),IF($C$14="Option 1 — Same Month Only",'🔄 Topic Pool'!B33=$B$400,OR(AND('🔄 Topic Pool'!B33=$B$400,ROUND(('🔄 Topic Pool'!A33-1)/7,0)=$A$400),AND('🔄 Topic Pool'!B33=$B$400,ROUND(('🔄 Topic Pool'!A33-1)/7,0)=$A$400+1))))),"🔒",IF('🔄 Topic Pool'!M33="🔒 NO","🔒",IF(COUNTIF('📋 Swap History'!$F$4:$F$200,'🔄 Topic Pool'!D33)>=$C$8,"🔒","✅"))) -> 🔒 | U101: =IF(AND('🔄 Topic Pool'!P33<>"✅ Done",'🔄 Topic Pool'!M33="✅ YES",NOT(A460=2),NOT(AND(A460=1,OR('🔄 Topic Pool'!P33="❌ Missed",'🔄 Topic Pool'!P33="🔄 Partial"))),IF($C$14="Option 1 — Same Month Only",'🔄 Topic Pool'!B33=$B$400,OR(AND('🔄 Topic Pool'!B33=$B$400,ROUND(('🔄 Topic Pool'!A33-1)/7,0)=$A$400),AND('🔄 Topic Pool'!B33=$B$400,ROUND(('🔄 Topic Pool'!A33-1)/7,0)=$A$400+1)))),'🔄 Topic Pool'!J33&" — Seq "&'🔄 Topic Pool'!C33&" in month","—") -> —
B102: =IF(AND('🔄 Topic Pool'!P34<>"✅ Done",'🔄 Topic Pool'!M34="✅ YES",NOT(A460=2),NOT(AND(A460=1,OR('🔄 Topic Pool'!P34="❌ Missed",'🔄 Topic Pool'!P34="🔄 Partial"))),IF($C$14="Option 1 — Same Month Only",'🔄 Topic Pool'!B34=$B$400,OR(AND('🔄 Topic Pool'!B34=$B$400,ROUND(('🔄 Topic Pool'!A34-1)/7,0)=$A$400),AND('🔄 Topic Pool'!B34=$B$400,ROUND(('🔄 Topic Pool'!A34-1)/7,0)=$A$400+1)))),'🔄 Topic Pool'!A34,"—") -> — | C102: =IF(AND('🔄 Topic Pool'!P34<>"✅ Done",'🔄 Topic Pool'!M34="✅ YES",NOT(A460=2),NOT(AND(A460=1,OR('🔄 Topic Pool'!P34="❌ Missed",'🔄 Topic Pool'!P34="🔄 Partial"))),IF($C$14="Option 1 — Same Month Only",'🔄 Topic Pool'!B34=$B$400,OR(AND('🔄 Topic Pool'!B34=$B$400,ROUND(('🔄 Topic Pool'!A34-1)/7,0)=$A$400),AND('🔄 Topic Pool'!B34=$B$400,ROUND(('🔄 Topic Pool'!A34-1)/7,0)=$A$400+1)))),'🔄 Topic Pool'!D34,"—") -> — | M102: =IF(AND('🔄 Topic Pool'!P34<>"✅ Done",'🔄 Topic Pool'!M34="✅ YES",NOT(A460=2),NOT(AND(A460=1,OR('🔄 Topic Pool'!P34="❌ Missed",'🔄 Topic Pool'!P34="🔄 Partial"))),IF($C$14="Option 1 — Same Month Only",'🔄 Topic Pool'!B34=$B$400,OR(AND('🔄 Topic Pool'!B34=$B$400,ROUND(('🔄 Topic Pool'!A34-1)/7,0)=$A$400),AND('🔄 Topic Pool'!B34=$B$400,ROUND(('🔄 Topic Pool'!A34-1)/7,0)=$A$400+1)))),'🔄 Topic Pool'!E34,"—") -> — | O102: =IF(AND('🔄 Topic Pool'!P34<>"✅ Done",'🔄 Topic Pool'!M34="✅ YES",NOT(A460=2),NOT(AND(A460=1,OR('🔄 Topic Pool'!P34="❌ Missed",'🔄 Topic Pool'!P34="🔄 Partial"))),IF($C$14="Option 1 — Same Month Only",'🔄 Topic Pool'!B34=$B$400,OR(AND('🔄 Topic Pool'!B34=$B$400,ROUND(('🔄 Topic Pool'!A34-1)/7,0)=$A$400),AND('🔄 Topic Pool'!B34=$B$400,ROUND(('🔄 Topic Pool'!A34-1)/7,0)=$A$400+1)))),'🔄 Topic Pool'!G34,"—") -> — | P102: =IF(AND('🔄 Topic Pool'!P34<>"✅ Done",'🔄 Topic Pool'!M34="✅ YES",NOT(A460=2),NOT(AND(A460=1,OR('🔄 Topic Pool'!P34="❌ Missed",'🔄 Topic Pool'!P34="🔄 Partial"))),IF($C$14="Option 1 — Same Month Only",'🔄 Topic Pool'!B34=$B$400,OR(AND('🔄 Topic Pool'!B34=$B$400,ROUND(('🔄 Topic Pool'!A34-1)/7,0)=$A$400),AND('🔄 Topic Pool'!B34=$B$400,ROUND(('🔄 Topic Pool'!A34-1)/7,0)=$A$400+1)))),'🔄 Topic Pool'!J34,"—") -> — | R102: =IF(AND('🔄 Topic Pool'!P34<>"✅ Done",'🔄 Topic Pool'!M34="✅ YES",NOT(A460=2),NOT(AND(A460=1,OR('🔄 Topic Pool'!P34="❌ Missed",'🔄 Topic Pool'!P34="🔄 Partial"))),IF($C$14="Option 1 — Same Month Only",'🔄 Topic Pool'!B34=$B$400,OR(AND('🔄 Topic Pool'!B34=$B$400,ROUND(('🔄 Topic Pool'!A34-1)/7,0)=$A$400),AND('🔄 Topic Pool'!B34=$B$400,ROUND(('🔄 Topic Pool'!A34-1)/7,0)=$A$400+1)))),COUNTIF('📋 Swap History'!$F$4:$F$200,'🔄 Topic Pool'!D34),"—") -> — | S102: =IF(NOT(AND('🔄 Topic Pool'!P34<>"✅ Done",'🔄 Topic Pool'!M34="✅ YES",NOT(A460=2),NOT(AND(A460=1,OR('🔄 Topic Pool'!P34="❌ Missed",'🔄 Topic Pool'!P34="🔄 Partial"))),IF($C$14="Option 1 — Same Month Only",'🔄 Topic Pool'!B34=$B$400,OR(AND('🔄 Topic Pool'!B34=$B$400,ROUND(('🔄 Topic Pool'!A34-1)/7,0)=$A$400),AND('🔄 Topic Pool'!B34=$B$400,ROUND(('🔄 Topic Pool'!A34-1)/7,0)=$A$400+1))))),"🔒",IF('🔄 Topic Pool'!M34="🔒 NO","🔒",IF(COUNTIF('📋 Swap History'!$F$4:$F$200,'🔄 Topic Pool'!D34)>=$C$8,"🔒","✅"))) -> 🔒 | U102: =IF(AND('🔄 Topic Pool'!P34<>"✅ Done",'🔄 Topic Pool'!M34="✅ YES",NOT(A460=2),NOT(AND(A460=1,OR('🔄 Topic Pool'!P34="❌ Missed",'🔄 Topic Pool'!P34="🔄 Partial"))),IF($C$14="Option 1 — Same Month Only",'🔄 Topic Pool'!B34=$B$400,OR(AND('🔄 Topic Pool'!B34=$B$400,ROUND(('🔄 Topic Pool'!A34-1)/7,0)=$A$400),AND('🔄 Topic Pool'!B34=$B$400,ROUND(('🔄 Topic Pool'!A34-1)/7,0)=$A$400+1)))),'🔄 Topic Pool'!J34&" — Seq "&'🔄 Topic Pool'!C34&" in month","—") -> —
B103: =IF(AND('🔄 Topic Pool'!P35<>"✅ Done",'🔄 Topic Pool'!M35="✅ YES",NOT(A460=2),NOT(AND(A460=1,OR('🔄 Topic Pool'!P35="❌ Missed",'🔄 Topic Pool'!P35="🔄 Partial"))),IF($C$14="Option 1 — Same Month Only",'🔄 Topic Pool'!B35=$B$400,OR(AND('🔄 Topic Pool'!B35=$B$400,ROUND(('🔄 Topic Pool'!A35-1)/7,0)=$A$400),AND('🔄 Topic Pool'!B35=$B$400,ROUND(('🔄 Topic Pool'!A35-1)/7,0)=$A$400+1)))),'🔄 Topic Pool'!A35,"—") -> — | C103: =IF(AND('🔄 Topic Pool'!P35<>"✅ Done",'🔄 Topic Pool'!M35="✅ YES",NOT(A460=2),NOT(AND(A460=1,OR('🔄 Topic Pool'!P35="❌ Missed",'🔄 Topic Pool'!P35="🔄 Partial"))),IF($C$14="Option 1 — Same Month Only",'🔄 Topic Pool'!B35=$B$400,OR(AND('🔄 Topic Pool'!B35=$B$400,ROUND(('🔄 Topic Pool'!A35-1)/7,0)=$A$400),AND('🔄 Topic Pool'!B35=$B$400,ROUND(('🔄 Topic Pool'!A35-1)/7,0)=$A$400+1)))),'🔄 Topic Pool'!D35,"—") -> — | M103: =IF(AND('🔄 Topic Pool'!P35<>"✅ Done",'🔄 Topic Pool'!M35="✅ YES",NOT(A460=2),NOT(AND(A460=1,OR('🔄 Topic Pool'!P35="❌ Missed",'🔄 Topic Pool'!P35="🔄 Partial"))),IF($C$14="Option 1 — Same Month Only",'🔄 Topic Pool'!B35=$B$400,OR(AND('🔄 Topic Pool'!B35=$B$400,ROUND(('🔄 Topic Pool'!A35-1)/7,0)=$A$400),AND('🔄 Topic Pool'!B35=$B$400,ROUND(('🔄 Topic Pool'!A35-1)/7,0)=$A$400+1)))),'🔄 Topic Pool'!E35,"—") -> — | O103: =IF(AND('🔄 Topic Pool'!P35<>"✅ Done",'🔄 Topic Pool'!M35="✅ YES",NOT(A460=2),NOT(AND(A460=1,OR('🔄 Topic Pool'!P35="❌ Missed",'🔄 Topic Pool'!P35="🔄 Partial"))),IF($C$14="Option 1 — Same Month Only",'🔄 Topic Pool'!B35=$B$400,OR(AND('🔄 Topic Pool'!B35=$B$400,ROUND(('🔄 Topic Pool'!A35-1)/7,0)=$A$400),AND('🔄 Topic Pool'!B35=$B$400,ROUND(('🔄 Topic Pool'!A35-1)/7,0)=$A$400+1)))),'🔄 Topic Pool'!G35,"—") -> — | P103: =IF(AND('🔄 Topic Pool'!P35<>"✅ Done",'🔄 Topic Pool'!M35="✅ YES",NOT(A460=2),NOT(AND(A460=1,OR('🔄 Topic Pool'!P35="❌ Missed",'🔄 Topic Pool'!P35="🔄 Partial"))),IF($C$14="Option 1 — Same Month Only",'🔄 Topic Pool'!B35=$B$400,OR(AND('🔄 Topic Pool'!B35=$B$400,ROUND(('🔄 Topic Pool'!A35-1)/7,0)=$A$400),AND('🔄 Topic Pool'!B35=$B$400,ROUND(('🔄 Topic Pool'!A35-1)/7,0)=$A$400+1)))),'🔄 Topic Pool'!J35,"—") -> — | R103: =IF(AND('🔄 Topic Pool'!P35<>"✅ Done",'🔄 Topic Pool'!M35="✅ YES",NOT(A460=2),NOT(AND(A460=1,OR('🔄 Topic Pool'!P35="❌ Missed",'🔄 Topic Pool'!P35="🔄 Partial"))),IF($C$14="Option 1 — Same Month Only",'🔄 Topic Pool'!B35=$B$400,OR(AND('🔄 Topic Pool'!B35=$B$400,ROUND(('🔄 Topic Pool'!A35-1)/7,0)=$A$400),AND('🔄 Topic Pool'!B35=$B$400,ROUND(('🔄 Topic Pool'!A35-1)/7,0)=$A$400+1)))),COUNTIF('📋 Swap History'!$F$4:$F$200,'🔄 Topic Pool'!D35),"—") -> — | S103: =IF(NOT(AND('🔄 Topic Pool'!P35<>"✅ Done",'🔄 Topic Pool'!M35="✅ YES",NOT(A460=2),NOT(AND(A460=1,OR('🔄 Topic Pool'!P35="❌ Missed",'🔄 Topic Pool'!P35="🔄 Partial"))),IF($C$14="Option 1 — Same Month Only",'🔄 Topic Pool'!B35=$B$400,OR(AND('🔄 Topic Pool'!B35=$B$400,ROUND(('🔄 Topic Pool'!A35-1)/7,0)=$A$400),AND('🔄 Topic Pool'!B35=$B$400,ROUND(('🔄 Topic Pool'!A35-1)/7,0)=$A$400+1))))),"🔒",IF('🔄 Topic Pool'!M35="🔒 NO","🔒",IF(COUNTIF('📋 Swap History'!$F$4:$F$200,'🔄 Topic Pool'!D35)>=$C$8,"🔒","✅"))) -> 🔒 | U103: =IF(AND('🔄 Topic Pool'!P35<>"✅ Done",'🔄 Topic Pool'!M35="✅ YES",NOT(A460=2),NOT(AND(A460=1,OR('🔄 Topic Pool'!P35="❌ Missed",'🔄 Topic Pool'!P35="🔄 Partial"))),IF($C$14="Option 1 — Same Month Only",'🔄 Topic Pool'!B35=$B$400,OR(AND('🔄 Topic Pool'!B35=$B$400,ROUND(('🔄 Topic Pool'!A35-1)/7,0)=$A$400),AND('🔄 Topic Pool'!B35=$B$400,ROUND(('🔄 Topic Pool'!A35-1)/7,0)=$A$400+1)))),'🔄 Topic Pool'!J35&" — Seq "&'🔄 Topic Pool'!C35&" in month","—") -> —
B104: =IF(AND('🔄 Topic Pool'!P37<>"✅ Done",'🔄 Topic Pool'!M37="✅ YES",NOT(A460=2),NOT(AND(A460=1,OR('🔄 Topic Pool'!P37="❌ Missed",'🔄 Topic Pool'!P37="🔄 Partial"))),IF($C$14="Option 1 — Same Month Only",'🔄 Topic Pool'!B37=$B$400,OR(AND('🔄 Topic Pool'!B37=$B$400,ROUND(('🔄 Topic Pool'!A37-1)/7,0)=$A$400),AND('🔄 Topic Pool'!B37=$B$400,ROUND(('🔄 Topic Pool'!A37-1)/7,0)=$A$400+1)))),'🔄 Topic Pool'!A37,"—") -> — | C104: =IF(AND('🔄 Topic Pool'!P37<>"✅ Done",'🔄 Topic Pool'!M37="✅ YES",NOT(A460=2),NOT(AND(A460=1,OR('🔄 Topic Pool'!P37="❌ Missed",'🔄 Topic Pool'!P37="🔄 Partial"))),IF($C$14="Option 1 — Same Month Only",'🔄 Topic Pool'!B37=$B$400,OR(AND('🔄 Topic Pool'!B37=$B$400,ROUND(('🔄 Topic Pool'!A37-1)/7,0)=$A$400),AND('🔄 Topic Pool'!B37=$B$400,ROUND(('🔄 Topic Pool'!A37-1)/7,0)=$A$400+1)))),'🔄 Topic Pool'!D37,"—") -> — | M104: =IF(AND('🔄 Topic Pool'!P37<>"✅ Done",'🔄 Topic Pool'!M37="✅ YES",NOT(A460=2),NOT(AND(A460=1,OR('🔄 Topic Pool'!P37="❌ Missed",'🔄 Topic Pool'!P37="🔄 Partial"))),IF($C$14="Option 1 — Same Month Only",'🔄 Topic Pool'!B37=$B$400,OR(AND('🔄 Topic Pool'!B37=$B$400,ROUND(('🔄 Topic Pool'!A37-1)/7,0)=$A$400),AND('🔄 Topic Pool'!B37=$B$400,ROUND(('🔄 Topic Pool'!A37-1)/7,0)=$A$400+1)))),'🔄 Topic Pool'!E37,"—") -> — | O104: =IF(AND('🔄 Topic Pool'!P37<>"✅ Done",'🔄 Topic Pool'!M37="✅ YES",NOT(A460=2),NOT(AND(A460=1,OR('🔄 Topic Pool'!P37="❌ Missed",'🔄 Topic Pool'!P37="🔄 Partial"))),IF($C$14="Option 1 — Same Month Only",'🔄 Topic Pool'!B37=$B$400,OR(AND('🔄 Topic Pool'!B37=$B$400,ROUND(('🔄 Topic Pool'!A37-1)/7,0)=$A$400),AND('🔄 Topic Pool'!B37=$B$400,ROUND(('🔄 Topic Pool'!A37-1)/7,0)=$A$400+1)))),'🔄 Topic Pool'!G37,"—") -> — | P104: =IF(AND('🔄 Topic Pool'!P37<>"✅ Done",'🔄 Topic Pool'!M37="✅ YES",NOT(A460=2),NOT(AND(A460=1,OR('🔄 Topic Pool'!P37="❌ Missed",'🔄 Topic Pool'!P37="🔄 Partial"))),IF($C$14="Option 1 — Same Month Only",'🔄 Topic Pool'!B37=$B$400,OR(AND('🔄 Topic Pool'!B37=$B$400,ROUND(('🔄 Topic Pool'!A37-1)/7,0)=$A$400),AND('🔄 Topic Pool'!B37=$B$400,ROUND(('🔄 Topic Pool'!A37-1)/7,0)=$A$400+1)))),'🔄 Topic Pool'!J37,"—") -> — | R104: =IF(AND('🔄 Topic Pool'!P37<>"✅ Done",'🔄 Topic Pool'!M37="✅ YES",NOT(A460=2),NOT(AND(A460=1,OR('🔄 Topic Pool'!P37="❌ Missed",'🔄 Topic Pool'!P37="🔄 Partial"))),IF($C$14="Option 1 — Same Month Only",'🔄 Topic Pool'!B37=$B$400,OR(AND('🔄 Topic Pool'!B37=$B$400,ROUND(('🔄 Topic Pool'!A37-1)/7,0)=$A$400),AND('🔄 Topic Pool'!B37=$B$400,ROUND(('🔄 Topic Pool'!A37-1)/7,0)=$A$400+1)))),COUNTIF('📋 Swap History'!$F$4:$F$200,'🔄 Topic Pool'!D37),"—") -> — | S104: =IF(NOT(AND('🔄 Topic Pool'!P37<>"✅ Done",'🔄 Topic Pool'!M37="✅ YES",NOT(A460=2),NOT(AND(A460=1,OR('🔄 Topic Pool'!P37="❌ Missed",'🔄 Topic Pool'!P37="🔄 Partial"))),IF($C$14="Option 1 — Same Month Only",'🔄 Topic Pool'!B37=$B$400,OR(AND('🔄 Topic Pool'!B37=$B$400,ROUND(('🔄 Topic Pool'!A37-1)/7,0)=$A$400),AND('🔄 Topic Pool'!B37=$B$400,ROUND(('🔄 Topic Pool'!A37-1)/7,0)=$A$400+1))))),"🔒",IF('🔄 Topic Pool'!M37="🔒 NO","🔒",IF(COUNTIF('📋 Swap History'!$F$4:$F$200,'🔄 Topic Pool'!D37)>=$C$8,"🔒","✅"))) -> 🔒 | U104: =IF(AND('🔄 Topic Pool'!P37<>"✅ Done",'🔄 Topic Pool'!M37="✅ YES",NOT(A460=2),NOT(AND(A460=1,OR('🔄 Topic Pool'!P37="❌ Missed",'🔄 Topic Pool'!P37="🔄 Partial"))),IF($C$14="Option 1 — Same Month Only",'🔄 Topic Pool'!B37=$B$400,OR(AND('🔄 Topic Pool'!B37=$B$400,ROUND(('🔄 Topic Pool'!A37-1)/7,0)=$A$400),AND('🔄 Topic Pool'!B37=$B$400,ROUND(('🔄 Topic Pool'!A37-1)/7,0)=$A$400+1)))),'🔄 Topic Pool'!J37&" — Seq "&'🔄 Topic Pool'!C37&" in month","—") -> —
B105: =IF(AND('🔄 Topic Pool'!P39<>"✅ Done",'🔄 Topic Pool'!M39="✅ YES",NOT(A460=2),NOT(AND(A460=1,OR('🔄 Topic Pool'!P39="❌ Missed",'🔄 Topic Pool'!P39="🔄 Partial"))),IF($C$14="Option 1 — Same Month Only",'🔄 Topic Pool'!B39=$B$400,OR(AND('🔄 Topic Pool'!B39=$B$400,ROUND(('🔄 Topic Pool'!A39-1)/7,0)=$A$400),AND('🔄 Topic Pool'!B39=$B$400,ROUND(('🔄 Topic Pool'!A39-1)/7,0)=$A$400+1)))),'🔄 Topic Pool'!A39,"—") -> — | C105: =IF(AND('🔄 Topic Pool'!P39<>"✅ Done",'🔄 Topic Pool'!M39="✅ YES",NOT(A460=2),NOT(AND(A460=1,OR('🔄 Topic Pool'!P39="❌ Missed",'🔄 Topic Pool'!P39="🔄 Partial"))),IF($C$14="Option 1 — Same Month Only",'🔄 Topic Pool'!B39=$B$400,OR(AND('🔄 Topic Pool'!B39=$B$400,ROUND(('🔄 Topic Pool'!A39-1)/7,0)=$A$400),AND('🔄 Topic Pool'!B39=$B$400,ROUND(('🔄 Topic Pool'!A39-1)/7,0)=$A$400+1)))),'🔄 Topic Pool'!D39,"—") -> — | M105: =IF(AND('🔄 Topic Pool'!P39<>"✅ Done",'🔄 Topic Pool'!M39="✅ YES",NOT(A460=2),NOT(AND(A460=1,OR('🔄 Topic Pool'!P39="❌ Missed",'🔄 Topic Pool'!P39="🔄 Partial"))),IF($C$14="Option 1 — Same Month Only",'🔄 Topic Pool'!B39=$B$400,OR(AND('🔄 Topic Pool'!B39=$B$400,ROUND(('🔄 Topic Pool'!A39-1)/7,0)=$A$400),AND('🔄 Topic Pool'!B39=$B$400,ROUND(('🔄 Topic Pool'!A39-1)/7,0)=$A$400+1)))),'🔄 Topic Pool'!E39,"—") -> — | O105: =IF(AND('🔄 Topic Pool'!P39<>"✅ Done",'🔄 Topic Pool'!M39="✅ YES",NOT(A460=2),NOT(AND(A460=1,OR('🔄 Topic Pool'!P39="❌ Missed",'🔄 Topic Pool'!P39="🔄 Partial"))),IF($C$14="Option 1 — Same Month Only",'🔄 Topic Pool'!B39=$B$400,OR(AND('🔄 Topic Pool'!B39=$B$400,ROUND(('🔄 Topic Pool'!A39-1)/7,0)=$A$400),AND('🔄 Topic Pool'!B39=$B$400,ROUND(('🔄 Topic Pool'!A39-1)/7,0)=$A$400+1)))),'🔄 Topic Pool'!G39,"—") -> — | P105: =IF(AND('🔄 Topic Pool'!P39<>"✅ Done",'🔄 Topic Pool'!M39="✅ YES",NOT(A460=2),NOT(AND(A460=1,OR('🔄 Topic Pool'!P39="❌ Missed",'🔄 Topic Pool'!P39="🔄 Partial"))),IF($C$14="Option 1 — Same Month Only",'🔄 Topic Pool'!B39=$B$400,OR(AND('🔄 Topic Pool'!B39=$B$400,ROUND(('🔄 Topic Pool'!A39-1)/7,0)=$A$400),AND('🔄 Topic Pool'!B39=$B$400,ROUND(('🔄 Topic Pool'!A39-1)/7,0)=$A$400+1)))),'🔄 Topic Pool'!J39,"—") -> — | R105: =IF(AND('🔄 Topic Pool'!P39<>"✅ Done",'🔄 Topic Pool'!M39="✅ YES",NOT(A460=2),NOT(AND(A460=1,OR('🔄 Topic Pool'!P39="❌ Missed",'🔄 Topic Pool'!P39="🔄 Partial"))),IF($C$14="Option 1 — Same Month Only",'🔄 Topic Pool'!B39=$B$400,OR(AND('🔄 Topic Pool'!B39=$B$400,ROUND(('🔄 Topic Pool'!A39-1)/7,0)=$A$400),AND('🔄 Topic Pool'!B39=$B$400,ROUND(('🔄 Topic Pool'!A39-1)/7,0)=$A$400+1)))),COUNTIF('📋 Swap History'!$F$4:$F$200,'🔄 Topic Pool'!D39),"—") -> — | S105: =IF(NOT(AND('🔄 Topic Pool'!P39<>"✅ Done",'🔄 Topic Pool'!M39="✅ YES",NOT(A460=2),NOT(AND(A460=1,OR('🔄 Topic Pool'!P39="❌ Missed",'🔄 Topic Pool'!P39="🔄 Partial"))),IF($C$14="Option 1 — Same Month Only",'🔄 Topic Pool'!B39=$B$400,OR(AND('🔄 Topic Pool'!B39=$B$400,ROUND(('🔄 Topic Pool'!A39-1)/7,0)=$A$400),AND('🔄 Topic Pool'!B39=$B$400,ROUND(('🔄 Topic Pool'!A39-1)/7,0)=$A$400+1))))),"🔒",IF('🔄 Topic Pool'!M39="🔒 NO","🔒",IF(COUNTIF('📋 Swap History'!$F$4:$F$200,'🔄 Topic Pool'!D39)>=$C$8,"🔒","✅"))) -> 🔒 | U105: =IF(AND('🔄 Topic Pool'!P39<>"✅ Done",'🔄 Topic Pool'!M39="✅ YES",NOT(A460=2),NOT(AND(A460=1,OR('🔄 Topic Pool'!P39="❌ Missed",'🔄 Topic Pool'!P39="🔄 Partial"))),IF($C$14="Option 1 — Same Month Only",'🔄 Topic Pool'!B39=$B$400,OR(AND('🔄 Topic Pool'!B39=$B$400,ROUND(('🔄 Topic Pool'!A39-1)/7,0)=$A$400),AND('🔄 Topic Pool'!B39=$B$400,ROUND(('🔄 Topic Pool'!A39-1)/7,0)=$A$400+1)))),'🔄 Topic Pool'!J39&" — Seq "&'🔄 Topic Pool'!C39&" in month","—") -> —
...

Sheet 📝 Daily Log
A1: DAILY LEARNING LOG — Log every session here
B2: Date | C2: Week # | D2: Day | E2: Topic Studied | F2: Phase | G2: Status | H2: Hours | I2: Confidence (1-5) | J2: DSA Problems | K2: Proj / Cert | L2: Notes / Blockers
B3: 46111 | C3: 1 | D3: Mon | E3: Python OOP — Classes & Dunder Methods | F3: M1 - Python/SQL | G3: ✅ Done | H3: 3 | I3: 4 | J3: 15 | L3: Finished Fluent Python Ch.1. Built 3 ETL classes. Felt good about decorators.
B4: 46112 | C4: 1 | D4: Tue | E4: Python OOP — Inheritance & Composition | F4: M1 - Python/SQL | G4: ✅ Done | H4: 2.5 | I4: 3 | J4: 0 | L4: Struggled with MRO. Need to revisit tomorrow.
B5: 46113 | C5: 1 | D5: Wed | E5: Python Advanced — Generators | F5: M1 - Python/SQL | G5: 🔄 Partial | H5: 1.5 | I5: 3 | J5: 8 | L5: Only got through half the generators content. Generator expressions still unclear.
B6: 46114 | C6: 1 | D6: Thu | E6: Python Advanced — Decorators | F6: M1 - Python/SQL | G6: ✅ Done | H6: 2 | I6: 4 | J6: 0 | L6: Decorators clicked today. Built timer + logging decorator for ETL.
B7: 46115 | C7: 1 | D7: Fri | E7: LeetCode — Arrays & Hashing | F7: M1 - Python/SQL | G7: ✅ Done | H7: 1.5 | I7: 4 | J7: 7 | L7: Two Sum, Group Anagrams, Top K Frequent — all solved.

Sheet 📈 Weekly Review
A1: WEEKLY REVIEW — Fill in every Sunday evening
B2: Week | C2: Date | D2: What I completed | E2: Topics I felt confident in | F2: Topics I struggled with | G2: % of plan done | H2: Avg confidence | I2: DSA total | J2: Priorities next week
B3: W1 | C3: 46117 | G3: =IFERROR(COUNTIFS('📝 Daily Log'!C$3:C$500,1,'📝 Daily Log'!G$3:G$500,"✅ Done")/COUNTIF('📝 Daily Log'!C$3:C$500,1),"") -> 0.8 | H3: =IFERROR(AVERAGEIF('📝 Daily Log'!C$3:C$500,1,'📝 Daily Log'!I$3:I$500),"") -> 3.6 | I3: =IFERROR(SUMIF('📝 Daily Log'!C$3:C$500,1,'📝 Daily Log'!J$3:J$500),"") -> 30
B4: W2 | C4: 46124 | G4: =IFERROR(COUNTIFS('📝 Daily Log'!C$3:C$500,2,'📝 Daily Log'!G$3:G$500,"✅ Done")/COUNTIF('📝 Daily Log'!C$3:C$500,2),"") | H4: =IFERROR(AVERAGEIF('📝 Daily Log'!C$3:C$500,2,'📝 Daily Log'!I$3:I$500),"") | I4: =IFERROR(SUMIF('📝 Daily Log'!C$3:C$500,2,'📝 Daily Log'!J$3:J$500),"") -> 0
B5: W3 | C5: 46131 | G5: =IFERROR(COUNTIFS('📝 Daily Log'!C$3:C$500,3,'📝 Daily Log'!G$3:G$500,"✅ Done")/COUNTIF('📝 Daily Log'!C$3:C$500,3),"") | H5: =IFERROR(AVERAGEIF('📝 Daily Log'!C$3:C$500,3,'📝 Daily Log'!I$3:I$500),"") | I5: =IFERROR(SUMIF('📝 Daily Log'!C$3:C$500,3,'📝 Daily Log'!J$3:J$500),"") -> 0
B6: W4 | C6: 46138 | G6: =IFERROR(COUNTIFS('📝 Daily Log'!C$3:C$500,4,'📝 Daily Log'!G$3:G$500,"✅ Done")/COUNTIF('📝 Daily Log'!C$3:C$500,4),"") | H6: =IFERROR(AVERAGEIF('📝 Daily Log'!C$3:C$500,4,'📝 Daily Log'!I$3:I$500),"") | I6: =IFERROR(SUMIF('📝 Daily Log'!C$3:C$500,4,'📝 Daily Log'!J$3:J$500),"") -> 0
B7: W5 | C7: 46145 | G7: =IFERROR(COUNTIFS('📝 Daily Log'!C$3:C$500,5,'📝 Daily Log'!G$3:G$500,"✅ Done")/COUNTIF('📝 Daily Log'!C$3:C$500,5),"") | H7: =IFERROR(AVERAGEIF('📝 Daily Log'!C$3:C$500,5,'📝 Daily Log'!I$3:I$500),"") | I7: =IFERROR(SUMIF('📝 Daily Log'!C$3:C$500,5,'📝 Daily Log'!J$3:J$500),"") -> 0
B8: W6 | C8: 46152 | G8: =IFERROR(COUNTIFS('📝 Daily Log'!C$3:C$500,6,'📝 Daily Log'!G$3:G$500,"✅ Done")/COUNTIF('📝 Daily Log'!C$3:C$500,6),"") | H8: =IFERROR(AVERAGEIF('📝 Daily Log'!C$3:C$500,6,'📝 Daily Log'!I$3:I$500),"") | I8: =IFERROR(SUMIF('📝 Daily Log'!C$3:C$500,6,'📝 Daily Log'!J$3:J$500),"") -> 0
B9: W7 | C9: 46159 | G9: =IFERROR(COUNTIFS('📝 Daily Log'!C$3:C$500,7,'📝 Daily Log'!G$3:G$500,"✅ Done")/COUNTIF('📝 Daily Log'!C$3:C$500,7),"") | H9: =IFERROR(AVERAGEIF('📝 Daily Log'!C$3:C$500,7,'📝 Daily Log'!I$3:I$500),"") | I9: =IFERROR(SUMIF('📝 Daily Log'!C$3:C$500,7,'📝 Daily Log'!J$3:J$500),"") -> 0
B10: W8 | C10: 46166 | G10: =IFERROR(COUNTIFS('📝 Daily Log'!C$3:C$500,8,'📝 Daily Log'!G$3:G$500,"✅ Done")/COUNTIF('📝 Daily Log'!C$3:C$500,8),"") | H10: =IFERROR(AVERAGEIF('📝 Daily Log'!C$3:C$500,8,'📝 Daily Log'!I$3:I$500),"") | I10: =IFERROR(SUMIF('📝 Daily Log'!C$3:C$500,8,'📝 Daily Log'!J$3:J$500),"") -> 0
B11: W9 | C11: 46173 | G11: =IFERROR(COUNTIFS('📝 Daily Log'!C$3:C$500,9,'📝 Daily Log'!G$3:G$500,"✅ Done")/COUNTIF('📝 Daily Log'!C$3:C$500,9),"") | H11: =IFERROR(AVERAGEIF('📝 Daily Log'!C$3:C$500,9,'📝 Daily Log'!I$3:I$500),"") | I11: =IFERROR(SUMIF('📝 Daily Log'!C$3:C$500,9,'📝 Daily Log'!J$3:J$500),"") -> 0
B12: W10 | C12: 46180 | G12: =IFERROR(COUNTIFS('📝 Daily Log'!C$3:C$500,10,'📝 Daily Log'!G$3:G$500,"✅ Done")/COUNTIF('📝 Daily Log'!C$3:C$500,10),"") | H12: =IFERROR(AVERAGEIF('📝 Daily Log'!C$3:C$500,10,'📝 Daily Log'!I$3:I$500),"") | I12: =IFERROR(SUMIF('📝 Daily Log'!C$3:C$500,10,'📝 Daily Log'!J$3:J$500),"") -> 0
B13: W11 | C13: 46187 | G13: =IFERROR(COUNTIFS('📝 Daily Log'!C$3:C$500,11,'📝 Daily Log'!G$3:G$500,"✅ Done")/COUNTIF('📝 Daily Log'!C$3:C$500,11),"") | H13: =IFERROR(AVERAGEIF('📝 Daily Log'!C$3:C$500,11,'📝 Daily Log'!I$3:I$500),"") | I13: =IFERROR(SUMIF('📝 Daily Log'!C$3:C$500,11,'📝 Daily Log'!J$3:J$500),"") -> 0
B14: W12 | C14: 46194 | G14: =IFERROR(COUNTIFS('📝 Daily Log'!C$3:C$500,12,'📝 Daily Log'!G$3:G$500,"✅ Done")/COUNTIF('📝 Daily Log'!C$3:C$500,12),"") | H14: =IFERROR(AVERAGEIF('📝 Daily Log'!C$3:C$500,12,'📝 Daily Log'!I$3:I$500),"") | I14: =IFERROR(SUMIF('📝 Daily Log'!C$3:C$500,12,'📝 Daily Log'!J$3:J$500),"") -> 0
B15: W13 | C15: 46201 | G15: =IFERROR(COUNTIFS('📝 Daily Log'!C$3:C$500,13,'📝 Daily Log'!G$3:G$500,"✅ Done")/COUNTIF('📝 Daily Log'!C$3:C$500,13),"") | H15: =IFERROR(AVERAGEIF('📝 Daily Log'!C$3:C$500,13,'📝 Daily Log'!I$3:I$500),"") | I15: =IFERROR(SUMIF('📝 Daily Log'!C$3:C$500,13,'📝 Daily Log'!J$3:J$500),"") -> 0
B16: W14 | C16: 46208 | G16: =IFERROR(COUNTIFS('📝 Daily Log'!C$3:C$500,14,'📝 Daily Log'!G$3:G$500,"✅ Done")/COUNTIF('📝 Daily Log'!C$3:C$500,14),"") | H16: =IFERROR(AVERAGEIF('📝 Daily Log'!C$3:C$500,14,'📝 Daily Log'!I$3:I$500),"") | I16: =IFERROR(SUMIF('📝 Daily Log'!C$3:C$500,14,'📝 Daily Log'!J$3:J$500),"") -> 0
B17: W15 | C17: 46215 | G17: =IFERROR(COUNTIFS('📝 Daily Log'!C$3:C$500,15,'📝 Daily Log'!G$3:G$500,"✅ Done")/COUNTIF('📝 Daily Log'!C$3:C$500,15),"") | H17: =IFERROR(AVERAGEIF('📝 Daily Log'!C$3:C$500,15,'📝 Daily Log'!I$3:I$500),"") | I17: =IFERROR(SUMIF('📝 Daily Log'!C$3:C$500,15,'📝 Daily Log'!J$3:J$500),"") -> 0
B18: W16 | C18: 46222 | G18: =IFERROR(COUNTIFS('📝 Daily Log'!C$3:C$500,16,'📝 Daily Log'!G$3:G$500,"✅ Done")/COUNTIF('📝 Daily Log'!C$3:C$500,16),"") | H18: =IFERROR(AVERAGEIF('📝 Daily Log'!C$3:C$500,16,'📝 Daily Log'!I$3:I$500),"") | I18: =IFERROR(SUMIF('📝 Daily Log'!C$3:C$500,16,'📝 Daily Log'!J$3:J$500),"") -> 0
B19: W17 | C19: 46229 | G19: =IFERROR(COUNTIFS('📝 Daily Log'!C$3:C$500,17,'📝 Daily Log'!G$3:G$500,"✅ Done")/COUNTIF('📝 Daily Log'!C$3:C$500,17),"") | H19: =IFERROR(AVERAGEIF('📝 Daily Log'!C$3:C$500,17,'📝 Daily Log'!I$3:I$500),"") | I19: =IFERROR(SUMIF('📝 Daily Log'!C$3:C$500,17,'📝 Daily Log'!J$3:J$500),"") -> 0
B20: W18 | C20: 46236 | G20: =IFERROR(COUNTIFS('📝 Daily Log'!C$3:C$500,18,'📝 Daily Log'!G$3:G$500,"✅ Done")/COUNTIF('📝 Daily Log'!C$3:C$500,18),"") | H20: =IFERROR(AVERAGEIF('📝 Daily Log'!C$3:C$500,18,'📝 Daily Log'!I$3:I$500),"") | I20: =IFERROR(SUMIF('📝 Daily Log'!C$3:C$500,18,'📝 Daily Log'!J$3:J$500),"") -> 0
B21: W19 | C21: 46243 | G21: =IFERROR(COUNTIFS('📝 Daily Log'!C$3:C$500,19,'📝 Daily Log'!G$3:G$500,"✅ Done")/COUNTIF('📝 Daily Log'!C$3:C$500,19),"") | H21: =IFERROR(AVERAGEIF('📝 Daily Log'!C$3:C$500,19,'📝 Daily Log'!I$3:I$500),"") | I21: =IFERROR(SUMIF('📝 Daily Log'!C$3:C$500,19,'📝 Daily Log'!J$3:J$500),"") -> 0
B22: W20 | C22: 46250 | G22: =IFERROR(COUNTIFS('📝 Daily Log'!C$3:C$500,20,'📝 Daily Log'!G$3:G$500,"✅ Done")/COUNTIF('📝 Daily Log'!C$3:C$500,20),"") | H22: =IFERROR(AVERAGEIF('📝 Daily Log'!C$3:C$500,20,'📝 Daily Log'!I$3:I$500),"") | I22: =IFERROR(SUMIF('📝 Daily Log'!C$3:C$500,20,'📝 Daily Log'!J$3:J$500),"") -> 0
B23: W21 | C23: 46257 | G23: =IFERROR(COUNTIFS('📝 Daily Log'!C$3:C$500,21,'📝 Daily Log'!G$3:G$500,"✅ Done")/COUNTIF('📝 Daily Log'!C$3:C$500,21),"") | H23: =IFERROR(AVERAGEIF('📝 Daily Log'!C$3:C$500,21,'📝 Daily Log'!I$3:I$500),"") | I23: =IFERROR(SUMIF('📝 Daily Log'!C$3:C$500,21,'📝 Daily Log'!J$3:J$500),"") -> 0
B24: W22 | C24: 46264 | G24: =IFERROR(COUNTIFS('📝 Daily Log'!C$3:C$500,22,'📝 Daily Log'!G$3:G$500,"✅ Done")/COUNTIF('📝 Daily Log'!C$3:C$500,22),"") | H24: =IFERROR(AVERAGEIF('📝 Daily Log'!C$3:C$500,22,'📝 Daily Log'!I$3:I$500),"") | I24: =IFERROR(SUMIF('📝 Daily Log'!C$3:C$500,22,'📝 Daily Log'!J$3:J$500),"") -> 0
B25: W23 | C25: 46271 | G25: =IFERROR(COUNTIFS('📝 Daily Log'!C$3:C$500,23,'📝 Daily Log'!G$3:G$500,"✅ Done")/COUNTIF('📝 Daily Log'!C$3:C$500,23),"") | H25: =IFERROR(AVERAGEIF('📝 Daily Log'!C$3:C$500,23,'📝 Daily Log'!I$3:I$500),"") | I25: =IFERROR(SUMIF('📝 Daily Log'!C$3:C$500,23,'📝 Daily Log'!J$3:J$500),"") -> 0
B26: W24 | C26: 46278 | G26: =IFERROR(COUNTIFS('📝 Daily Log'!C$3:C$500,24,'📝 Daily Log'!G$3:G$500,"✅ Done")/COUNTIF('📝 Daily Log'!C$3:C$500,24),"") | H26: =IFERROR(AVERAGEIF('📝 Daily Log'!C$3:C$500,24,'📝 Daily Log'!I$3:I$500),"") | I26: =IFERROR(SUMIF('📝 Daily Log'!C$3:C$500,24,'📝 Daily Log'!J$3:J$500),"") -> 0
B27: W25 | C27: 46285 | G27: =IFERROR(COUNTIFS('📝 Daily Log'!C$3:C$500,25,'📝 Daily Log'!G$3:G$500,"✅ Done")/COUNTIF('📝 Daily Log'!C$3:C$500,25),"") | H27: =IFERROR(AVERAGEIF('📝 Daily Log'!C$3:C$500,25,'📝 Daily Log'!I$3:I$500),"") | I27: =IFERROR(SUMIF('📝 Daily Log'!C$3:C$500,25,'📝 Daily Log'!J$3:J$500),"") -> 0
B28: W26 | C28: 46292 | G28: =IFERROR(COUNTIFS('📝 Daily Log'!C$3:C$500,26,'📝 Daily Log'!G$3:G$500,"✅ Done")/COUNTIF('📝 Daily Log'!C$3:C$500,26),"") | H28: =IFERROR(AVERAGEIF('📝 Daily Log'!C$3:C$500,26,'📝 Daily Log'!I$3:I$500),"") | I28: =IFERROR(SUMIF('📝 Daily Log'!C$3:C$500,26,'📝 Daily Log'!J$3:J$500),"") -> 0
B29: W27 | C29: 46299 | G29: =IFERROR(COUNTIFS('📝 Daily Log'!C$3:C$500,27,'📝 Daily Log'!G$3:G$500,"✅ Done")/COUNTIF('📝 Daily Log'!C$3:C$500,27),"") | H29: =IFERROR(AVERAGEIF('📝 Daily Log'!C$3:C$500,27,'📝 Daily Log'!I$3:I$500),"") | I29: =IFERROR(SUMIF('📝 Daily Log'!C$3:C$500,27,'📝 Daily Log'!J$3:J$500),"") -> 0
B30: W28 | C30: 46306 | G30: =IFERROR(COUNTIFS('📝 Daily Log'!C$3:C$500,28,'📝 Daily Log'!G$3:G$500,"✅ Done")/COUNTIF('📝 Daily Log'!C$3:C$500,28),"") | H30: =IFERROR(AVERAGEIF('📝 Daily Log'!C$3:C$500,28,'📝 Daily Log'!I$3:I$500),"") | I30: =IFERROR(SUMIF('📝 Daily Log'!C$3:C$500,28,'📝 Daily Log'!J$3:J$500),"") -> 0
B31: W29 | C31: 46313 | G31: =IFERROR(COUNTIFS('📝 Daily Log'!C$3:C$500,29,'📝 Daily Log'!G$3:G$500,"✅ Done")/COUNTIF('📝 Daily Log'!C$3:C$500,29),"") | H31: =IFERROR(AVERAGEIF('📝 Daily Log'!C$3:C$500,29,'📝 Daily Log'!I$3:I$500),"") | I31: =IFERROR(SUMIF('📝 Daily Log'!C$3:C$500,29,'📝 Daily Log'!J$3:J$500),"") -> 0
B32: W30 | C32: 46320 | G32: =IFERROR(COUNTIFS('📝 Daily Log'!C$3:C$500,30,'📝 Daily Log'!G$3:G$500,"✅ Done")/COUNTIF('📝 Daily Log'!C$3:C$500,30),"") | H32: =IFERROR(AVERAGEIF('📝 Daily Log'!C$3:C$500,30,'📝 Daily Log'!I$3:I$500),"") | I32: =IFERROR(SUMIF('📝 Daily Log'!C$3:C$500,30,'📝 Daily Log'!J$3:J$500),"") -> 0
B33: W31 | C33: 46327 | G33: =IFERROR(COUNTIFS('📝 Daily Log'!C$3:C$500,31,'📝 Daily Log'!G$3:G$500,"✅ Done")/COUNTIF('📝 Daily Log'!C$3:C$500,31),"") | H33: =IFERROR(AVERAGEIF('📝 Daily Log'!C$3:C$500,31,'📝 Daily Log'!I$3:I$500),"") | I33: =IFERROR(SUMIF('📝 Daily Log'!C$3:C$500,31,'📝 Daily Log'!J$3:J$500),"") -> 0
B34: W32 | C34: 46334 | G34: =IFERROR(COUNTIFS('📝 Daily Log'!C$3:C$500,32,'📝 Daily Log'!G$3:G$500,"✅ Done")/COUNTIF('📝 Daily Log'!C$3:C$500,32),"") | H34: =IFERROR(AVERAGEIF('📝 Daily Log'!C$3:C$500,32,'📝 Daily Log'!I$3:I$500),"") | I34: =IFERROR(SUMIF('📝 Daily Log'!C$3:C$500,32,'📝 Daily Log'!J$3:J$500),"") -> 0
B35: W33 | C35: 46341 | G35: =IFERROR(COUNTIFS('📝 Daily Log'!C$3:C$500,33,'📝 Daily Log'!G$3:G$500,"✅ Done")/COUNTIF('📝 Daily Log'!C$3:C$500,33),"") | H35: =IFERROR(AVERAGEIF('📝 Daily Log'!C$3:C$500,33,'📝 Daily Log'!I$3:I$500),"") | I35: =IFERROR(SUMIF('📝 Daily Log'!C$3:C$500,33,'📝 Daily Log'!J$3:J$500),"") -> 0
B36: W34 | C36: 46348 | G36: =IFERROR(COUNTIFS('📝 Daily Log'!C$3:C$500,34,'📝 Daily Log'!G$3:G$500,"✅ Done")/COUNTIF('📝 Daily Log'!C$3:C$500,34),"") | H36: =IFERROR(AVERAGEIF('📝 Daily Log'!C$3:C$500,34,'📝 Daily Log'!I$3:I$500),"") | I36: =IFERROR(SUMIF('📝 Daily Log'!C$3:C$500,34,'📝 Daily Log'!J$3:J$500),"") -> 0
B37: W35 | C37: 46355 | G37: =IFERROR(COUNTIFS('📝 Daily Log'!C$3:C$500,35,'📝 Daily Log'!G$3:G$500,"✅ Done")/COUNTIF('📝 Daily Log'!C$3:C$500,35),"") | H37: =IFERROR(AVERAGEIF('📝 Daily Log'!C$3:C$500,35,'📝 Daily Log'!I$3:I$500),"") | I37: =IFERROR(SUMIF('📝 Daily Log'!C$3:C$500,35,'📝 Daily Log'!J$3:J$500),"") -> 0
B38: W36 | C38: 46362 | G38: =IFERROR(COUNTIFS('📝 Daily Log'!C$3:C$500,36,'📝 Daily Log'!G$3:G$500,"✅ Done")/COUNTIF('📝 Daily Log'!C$3:C$500,36),"") | H38: =IFERROR(AVERAGEIF('📝 Daily Log'!C$3:C$500,36,'📝 Daily Log'!I$3:I$500),"") | I38: =IFERROR(SUMIF('📝 Daily Log'!C$3:C$500,36,'📝 Daily Log'!J$3:J$500),"") -> 0
B39: W37 | C39: 46369 | G39: =IFERROR(COUNTIFS('📝 Daily Log'!C$3:C$500,37,'📝 Daily Log'!G$3:G$500,"✅ Done")/COUNTIF('📝 Daily Log'!C$3:C$500,37),"") | H39: =IFERROR(AVERAGEIF('📝 Daily Log'!C$3:C$500,37,'📝 Daily Log'!I$3:I$500),"") | I39: =IFERROR(SUMIF('📝 Daily Log'!C$3:C$500,37,'📝 Daily Log'!J$3:J$500),"") -> 0
B40: W38 | C40: 46376 | G40: =IFERROR(COUNTIFS('📝 Daily Log'!C$3:C$500,38,'📝 Daily Log'!G$3:G$500,"✅ Done")/COUNTIF('📝 Daily Log'!C$3:C$500,38),"") | H40: =IFERROR(AVERAGEIF('📝 Daily Log'!C$3:C$500,38,'📝 Daily Log'!I$3:I$500),"") | I40: =IFERROR(SUMIF('📝 Daily Log'!C$3:C$500,38,'📝 Daily Log'!J$3:J$500),"") -> 0
B41: W39 | C41: 46383 | G41: =IFERROR(COUNTIFS('📝 Daily Log'!C$3:C$500,39,'📝 Daily Log'!G$3:G$500,"✅ Done")/COUNTIF('📝 Daily Log'!C$3:C$500,39),"") | H41: =IFERROR(AVERAGEIF('📝 Daily Log'!C$3:C$500,39,'📝 Daily Log'!I$3:I$500),"") | I41: =IFERROR(SUMIF('📝 Daily Log'!C$3:C$500,39,'📝 Daily Log'!J$3:J$500),"") -> 0

Sheet 📊 Dashboard
A1: DE LEARNING TRACKER — PROGRESS DASHBOARD
B3: Total Hours Logged | E3: Sessions Done | H3: Sessions Missed | K3: DSA Problems Solved | N3: Avg Confidence (1-5) | Q3: Weeks Active
B4: =IFERROR(SUM('📝 Daily Log'!H3:H500),0) -> 10.5 | E4: =IFERROR(COUNTIF('📝 Daily Log'!G3:G500,"✅ Done"),0) -> 4 | H4: =IFERROR(COUNTIF('📝 Daily Log'!G3:G500,"❌ Missed"),0) -> 0 | K4: =IFERROR(SUM('📝 Daily Log'!J3:J500),0) -> 30 | N4: =IFERROR(AVERAGEIF('📝 Daily Log'!G3:G500,"✅ Done",'📝 Daily Log'!I3:I500),0) -> 3.75 | Q4: =IFERROR(COUNTA(unique('📝 Daily Log'!C3:C500))-IF(COUNTIF('📝 Daily Log'!C3:C500,"")>0,1,0),0) -> 0
B8: PHASE-BY-PHASE PROGRESS
B9: Phase | D9: Sessions Done | F9: Hours | H9: Avg Conf | J9: DSA done | L9: % Complete
B10: M1 - Python/SQL | D10: =IFERROR(COUNTIFS('📝 Daily Log'!F$3:F$500,"M1 - Python/SQL",'📝 Daily Log'!G$3:G$500,"✅ Done"),0) -> 4 | F10: =IFERROR(SUMIF('📝 Daily Log'!F$3:F$500,"M1 - Python/SQL",'📝 Daily Log'!H$3:H$500),0) -> 10.5 | H10: =IFERROR(AVERAGEIFS('📝 Daily Log'!I$3:I$500,'📝 Daily Log'!F$3:F$500,"M1 - Python/SQL",'📝 Daily Log'!I$3:I$500,"<>"),"") -> 3.6 | J10: =IFERROR(SUMIF('📝 Daily Log'!F$3:F$500,"M1 - Python/SQL",'📝 Daily Log'!J$3:J$500),0) -> 30 | L10: =IFERROR(COUNTIFS('📝 Daily Log'!F$3:F$500,"M1 - Python/SQL",'📝 Daily Log'!G$3:G$500,"✅ Done")/COUNTIF('📝 Daily Log'!F$3:F$500,"M1 - Python/SQL"),"") -> 0.8
B11: M2 - Spark | D11: =IFERROR(COUNTIFS('📝 Daily Log'!F$3:F$500,"M2 - Spark",'📝 Daily Log'!G$3:G$500,"✅ Done"),0) -> 0 | F11: =IFERROR(SUMIF('📝 Daily Log'!F$3:F$500,"M2 - Spark",'📝 Daily Log'!H$3:H$500),0) -> 0 | H11: =IFERROR(AVERAGEIFS('📝 Daily Log'!I$3:I$500,'📝 Daily Log'!F$3:F$500,"M2 - Spark",'📝 Daily Log'!I$3:I$500,"<>"),"") | J11: =IFERROR(SUMIF('📝 Daily Log'!F$3:F$500,"M2 - Spark",'📝 Daily Log'!J$3:J$500),0) -> 0 | L11: =IFERROR(COUNTIFS('📝 Daily Log'!F$3:F$500,"M2 - Spark",'📝 Daily Log'!G$3:G$500,"✅ Done")/COUNTIF('📝 Daily Log'!F$3:F$500,"M2 - Spark"),"")
B12: M3 - Kafka | D12: =IFERROR(COUNTIFS('📝 Daily Log'!F$3:F$500,"M3 - Kafka",'📝 Daily Log'!G$3:G$500,"✅ Done"),0) -> 0 | F12: =IFERROR(SUMIF('📝 Daily Log'!F$3:F$500,"M3 - Kafka",'📝 Daily Log'!H$3:H$500),0) -> 0 | H12: =IFERROR(AVERAGEIFS('📝 Daily Log'!I$3:I$500,'📝 Daily Log'!F$3:F$500,"M3 - Kafka",'📝 Daily Log'!I$3:I$500,"<>"),"") | J12: =IFERROR(SUMIF('📝 Daily Log'!F$3:F$500,"M3 - Kafka",'📝 Daily Log'!J$3:J$500),0) -> 0 | L12: =IFERROR(COUNTIFS('📝 Daily Log'!F$3:F$500,"M3 - Kafka",'📝 Daily Log'!G$3:G$500,"✅ Done")/COUNTIF('📝 Daily Log'!F$3:F$500,"M3 - Kafka"),"")
B13: M4 - Cloud | D13: =IFERROR(COUNTIFS('📝 Daily Log'!F$3:F$500,"M4 - Cloud",'📝 Daily Log'!G$3:G$500,"✅ Done"),0) -> 0 | F13: =IFERROR(SUMIF('📝 Daily Log'!F$3:F$500,"M4 - Cloud",'📝 Daily Log'!H$3:H$500),0) -> 0 | H13: =IFERROR(AVERAGEIFS('📝 Daily Log'!I$3:I$500,'📝 Daily Log'!F$3:F$500,"M4 - Cloud",'📝 Daily Log'!I$3:I$500,"<>"),"") | J13: =IFERROR(SUMIF('📝 Daily Log'!F$3:F$500,"M4 - Cloud",'📝 Daily Log'!J$3:J$500),0) -> 0 | L13: =IFERROR(COUNTIFS('📝 Daily Log'!F$3:F$500,"M4 - Cloud",'📝 Daily Log'!G$3:G$500,"✅ Done")/COUNTIF('📝 Daily Log'!F$3:F$500,"M4 - Cloud"),"")
B14: M5 - SysDesign | D14: =IFERROR(COUNTIFS('📝 Daily Log'!F$3:F$500,"M5 - SysDesign",'📝 Daily Log'!G$3:G$500,"✅ Done"),0) -> 0 | F14: =IFERROR(SUMIF('📝 Daily Log'!F$3:F$500,"M5 - SysDesign",'📝 Daily Log'!H$3:H$500),0) -> 0 | H14: =IFERROR(AVERAGEIFS('📝 Daily Log'!I$3:I$500,'📝 Daily Log'!F$3:F$500,"M5 - SysDesign",'📝 Daily Log'!I$3:I$500,"<>"),"") | J14: =IFERROR(SUMIF('📝 Daily Log'!F$3:F$500,"M5 - SysDesign",'📝 Daily Log'!J$3:J$500),0) -> 0 | L14: =IFERROR(COUNTIFS('📝 Daily Log'!F$3:F$500,"M5 - SysDesign",'📝 Daily Log'!G$3:G$500,"✅ Done")/COUNTIF('📝 Daily Log'!F$3:F$500,"M5 - SysDesign"),"")
B15: M6 - Interview | D15: =IFERROR(COUNTIFS('📝 Daily Log'!F$3:F$500,"M6 - Interview",'📝 Daily Log'!G$3:G$500,"✅ Done"),0) -> 0 | F15: =IFERROR(SUMIF('📝 Daily Log'!F$3:F$500,"M6 - Interview",'📝 Daily Log'!H$3:H$500),0) -> 0 | H15: =IFERROR(AVERAGEIFS('📝 Daily Log'!I$3:I$500,'📝 Daily Log'!F$3:F$500,"M6 - Interview",'📝 Daily Log'!I$3:I$500,"<>"),"") | J15: =IFERROR(SUMIF('📝 Daily Log'!F$3:F$500,"M6 - Interview",'📝 Daily Log'!J$3:J$500),0) -> 0 | L15: =IFERROR(COUNTIFS('📝 Daily Log'!F$3:F$500,"M6 - Interview",'📝 Daily Log'!G$3:G$500,"✅ Done")/COUNTIF('📝 Daily Log'!F$3:F$500,"M6 - Interview"),"")
B16: M7 - LLM | D16: =IFERROR(COUNTIFS('📝 Daily Log'!F$3:F$500,"M7 - LLM",'📝 Daily Log'!G$3:G$500,"✅ Done"),0) -> 0 | F16: =IFERROR(SUMIF('📝 Daily Log'!F$3:F$500,"M7 - LLM",'📝 Daily Log'!H$3:H$500),0) -> 0 | H16: =IFERROR(AVERAGEIFS('📝 Daily Log'!I$3:I$500,'📝 Daily Log'!F$3:F$500,"M7 - LLM",'📝 Daily Log'!I$3:I$500,"<>"),"") | J16: =IFERROR(SUMIF('📝 Daily Log'!F$3:F$500,"M7 - LLM",'📝 Daily Log'!J$3:J$500),0) -> 0 | L16: =IFERROR(COUNTIFS('📝 Daily Log'!F$3:F$500,"M7 - LLM",'📝 Daily Log'!G$3:G$500,"✅ Done")/COUNTIF('📝 Daily Log'!F$3:F$500,"M7 - LLM"),"")
B17: M8 - Agents | D17: =IFERROR(COUNTIFS('📝 Daily Log'!F$3:F$500,"M8 - Agents",'📝 Daily Log'!G$3:G$500,"✅ Done"),0) -> 0 | F17: =IFERROR(SUMIF('📝 Daily Log'!F$3:F$500,"M8 - Agents",'📝 Daily Log'!H$3:H$500),0) -> 0 | H17: =IFERROR(AVERAGEIFS('📝 Daily Log'!I$3:I$500,'📝 Daily Log'!F$3:F$500,"M8 - Agents",'📝 Daily Log'!I$3:I$500,"<>"),"") | J17: =IFERROR(SUMIF('📝 Daily Log'!F$3:F$500,"M8 - Agents",'📝 Daily Log'!J$3:J$500),0) -> 0 | L17: =IFERROR(COUNTIFS('📝 Daily Log'!F$3:F$500,"M8 - Agents",'📝 Daily Log'!G$3:G$500,"✅ Done")/COUNTIF('📝 Daily Log'!F$3:F$500,"M8 - Agents"),"")
B18: M9 - LLMOps | D18: =IFERROR(COUNTIFS('📝 Daily Log'!F$3:F$500,"M9 - LLMOps",'📝 Daily Log'!G$3:G$500,"✅ Done"),0) -> 0 | F18: =IFERROR(SUMIF('📝 Daily Log'!F$3:F$500,"M9 - LLMOps",'📝 Daily Log'!H$3:H$500),0) -> 0 | H18: =IFERROR(AVERAGEIFS('📝 Daily Log'!I$3:I$500,'📝 Daily Log'!F$3:F$500,"M9 - LLMOps",'📝 Daily Log'!I$3:I$500,"<>"),"") | J18: =IFERROR(SUMIF('📝 Daily Log'!F$3:F$500,"M9 - LLMOps",'📝 Daily Log'!J$3:J$500),0) -> 0 | L18: =IFERROR(COUNTIFS('📝 Daily Log'!F$3:F$500,"M9 - LLMOps",'📝 Daily Log'!G$3:G$500,"✅ Done")/COUNTIF('📝 Daily Log'!F$3:F$500,"M9 - LLMOps"),"")
B20: 📈 WEEKLY VELOCITY (Hrs per week — are you speeding up or slowing down?)
B21: Week | C21: Hours | D21: vs Target (14hrs) | E21: vs Last Week | F21: Trend
B22: W1 | C22: ='🔢 Stats (Do Not Edit)'!B2 -> 10.5 | D22: =IFERROR(C22-14,"") -> -3.5 | E22: — | F22: =IFERROR(IF(C22>=14,"✅ On track",IF(C22>=10,"⚠️ Low","❌ Behind")),"—") -> ⚠️ Low
B23: W2 | C23: ='🔢 Stats (Do Not Edit)'!B3 -> 0 | D23: =IFERROR(C23-14,"") -> -14 | E23: =IFERROR(C23-C22,"") -> -10.5 | F23: =IFERROR(IF(C23>=14,"✅ On track",IF(C23>=10,"⚠️ Low","❌ Behind")),"—") -> ❌ Behind
B24: W3 | C24: ='🔢 Stats (Do Not Edit)'!B4 -> 0 | D24: =IFERROR(C24-14,"") -> -14 | E24: =IFERROR(C24-C23,"") -> 0 | F24: =IFERROR(IF(C24>=14,"✅ On track",IF(C24>=10,"⚠️ Low","❌ Behind")),"—") -> ❌ Behind
B25: W4 | C25: ='🔢 Stats (Do Not Edit)'!B5 -> 0 | D25: =IFERROR(C25-14,"") -> -14 | E25: =IFERROR(C25-C24,"") -> 0 | F25: =IFERROR(IF(C25>=14,"✅ On track",IF(C25>=10,"⚠️ Low","❌ Behind")),"—") -> ❌ Behind
B26: W5 | C26: ='🔢 Stats (Do Not Edit)'!B6 -> 0 | D26: =IFERROR(C26-14,"") -> -14 | E26: =IFERROR(C26-C25,"") -> 0 | F26: =IFERROR(IF(C26>=14,"✅ On track",IF(C26>=10,"⚠️ Low","❌ Behind")),"—") -> ❌ Behind
B27: W6 | C27: ='🔢 Stats (Do Not Edit)'!B7 -> 0 | D27: =IFERROR(C27-14,"") -> -14 | E27: =IFERROR(C27-C26,"") -> 0 | F27: =IFERROR(IF(C27>=14,"✅ On track",IF(C27>=10,"⚠️ Low","❌ Behind")),"—") -> ❌ Behind
B28: W7 | C28: ='🔢 Stats (Do Not Edit)'!B8 -> 0 | D28: =IFERROR(C28-14,"") -> -14 | E28: =IFERROR(C28-C27,"") -> 0 | F28: =IFERROR(IF(C28>=14,"✅ On track",IF(C28>=10,"⚠️ Low","❌ Behind")),"—") -> ❌ Behind
B29: W8 | C29: ='🔢 Stats (Do Not Edit)'!B9 -> 0 | D29: =IFERROR(C29-14,"") -> -14 | E29: =IFERROR(C29-C28,"") -> 0 | F29: =IFERROR(IF(C29>=14,"✅ On track",IF(C29>=10,"⚠️ Low","❌ Behind")),"—") -> ❌ Behind
B30: W9 | C30: ='🔢 Stats (Do Not Edit)'!B10 -> 0 | D30: =IFERROR(C30-14,"") -> -14 | E30: =IFERROR(C30-C29,"") -> 0 | F30: =IFERROR(IF(C30>=14,"✅ On track",IF(C30>=10,"⚠️ Low","❌ Behind")),"—") -> ❌ Behind
B31: W10 | C31: ='🔢 Stats (Do Not Edit)'!B11 -> 0 | D31: =IFERROR(C31-14,"") -> -14 | E31: =IFERROR(C31-C30,"") -> 0 | F31: =IFERROR(IF(C31>=14,"✅ On track",IF(C31>=10,"⚠️ Low","❌ Behind")),"—") -> ❌ Behind
B32: W11 | C32: ='🔢 Stats (Do Not Edit)'!B12 -> 0 | D32: =IFERROR(C32-14,"") -> -14 | E32: =IFERROR(C32-C31,"") -> 0 | F32: =IFERROR(IF(C32>=14,"✅ On track",IF(C32>=10,"⚠️ Low","❌ Behind")),"—") -> ❌ Behind
B33: W12 | C33: ='🔢 Stats (Do Not Edit)'!B13 -> 0 | D33: =IFERROR(C33-14,"") -> -14 | E33: =IFERROR(C33-C32,"") -> 0 | F33: =IFERROR(IF(C33>=14,"✅ On track",IF(C33>=10,"⚠️ Low","❌ Behind")),"—") -> ❌ Behind
B34: W13 | C34: ='🔢 Stats (Do Not Edit)'!B14 -> 0 | D34: =IFERROR(C34-14,"") -> -14 | E34: =IFERROR(C34-C33,"") -> 0 | F34: =IFERROR(IF(C34>=14,"✅ On track",IF(C34>=10,"⚠️ Low","❌ Behind")),"—") -> ❌ Behind
... B60: W39 | C60: ='🔢 Stats (Do Not Edit)'!B40 -> 0 | D60: =IFERROR(C60-14,"") -> -14 | E60: =IFERROR(C60-C59,"") -> 0 | F60: =IFERROR(IF(C60>=14,"✅ On track",IF(C60>=10,"⚠️ Low","❌ Behind")),"—") -> ❌ Behind

Sheet 🔢 Stats (Do Not Edit)
A1: Week | B1: Hours | C1: Done | D1: Missed | E1: AvgConf | F1: DSA
A2: W1 | B2: =IFERROR(SUMIF('📝 Daily Log'!C$3:C$500,1,'📝 Daily Log'!H$3:H$500),0) -> 10.5 | C2: =IFERROR(COUNTIFS('📝 Daily Log'!C$3:C$500,1,'📝 Daily Log'!G$3:G$500,"✅ Done"),0) -> 4 | D2: =IFERROR(COUNTIFS('📝 Daily Log'!C$3:C$500,1,'📝 Daily Log'!G$3:G$500,"❌ Missed"),0) -> 0 | E2: =IFERROR(AVERAGEIFS('📝 Daily Log'!I$3:I$500,'📝 Daily Log'!C$3:C$500,1,'📝 Daily Log'!I$3:I$500,">0"),"") -> 3.6 | F2: =IFERROR(SUMIF('📝 Daily Log'!C$3:C$500,1,'📝 Daily Log'!J$3:J$500),0) -> 30
A3: W2 | B3: =IFERROR(SUMIF('📝 Daily Log'!C$3:C$500,2,'📝 Daily Log'!H$3:H$500),0) -> 0 | C3: =IFERROR(COUNTIFS('📝 Daily Log'!C$3:C$500,2,'📝 Daily Log'!G$3:G$500,"✅ Done"),0) -> 0 | D3: =IFERROR(COUNTIFS('📝 Daily Log'!C$3:C$500,2,'📝 Daily Log'!G$3:G$500,"❌ Missed"),0) -> 0 | E3: =IFERROR(AVERAGEIFS('📝 Daily Log'!I$3:I$500,'📝 Daily Log'!C$3:C$500,2,'📝 Daily Log'!I$3:I$500,">0"),"") | F3: =IFERROR(SUMIF('📝 Daily Log'!C$3:C$500,2,'📝 Daily Log'!J$3:J$500),0) -> 0
A4: W3 | B4: =IFERROR(SUMIF('📝 Daily Log'!C$3:C$500,3,'📝 Daily Log'!H$3:H$500),0) -> 0 | C4: =IFERROR(COUNTIFS('📝 Daily Log'!C$3:C$500,3,'📝 Daily Log'!G$3:G$500,"✅ Done"),0) -> 0 | D4: =IFERROR(COUNTIFS('📝 Daily Log'!C$3:C$500,3,'📝 Daily Log'!G$3:G$500,"❌ Missed"),0) -> 0 | E4: =IFERROR(AVERAGEIFS('📝 Daily Log'!I$3:I$500,'📝 Daily Log'!C$3:C$500,3,'📝 Daily Log'!I$3:I$500,">0"),"") | F4: =IFERROR(SUMIF('📝 Daily Log'!C$3:C$500,3,'📝 Daily Log'!J$3:J$500),0) -> 0
A5: W4 | B5: =IFERROR(SUMIF('📝 Daily Log'!C$3:C$500,4,'📝 Daily Log'!H$3:H$500),0) -> 0 | C5: =IFERROR(COUNTIFS('📝 Daily Log'!C$3:C$500,4,'📝 Daily Log'!G$3:G$500,"✅ Done"),0) -> 0 | D5: =IFERROR(COUNTIFS('📝 Daily Log'!C$3:C$500,4,'📝 Daily Log'!G$3:G$500,"❌ Missed"),0) -> 0 | E5: =IFERROR(AVERAGEIFS('📝 Daily Log'!I$3:I$500,'📝 Daily Log'!C$3:C$500,4,'📝 Daily Log'!I$3:I$500,">0"),"") | F5: =IFERROR(SUMIF('📝 Daily Log'!C$3:C$500,4,'📝 Daily Log'!J$3:J$500),0) -> 0
A6: W5 | B6: =IFERROR(SUMIF('📝 Daily Log'!C$3:C$500,5,'📝 Daily Log'!H$3:H$500),0) -> 0 | C6: =IFERROR(COUNTIFS('📝 Daily Log'!C$3:C$500,5,'📝 Daily Log'!G$3:G$500,"✅ Done"),0) -> 0 | D6: =IFERROR(COUNTIFS('📝 Daily Log'!C$3:C$500,5,'📝 Daily Log'!G$3:G$500,"❌ Missed"),0) -> 0 | E6: =IFERROR(AVERAGEIFS('📝 Daily Log'!I$3:I$500,'📝 Daily Log'!C$3:C$500,5,'📝 Daily Log'!I$3:I$500,">0"),"") | F6: =IFERROR(SUMIF('📝 Daily Log'!C$3:C$500,5,'📝 Daily Log'!J$3:J$500),0) -> 0
A7: W6 | B7: =IFERROR(SUMIF('📝 Daily Log'!C$3:C$500,6,'📝 Daily Log'!H$3:H$500),0) -> 0 | C7: =IFERROR(COUNTIFS('📝 Daily Log'!C$3:C$500,6,'📝 Daily Log'!G$3:G$500,"✅ Done"),0) -> 0 | D7: =IFERROR(COUNTIFS('📝 Daily Log'!C$3:C$500,6,'📝 Daily Log'!G$3:G$500,"❌ Missed"),0) -> 0 | E7: =IFERROR(AVERAGEIFS('📝 Daily Log'!I$3:I$500,'📝 Daily Log'!C$3:C$500,6,'📝 Daily Log'!I$3:I$500,">0"),"") | F7: =IFERROR(SUMIF('📝 Daily Log'!C$3:C$500,6,'📝 Daily Log'!J$3:J$500),0) -> 0
A8: W7 | B8: =IFERROR(SUMIF('📝 Daily Log'!C$3:C$500,7,'📝 Daily Log'!H$3:H$500),0) -> 0 | C8: =IFERROR(COUNTIFS('📝 Daily Log'!C$3:C$500,7,'📝 Daily Log'!G$3:G$500,"✅ Done"),0) -> 0 | D8: =IFERROR(COUNTIFS('📝 Daily Log'!C$3:C$500,7,'📝 Daily Log'!G$3:G$500,"❌ Missed"),0) -> 0 | E8: =IFERROR(AVERAGEIFS('📝 Daily Log'!I$3:I$500,'📝 Daily Log'!C$3:C$500,7,'📝 Daily Log'!I$3:I$500,">0"),"") | F8: =IFERROR(SUMIF('📝 Daily Log'!C$3:C$500,7,'📝 Daily Log'!J$3:J$500),0) -> 0
A9: W8 | B9: =IFERROR(SUMIF('📝 Daily Log'!C$3:C$500,8,'📝 Daily Log'!H$3:H$500),0) -> 0 | C9: =IFERROR(COUNTIFS('📝 Daily Log'!C$3:C$500,8,'📝 Daily Log'!G$3:G$500,"✅ Done"),0) -> 0 | D9: =IFERROR(COUNTIFS('📝 Daily Log'!C$3:C$500,8,'📝 Daily Log'!G$3:G$500,"❌ Missed"),0) -> 0 | E9: =IFERROR(AVERAGEIFS('📝 Daily Log'!I$3:I$500,'📝 Daily Log'!C$3:C$500,8,'📝 Daily Log'!I$3:I$500,">0"),"") | F9: =IFERROR(SUMIF('📝 Daily Log'!C$3:C$500,8,'📝 Daily Log'!J$3:J$500),0) -> 0
A10: W9 | B10: =IFERROR(SUMIF('📝 Daily Log'!C$3:C$500,9,'📝 Daily Log'!H$3:H$500),0) -> 0 | C10: =IFERROR(COUNTIFS('📝 Daily Log'!C$3:C$500,9,'📝 Daily Log'!G$3:G$500,"✅ Done"),0) -> 0 | D10: =IFERROR(COUNTIFS('📝 Daily Log'!C$3:C$500,9,'📝 Daily Log'!G$3:G$500,"❌ Missed"),0) -> 0 | E10: =IFERROR(AVERAGEIFS('📝 Daily Log'!I$3:I$500,'📝 Daily Log'!C$3:C$500,9,'📝 Daily Log'!I$3:I$500,">0"),"") | F10: =IFERROR(SUMIF('📝 Daily Log'!C$3:C$500,9,'📝 Daily Log'!J$3:J$500),0) -> 0
A11: W10 | B11: =IFERROR(SUMIF('📝 Daily Log'!C$3:C$500,10,'📝 Daily Log'!H$3:H$500),0) -> 0 | C11: =IFERROR(COUNTIFS('📝 Daily Log'!C$3:C$500,10,'📝 Daily Log'!G$3:G$500,"✅ Done"),0) -> 0 | D11: =IFERROR(COUNTIFS('📝 Daily Log'!C$3:C$500,10,'📝 Daily Log'!G$3:G$500,"❌ Missed"),0) -> 0 | E11: =IFERROR(AVERAGEIFS('📝 Daily Log'!I$3:I$500,'📝 Daily Log'!C$3:C$500,10,'📝 Daily Log'!I$3:I$500,">0"),"") | F11: =IFERROR(SUMIF('📝 Daily Log'!C$3:C$500,10,'📝 Daily Log'!J$3:J$500),0) -> 0
A12: W11 | B12: =IFERROR(SUMIF('📝 Daily Log'!C$3:C$500,11,'📝 Daily Log'!H$3:H$500),0) -> 0 | C12: =IFERROR(COUNTIFS('📝 Daily Log'!C$3:C$500,11,'📝 Daily Log'!G$3:G$500,"✅ Done"),0) -> 0 | D12: =IFERROR(COUNTIFS('📝 Daily Log'!C$3:C$500,11,'📝 Daily Log'!G$3:G$500,"❌ Missed"),0) -> 0 | E12: =IFERROR(AVERAGEIFS('📝 Daily Log'!I$3:I$500,'📝 Daily Log'!C$3:C$500,11,'📝 Daily Log'!I$3:I$500,">0"),"") | F12: =IFERROR(SUMIF('📝 Daily Log'!C$3:C$500,11,'📝 Daily Log'!J$3:J$500),0) -> 0
A13: W12 | B13: =IFERROR(SUMIF('📝 Daily Log'!C$3:C$500,12,'📝 Daily Log'!H$3:H$500),0) -> 0 | C13: =IFERROR(COUNTIFS('📝 Daily Log'!C$3:C$500,12,'📝 Daily Log'!G$3:G$500,"✅ Done"),0) -> 0 | D13: =IFERROR(COUNTIFS('📝 Daily Log'!C$3:C$500,12,'📝 Daily Log'!G$3:G$500,"❌ Missed"),0) -> 0 | E13: =IFERROR(AVERAGEIFS('📝 Daily Log'!I$3:I$500,'📝 Daily Log'!C$3:C$500,12,'📝 Daily Log'!I$3:I$500,">0"),"") | F13: =IFERROR(SUMIF('📝 Daily Log'!C$3:C$500,12,'📝 Daily Log'!J$3:J$500),0) -> 0
A14: W13 | B14: =IFERROR(SUMIF('📝 Daily Log'!C$3:C$500,13,'📝 Daily Log'!H$3:H$500),0) -> 0 | C14: =IFERROR(COUNTIFS('📝 Daily Log'!C$3:C$500,13,'📝 Daily Log'!G$3:G$500,"✅ Done"),0) -> 0 | D14: =IFERROR(COUNTIFS('📝 Daily Log'!C$3:C$500,13,'📝 Daily Log'!G$3:G$500,"❌ Missed"),0) -> 0 | E14: =IFERROR(AVERAGEIFS('📝 Daily Log'!I$3:I$500,'📝 Daily Log'!C$3:C$500,13,'📝 Daily Log'!I$3:I$500,">0"),"") | F14: =IFERROR(SUMIF('📝 Daily Log'!C$3:C$500,13,'📝 Daily Log'!J$3:J$500),0) -> 0
A15: W14 | B15: =IFERROR(SUMIF('📝 Daily Log'!C$3:C$500,14,'📝 Daily Log'!H$3:H$500),0) -> 0 | C15: =IFERROR(COUNTIFS('📝 Daily Log'!C$3:C$500,14,'📝 Daily Log'!G$3:G$500,"✅ Done"),0) -> 0 | D15: =IFERROR(COUNTIFS('📝 Daily Log'!C$3:C$500,14,'📝 Daily Log'!G$3:G$500,"❌ Missed"),0) -> 0 | E15: =IFERROR(AVERAGEIFS('📝 Daily Log'!I$3:I$500,'📝 Daily Log'!C$3:C$500,14,'📝 Daily Log'!I$3:I$500,">0"),"") | F15: =IFERROR(SUMIF('📝 Daily Log'!C$3:C$500,14,'📝 Daily Log'!J$3:J$500),0) -> 0
A16: W15 | B16: =IFERROR(SUMIF('📝 Daily Log'!C$3:C$500,15,'📝 Daily Log'!H$3:H$500),0) -> 0 | C16: =IFERROR(COUNTIFS('📝 Daily Log'!C$3:C$500,15,'📝 Daily Log'!G$3:G$500,"✅ Done"),0) -> 0 | D16: =IFERROR(COUNTIFS('📝 Daily Log'!C$3:C$500,15,'📝 Daily Log'!G$3:G$500,"❌ Missed"),0) -> 0 | E16: =IFERROR(AVERAGEIFS('📝 Daily Log'!I$3:I$500,'📝 Daily Log'!C$3:C$500,15,'📝 Daily Log'!I$3:I$500,">0"),"") | F16: =IFERROR(SUMIF('📝 Daily Log'!C$3:C$500,15,'📝 Daily Log'!J$3:J$500),0) -> 0
A17: W16 | B17: =IFERROR(SUMIF('📝 Daily Log'!C$3:C$500,16,'📝 Daily Log'!H$3:H$500),0) -> 0 | C17: =IFERROR(COUNTIFS('📝 Daily Log'!C$3:C$500,16,'📝 Daily Log'!G$3:G$500,"✅ Done"),0) -> 0 | D17: =IFERROR(COUNTIFS('📝 Daily Log'!C$3:C$500,16,'📝 Daily Log'!G$3:G$500,"❌ Missed"),0) -> 0 | E17: =IFERROR(AVERAGEIFS('📝 Daily Log'!I$3:I$500,'📝 Daily Log'!C$3:C$500,16,'📝 Daily Log'!I$3:I$500,">0"),"") | F17: =IFERROR(SUMIF('📝 Daily Log'!C$3:C$500,16,'📝 Daily Log'!J$3:J$500),0) -> 0
A18: W17 | B18: =IFERROR(SUMIF('📝 Daily Log'!C$3:C$500,17,'📝 Daily Log'!H$3:H$500),0) -> 0 | C18: =IFERROR(COUNTIFS('📝 Daily Log'!C$3:C$500,17,'📝 Daily Log'!G$3:G$500,"✅ Done"),0) -> 0 | D18: =IFERROR(COUNTIFS('📝 Daily Log'!C$3:C$500,17,'📝 Daily Log'!G$3:G$500,"❌ Missed"),0) -> 0 | E18: =IFERROR(AVERAGEIFS('📝 Daily Log'!I$3:I$500,'📝 Daily Log'!C$3:C$500,17,'📝 Daily Log'!I$3:I$500,">0"),"") | F18: =IFERROR(SUMIF('📝 Daily Log'!C$3:C$500,17,'📝 Daily Log'!J$3:J$500),0) -> 0
A19: W18 | B19: =IFERROR(SUMIF('📝 Daily Log'!C$3:C$500,18,'📝 Daily Log'!H$3:H$500),0) -> 0 | C19: =IFERROR(COUNTIFS('📝 Daily Log'!C$3:C$500,18,'📝 Daily Log'!G$3:G$500,"✅ Done"),0) -> 0 | D19: =IFERROR(COUNTIFS('📝 Daily Log'!C$3:C$500,18,'📝 Daily Log'!G$3:G$500,"❌ Missed"),0) -> 0 | E19: =IFERROR(AVERAGEIFS('📝 Daily Log'!I$3:I$500,'📝 Daily Log'!C$3:C$500,18,'📝 Daily Log'!I$3:I$500,">0"),"") | F19: =IFERROR(SUMIF('📝 Daily Log'!C$3:C$500,18,'📝 Daily Log'!J$3:J$500),0) -> 0
A20: W19 | B20: =IFERROR(SUMIF('📝 Daily Log'!C$3:C$500,19,'📝 Daily Log'!H$3:H$500),0) -> 0 | C20: =IFERROR(COUNTIFS('📝 Daily Log'!C$3:C$500,19,'📝 Daily Log'!G$3:G$500,"✅ Done"),0) -> 0 | D20: =IFERROR(COUNTIFS('📝 Daily Log'!C$3:C$500,19,'📝 Daily Log'!G$3:G$500,"❌ Missed"),0) -> 0 | E20: =IFERROR(AVERAGEIFS('📝 Daily Log'!I$3:I$500,'📝 Daily Log'!C$3:C$500,19,'📝 Daily Log'!I$3:I$500,">0"),"") | F20: =IFERROR(SUMIF('📝 Daily Log'!C$3:C$500,19,'📝 Daily Log'!J$3:J$500),0) -> 0
A21: W20 | B21: =IFERROR(SUMIF('📝 Daily Log'!C$3:C$500,20,'📝 Daily Log'!H$3:H$500),0) -> 0 | C21: =IFERROR(COUNTIFS('📝 Daily Log'!C$3:C$500,20,'📝 Daily Log'!G$3:G$500,"✅ Done"),0) -> 0 | D21: =IFERROR(COUNTIFS('📝 Daily Log'!C$3:C$500,20,'📝 Daily Log'!G$3:G$500,"❌ Missed"),0) -> 0 | E21: =IFERROR(AVERAGEIFS('📝 Daily Log'!I$3:I$500,'📝 Daily Log'!C$3:C$500,20,'📝 Daily Log'!I$3:I$500,">0"),"") | F21: =IFERROR(SUMIF('📝 Daily Log'!C$3:C$500,20,'📝 Daily Log'!J$3:J$500),0) -> 0
A22: W21 | B22: =IFERROR(SUMIF('📝 Daily Log'!C$3:C$500,21,'📝 Daily Log'!H$3:H$500),0) -> 0 | C22: =IFERROR(COUNTIFS('📝 Daily Log'!C$3:C$500,21,'📝 Daily Log'!G$3:G$500,"✅ Done"),0) -> 0 | D22: =IFERROR(COUNTIFS('📝 Daily Log'!C$3:C$500,21,'📝 Daily Log'!G$3:G$500,"❌ Missed"),0) -> 0 | E22: =IFERROR(AVERAGEIFS('📝 Daily Log'!I$3:I$500,'📝 Daily Log'!C$3:C$500,21,'📝 Daily Log'!I$3:I$500,">0"),"") | F22: =IFERROR(SUMIF('📝 Daily Log'!C$3:C$500,21,'📝 Daily Log'!J$3:J$500),0) -> 0
A23: W22 | B23: =IFERROR(SUMIF('📝 Daily Log'!C$3:C$500,22,'📝 Daily Log'!H$3:H$500),0) -> 0 | C23: =IFERROR(COUNTIFS('📝 Daily Log'!C$3:C$500,22,'📝 Daily Log'!G$3:G$500,"✅ Done"),0) -> 0 | D23: =IFERROR(COUNTIFS('📝 Daily Log'!C$3:C$500,22,'📝 Daily Log'!G$3:G$500,"❌ Missed"),0) -> 0 | E23: =IFERROR(AVERAGEIFS('📝 Daily Log'!I$3:I$500,'📝 Daily Log'!C$3:C$500,22,'📝 Daily Log'!I$3:I$500,">0"),"") | F23: =IFERROR(SUMIF('📝 Daily Log'!C$3:C$500,22,'📝 Daily Log'!J$3:J$500),0) -> 0
A24: W23 | B24: =IFERROR(SUMIF('📝 Daily Log'!C$3:C$500,23,'📝 Daily Log'!H$3:H$500),0) -> 0 | C24: =IFERROR(COUNTIFS('📝 Daily Log'!C$3:C$500,23,'📝 Daily Log'!G$3:G$500,"✅ Done"),0) -> 0 | D24: =IFERROR(COUNTIFS('📝 Daily Log'!C$3:C$500,23,'📝 Daily Log'!G$3:G$500,"❌ Missed"),0) -> 0 | E24: =IFERROR(AVERAGEIFS('📝 Daily Log'!I$3:I$500,'📝 Daily Log'!C$3:C$500,23,'📝 Daily Log'!I$3:I$500,">0"),"") | F24: =IFERROR(SUMIF('📝 Daily Log'!C$3:C$500,23,'📝 Daily Log'!J$3:J$500),0) -> 0
A25: W24 | B25: =IFERROR(SUMIF('📝 Daily Log'!C$3:C$500,24,'📝 Daily Log'!H$3:H$500),0) -> 0 | C25: =IFERROR(COUNTIFS('📝 Daily Log'!C$3:C$500,24,'📝 Daily Log'!G$3:G$500,"✅ Done"),0) -> 0 | D25: =IFERROR(COUNTIFS('📝 Daily Log'!C$3:C$500,24,'📝 Daily Log'!G$3:G$500,"❌ Missed"),0) -> 0 | E25: =IFERROR(AVERAGEIFS('📝 Daily Log'!I$3:I$500,'📝 Daily Log'!C$3:C$500,24,'📝 Daily Log'!I$3:I$500,">0"),"") | F25: =IFERROR(SUMIF('📝 Daily Log'!C$3:C$500,24,'📝 Daily Log'!J$3:J$500),0) -> 0
A26: W25 | B26: =IFERROR(SUMIF('📝 Daily Log'!C$3:C$500,25,'📝 Daily Log'!H$3:H$500),0) -> 0 | C26: =IFERROR(COUNTIFS('📝 Daily Log'!C$3:C$500,25,'📝 Daily Log'!G$3:G$500,"✅ Done"),0) -> 0 | D26: =IFERROR(COUNTIFS('📝 Daily Log'!C$3:C$500,25,'📝 Daily Log'!G$3:G$500,"❌ Missed"),0) -> 0 | E26: =IFERROR(AVERAGEIFS('📝 Daily Log'!I$3:I$500,'📝 Daily Log'!C$3:C$500,25,'📝 Daily Log'!I$3:I$500,">0"),"") | F26: =IFERROR(SUMIF('📝 Daily Log'!C$3:C$500,25,'📝 Daily Log'!J$3:J$500),0) -> 0
A27: W26 | B27: =IFERROR(SUMIF('📝 Daily Log'!C$3:C$500,26,'📝 Daily Log'!H$3:H$500),0) -> 0 | C27: =IFERROR(COUNTIFS('📝 Daily Log'!C$3:C$500,26,'📝 Daily Log'!G$3:G$500,"✅ Done"),0) -> 0 | D27: =IFERROR(COUNTIFS('📝 Daily Log'!C$3:C$500,26,'📝 Daily Log'!G$3:G$500,"❌ Missed"),0) -> 0 | E27: =IFERROR(AVERAGEIFS('📝 Daily Log'!I$3:I$500,'📝 Daily Log'!C$3:C$500,26,'📝 Daily Log'!I$3:I$500,">0"),"") | F27: =IFERROR(SUMIF('📝 Daily Log'!C$3:C$500,26,'📝 Daily Log'!J$3:J$500),0) -> 0
A28: W27 | B28: =IFERROR(SUMIF('📝 Daily Log'!C$3:C$500,27,'📝 Daily Log'!H$3:H$500),0) -> 0 | C28: =IFERROR(COUNTIFS('📝 Daily Log'!C$3:C$500,27,'📝 Daily Log'!G$3:G$500,"✅ Done"),0) -> 0 | D28: =IFERROR(COUNTIFS('📝 Daily Log'!C$3:C$500,27,'📝 Daily Log'!G$3:G$500,"❌ Missed"),0) -> 0 | E28: =IFERROR(AVERAGEIFS('📝 Daily Log'!I$3:I$500,'📝 Daily Log'!C$3:C$500,27,'📝 Daily Log'!I$3:I$500,">0"),"") | F28: =IFERROR(SUMIF('📝 Daily Log'!C$3:C$500,27,'📝 Daily Log'!J$3:J$500),0) -> 0
A29: W28 | B29: =IFERROR(SUMIF('📝 Daily Log'!C$3:C$500,28,'📝 Daily Log'!H$3:H$500),0) -> 0 | C29: =IFERROR(COUNTIFS('📝 Daily Log'!C$3:C$500,28,'📝 Daily Log'!G$3:G$500,"✅ Done"),0) -> 0 | D29: =IFERROR(COUNTIFS('📝 Daily Log'!C$3:C$500,28,'📝 Daily Log'!G$3:G$500,"❌ Missed"),0) -> 0 | E29: =IFERROR(AVERAGEIFS('📝 Daily Log'!I$3:I$500,'📝 Daily Log'!C$3:C$500,28,'📝 Daily Log'!I$3:I$500,">0"),"") | F29: =IFERROR(SUMIF('📝 Daily Log'!C$3:C$500,28,'📝 Daily Log'!J$3:J$500),0) -> 0
A30: W29 | B30: =IFERROR(SUMIF('📝 Daily Log'!C$3:C$500,29,'📝 Daily Log'!H$3:H$500),0) -> 0 | C30: =IFERROR(COUNTIFS('📝 Daily Log'!C$3:C$500,29,'📝 Daily Log'!G$3:G$500,"✅ Done"),0) -> 0 | D30: =IFERROR(COUNTIFS('📝 Daily Log'!C$3:C$500,29,'📝 Daily Log'!G$3:G$500,"❌ Missed"),0) -> 0 | E30: =IFERROR(AVERAGEIFS('📝 Daily Log'!I$3:I$500,'📝 Daily Log'!C$3:C$500,29,'📝 Daily Log'!I$3:I$500,">0"),"") | F30: =IFERROR(SUMIF('📝 Daily Log'!C$3:C$500,29,'📝 Daily Log'!J$3:J$500),0) -> 0
A31: W30 | B31: =IFERROR(SUMIF('📝 Daily Log'!C$3:C$500,30,'📝 Daily Log'!H$3:H$500),0) -> 0 | C31: =IFERROR(COUNTIFS('📝 Daily Log'!C$3:C$500,30,'📝 Daily Log'!G$3:G$500,"✅ Done"),0) -> 0 | D31: =IFERROR(COUNTIFS('📝 Daily Log'!C$3:C$500,30,'📝 Daily Log'!G$3:G$500,"❌ Missed"),0) -> 0 | E31: =IFERROR(AVERAGEIFS('📝 Daily Log'!I$3:I$500,'📝 Daily Log'!C$3:C$500,30,'📝 Daily Log'!I$3:I$500,">0"),"") | F31: =IFERROR(SUMIF('📝 Daily Log'!C$3:C$500,30,'📝 Daily Log'!J$3:J$500),0) -> 0
A32: W31 | B32: =IFERROR(SUMIF('📝 Daily Log'!C$3:C$500,31,'📝 Daily Log'!H$3:H$500),0) -> 0 | C32: =IFERROR(COUNTIFS('📝 Daily Log'!C$3:C$500,31,'📝 Daily Log'!G$3:G$500,"✅ Done"),0) -> 0 | D32: =IFERROR(COUNTIFS('📝 Daily Log'!C$3:C$500,31,'📝 Daily Log'!G$3:G$500,"❌ Missed"),0) -> 0 | E32: =IFERROR(AVERAGEIFS('📝 Daily Log'!I$3:I$500,'📝 Daily Log'!C$3:C$500,31,'📝 Daily Log'!I$3:I$500,">0"),"") | F32: =IFERROR(SUMIF('📝 Daily Log'!C$3:C$500,31,'📝 Daily Log'!J$3:J$500),0) -> 0
A33: W32 | B33: =IFERROR(SUMIF('📝 Daily Log'!C$3:C$500,32,'📝 Daily Log'!H$3:H$500),0) -> 0 | C33: =IFERROR(COUNTIFS('📝 Daily Log'!C$3:C$500,32,'📝 Daily Log'!G$3:G$500,"✅ Done"),0) -> 0 | D33: =IFERROR(COUNTIFS('📝 Daily Log'!C$3:C$500,32,'📝 Daily Log'!G$3:G$500,"❌ Missed"),0) -> 0 | E33: =IFERROR(AVERAGEIFS('📝 Daily Log'!I$3:I$500,'📝 Daily Log'!C$3:C$500,32,'📝 Daily Log'!I$3:I$500,">0"),"") | F33: =IFERROR(SUMIF('📝 Daily Log'!C$3:C$500,32,'📝 Daily Log'!J$3:J$500),0) -> 0
A34: W33 | B34: =IFERROR(SUMIF('📝 Daily Log'!C$3:C$500,33,'📝 Daily Log'!H$3:H$500),0) -> 0 | C34: =IFERROR(COUNTIFS('📝 Daily Log'!C$3:C$500,33,'📝 Daily Log'!G$3:G$500,"✅ Done"),0) -> 0 | D34: =IFERROR(COUNTIFS('📝 Daily Log'!C$3:C$500,33,'📝 Daily Log'!G$3:G$500,"❌ Missed"),0) -> 0 | E34: =IFERROR(AVERAGEIFS('📝 Daily Log'!I$3:I$500,'📝 Daily Log'!C$3:C$500,33,'📝 Daily Log'!I$3:I$500,">0"),"") | F34: =IFERROR(SUMIF('📝 Daily Log'!C$3:C$500,33,'📝 Daily Log'!J$3:J$500),0) -> 0
A35: W34 | B35: =IFERROR(SUMIF('📝 Daily Log'!C$3:C$500,34,'📝 Daily Log'!H$3:H$500),0) -> 0 | C35: =IFERROR(COUNTIFS('📝 Daily Log'!C$3:C$500,34,'📝 Daily Log'!G$3:G$500,"✅ Done"),0) -> 0 | D35: =IFERROR(COUNTIFS('📝 Daily Log'!C$3:C$500,34,'📝 Daily Log'!G$3:G$500,"❌ Missed"),0) -> 0 | E35: =IFERROR(AVERAGEIFS('📝 Daily Log'!I$3:I$500,'📝 Daily Log'!C$3:C$500,34,'📝 Daily Log'!I$3:I$500,">0"),"") | F35: =IFERROR(SUMIF('📝 Daily Log'!C$3:C$500,34,'📝 Daily Log'!J$3:J$500),0) -> 0
A36: W35 | B36: =IFERROR(SUMIF('📝 Daily Log'!C$3:C$500,35,'📝 Daily Log'!H$3:H$500),0) -> 0 | C36: =IFERROR(COUNTIFS('📝 Daily Log'!C$3:C$500,35,'📝 Daily Log'!G$3:G$500,"✅ Done"),0) -> 0 | D36: =IFERROR(COUNTIFS('📝 Daily Log'!C$3:C$500,35,'📝 Daily Log'!G$3:G$500,"❌ Missed"),0) -> 0 | E36: =IFERROR(AVERAGEIFS('📝 Daily Log'!I$3:I$500,'📝 Daily Log'!C$3:C$500,35,'📝 Daily Log'!I$3:I$500,">0"),"") | F36: =IFERROR(SUMIF('📝 Daily Log'!C$3:C$500,35,'📝 Daily Log'!J$3:J$500),0) -> 0
A37: W36 | B37: =IFERROR(SUMIF('📝 Daily Log'!C$3:C$500,36,'📝 Daily Log'!H$3:H$500),0) -> 0 | C37: =IFERROR(COUNTIFS('📝 Daily Log'!C$3:C$500,36,'📝 Daily Log'!G$3:G$500,"✅ Done"),0) -> 0 | D37: =IFERROR(COUNTIFS('📝 Daily Log'!C$3:C$500,36,'📝 Daily Log'!G$3:G$500,"❌ Missed"),0) -> 0 | E37: =IFERROR(AVERAGEIFS('📝 Daily Log'!I$3:I$500,'📝 Daily Log'!C$3:C$500,36,'📝 Daily Log'!I$3:I$500,">0"),"") | F37: =IFERROR(SUMIF('📝 Daily Log'!C$3:C$500,36,'📝 Daily Log'!J$3:J$500),0) -> 0
A38: W37 | B38: =IFERROR(SUMIF('📝 Daily Log'!C$3:C$500,37,'📝 Daily Log'!H$3:H$500),0) -> 0 | C38: =IFERROR(COUNTIFS('📝 Daily Log'!C$3:C$500,37,'📝 Daily Log'!G$3:G$500,"✅ Done"),0) -> 0 | D38: =IFERROR(COUNTIFS('📝 Daily Log'!C$3:C$500,37,'📝 Daily Log'!G$3:G$500,"❌ Missed"),0) -> 0 | E38: =IFERROR(AVERAGEIFS('📝 Daily Log'!I$3:I$500,'📝 Daily Log'!C$3:C$500,37,'📝 Daily Log'!I$3:I$500,">0"),"") | F38: =IFERROR(SUMIF('📝 Daily Log'!C$3:C$500,37,'📝 Daily Log'!J$3:J$500),0) -> 0
A39: W38 | B39: =IFERROR(SUMIF('📝 Daily Log'!C$3:C$500,38,'📝 Daily Log'!H$3:H$500),0) -> 0 | C39: =IFERROR(COUNTIFS('📝 Daily Log'!C$3:C$500,38,'📝 Daily Log'!G$3:G$500,"✅ Done"),0) -> 0 | D39: =IFERROR(COUNTIFS('📝 Daily Log'!C$3:C$500,38,'📝 Daily Log'!G$3:G$500,"❌ Missed"),0) -> 0 | E39: =IFERROR(AVERAGEIFS('📝 Daily Log'!I$3:I$500,'📝 Daily Log'!C$3:C$500,38,'📝 Daily Log'!I$3:I$500,">0"),"") | F39: =IFERROR(SUMIF('📝 Daily Log'!C$3:C$500,38,'📝 Daily Log'!J$3:J$500),0) -> 0
A40: W39 | B40: =IFERROR(SUMIF('📝 Daily Log'!C$3:C$500,39,'📝 Daily Log'!H$3:H$500),0) -> 0 | C40: =IFERROR(COUNTIFS('📝 Daily Log'!C$3:C$500,39,'📝 Daily Log'!G$3:G$500,"✅ Done"),0) -> 0 | D40: =IFERROR(COUNTIFS('📝 Daily Log'!C$3:C$500,39,'📝 Daily Log'!G$3:G$500,"❌ Missed"),0) -> 0 | E40: =IFERROR(AVERAGEIFS('📝 Daily Log'!I$3:I$500,'📝 Daily Log'!C$3:C$500,39,'📝 Daily Log'!I$3:I$500,">0"),"") | F40: =IFERROR(SUMIF('📝 Daily Log'!C$3:C$500,39,'📝 Daily Log'!J$3:J$500),0) -> 0

Sheet 🔗 Resource Links
A1: 🔗 RESOURCE LINKS — All study materials, courses, books, practice platforms per module
A2: [COURSE]=GrowDataSkills purchased course | FREE=no cost | Paid=buy separately | H2: Chapter / Section | I2: Free?
C3: Module | D3: Resource Name | E3: Type | F3: Cost | G3: URL | H3: Ch.1 pp.1-28, Ch.2 pp.29-80 | I3: No
C4: ── M0-Orientation ── | H4: Section: 'Object Oriented Programming' (~1h40m in) | I4: Free
C5: M0-Orientation | D5: Fundamentals of Data Engineering (Joe Reis) | E5: Book | F5: ~$50 | G5: amazon.com/Fundamentals-Data-Engineering | H5: Ch.9 pp.287-340 (Decorators), Ch.17 pp.567-620 (Generators) | I5: No
C6: M0-Orientation | D6: roadmap.sh/data-engineer | E6: Visual roadmap | F6: FREE | G6: roadmap.sh/data-engineer | H6: Full article (30 min read) | I6: Free
C7: M0-Orientation | D7: E-Learning Bridge (Shashank Mishra) — YouTube | E7: YouTube | F7: FREE | G7: youtube.com/@shashank_mishra | H7: Full article (45 min read) | I7: Free
C8: M0-Orientation | D8: neetcode.io — DSA roadmap (start Day 1!) | E8: Daily DSA | F8: FREE | G8: neetcode.io | H8: Ch.16 pp.373-402 (Analytic Functions) | I8: No
C9: ── M1-SQL ── | H9: Lesson: 'Window Functions' sections 1-3 | I9: Free
C10: M1-SQL | D10: GrowDataSkills AWS Module 1 (4 classes) | E10: Course | F10: Purchased ✅ | G10: academy.growdataskills.com | H10: Filter: Amazon + Data Engineer + Hard | I10: Free tier
C11: M1-SQL | D11: Mode Analytics SQL Tutorial (all 3 levels) | E11: Tutorial | F11: FREE | G11: mode.com/sql-tutorial | H11: Ch.13 pp.289-318 (Indexes & Optimization) | I11: No
C12: M1-SQL | D12: StrataScratch — filter Amazon + Flipkart SQL | E12: Practice | F12: Free tier | G12: stratascratch.com | H12: Ch.3 pp.57-98 (Branching), Ch.5 pp.131-166 (Workflows) | I12: Free
C13: M1-SQL | D13: LeetCode SQL problems (#175 → #1158 → #185) | E13: Practice | F13: Free tier | G13: leetcode.com/problemset/database/ | H13: Ch.1 pp.1-30 (Architecture), Ch.3 pp.61-96 (DataFrames) | I13: Free
C14: M1-SQL | D14: HackerRank SQL Advanced Certification | E14: Assessment | F14: FREE | G14: hackerrank.com/domains/sql | H14: Video 1 'Introduction to Apache Spark' (45 min) | I14: Free
C15: ── M2-Python ── | H15: Ch.4 pp.97-134 (Spark SQL), Ch.8 joins section | I15: Free
C16: M2-Python | D16: Fluent Python 2E (Luciano Ramalho) | E16: Book | F16: ~$60 | G16: oreilly.com/library/view/fluent-python-2nd | H16: Video 10 'Spark SQL', Video 12 'Joins in PySpark' | I16: Free
C17: M2-Python | D17: realpython.com — OOP, async, decorators | E17: Articles | F17: FREE | G17: realpython.com | H17: Ch.19 pp.381-430 (Performance Tuning), Ch.18 pp.355-380 (Monitoring) | I17: No
C18: M2-Python | D18: Exercism.io Python track (130 exercises) | E18: Practice | F18: FREE | G18: exercism.io/tracks/python | H18: Search: 'Databricks Spark Performance Tuning' Tech Talk | I18: Free
C19: M2-Python | D19: docs.pydantic.dev v2 | E19: Docs | F19: FREE | G19: docs.pydantic.dev | H19: 'Guides' → 'Delta Lake operations' (OPTIMIZE, VACUUM, MERGE) | I19: Free
C20: M2-Python | D20: docs.pytest.org Getting Started | E20: Docs | F20: FREE | G20: docs.pytest.org | H20: Course: 'Building with Delta Lake' — all modules | I20: Paid
C21: ── M3-BigData ── | H21: Ch.1 pp.1-16 (Concepts), Ch.3 pp.41-62 (Producers), Ch.4 pp.63-94 (Consumers) | I21: Free
C22: M3-BigData | D22: GrowDataSkills AWS Modules 2-3 (5 classes) | E22: Course | F22: Purchased ✅ | G22: academy.growdataskills.com | H22: Lessons 1-7 (Events→Consumer Groups) | I22: Free
C23: M3-BigData | D23: parquet.apache.org — technical spec | E23: Docs | F23: FREE | G23: parquet.apache.org | H23: Ch.6 pp.115-148 (Reliability), Ch.7 pp.149-180 (Pipelines) | I23: Free
C24: M3-BigData | D24: Fundamentals of Data Engineering Ch.6 | E24: Book chapter | F24: Paid | G24: oreilly.com | H24: Ch.8 pp.229-274 (Streaming) | I24: Free
C25: M3-BigData | D25: Hadoop: The Definitive Guide 4E (Tom White) | E25: Book | F25: ~$55 | G25: amazon.com | H25: Ch.5 pp.99-140 (DataStream API), Ch.6 pp.141-172 (Time & Watermarks) | I25: No
C26: ── M4-Kafka ── | H26: Courses: S3(1hr) + Glue(3hr) + Kinesis(2hr) + Redshift(4hr) + EMR(2hr) | I26: Free tier
C27: M4-Kafka | D27: GrowDataSkills AWS Module 3 (2 classes) | E27: Course | F27: Purchased ✅ | G27: academy.growdataskills.com | H27: Video: 'Complete Data Engineering Project on AWS' (1.5 hrs) | I27: Free
C28: M4-Kafka | D28: Kafka: The Definitive Guide 2E | E28: Book | F28: FREE via Confluent | G28: confluent.io/resources/kafka-the-definitive-guide-v2 | H28: Courses: BigQuery(3hr) + Dataflow(6hr) + Pub/Sub streaming(6hr) | I28: Free credits
C29: M4-Kafka | D29: developer.confluent.io — Kafka 101 (18 free lessons) | E29: Video course | F29: FREE | G29: developer.confluent.io/courses/apache-kafka/events/ | H29: Ch.2 pp.25-56 (DAGs), Ch.4 pp.85-120 (Templates/XCom), Ch.5 pp.121-152 (Dependencies) | I29: No
C30: M4-Kafka | D30: Microsoft Learn: Azure Event Hubs | E30: Docs + quickstart | F30: FREE | G30: learn.microsoft.com/azure/event-hubs/ | H30: Search: 'Apache Airflow Tutorial coder2j' — Parts 1-4 | I30: Free
C31: ── M5-NoSQL ── | H31: Course: 'dbt Fundamentals' (5 modules, 5hrs) + 'Advanced dbt' | I31: Free
C32: M5-NoSQL | D32: GrowDataSkills AWS Module 4 (4 classes) | E32: Course | F32: Purchased ✅ | G32: academy.growdataskills.com | H32: Ch.1 pp.3-22 (Reliability/Scalability), Ch.5-6 pp.151-228 (Replication/Partitioning) | I32: No
C33: M5-NoSQL | D33: MongoDB University M001 (Introduction) | E33: Free course | F33: FREE | G33: learn.mongodb.com | H33: Ch.7 pp.221-264 (Transactions), Ch.10-11 pp.389-489 (Batch+Streaming) | I33: No
C34: M5-NoSQL | D34: Cassandra: The Definitive Guide 3E | E34: Book | F34: ~$50 | G34: amazon.com | H34: Videos: 'Consistent Hashing', 'Rate Limiter', 'Design Kafka' (each 15-30 min) | I34: Free
C35: M5-NoSQL | D35: The DynamoDB Book (Alex DeBrie) | E35: Book | F35: ~$49 | G35: dynamodbbook.com | H35: Short visual explainers for each architecture pattern (5-10 min each) | I35: Free
C36: M5-NoSQL | D36: redis.io official documentation | E36: Docs | F36: FREE | G36: redis.io/docs/ | H36: Ch.1 pp.1-42 (Strategy), Ch.2 pp.43-76 (Observer), Ch.4 pp.109-158 (Factory) | I36: No
C37: M5-NoSQL | D37: Microsoft Learn: Cosmos DB | E37: Tutorials + labs | F37: FREE | G37: learn.microsoft.com/azure/cosmos-db/ | H37: Full catalog with Python code — focus on: Strategy, Observer, Factory, Singleton | I37: Free
C38: M5-NoSQL | D38: Elasticsearch: The Definitive Guide (free online) | E38: Book | F38: FREE | G38: elastic.co/guide/ | H38: Ch.2 pp.31-64 (DE Lifecycle), Ch.3 pp.65-98 (Architecture), Ch.6 pp.165-202 (Storage) | I38: No
C39: ── M6-Spark ── | H39: Start §1 (Arrays), progress through §13 (DP) — 190 problems total | I39: Free
C40: M6-Spark | D40: GrowDataSkills AWS Module 5 (5 classes) | E40: Course | F40: Purchased ✅ | G40: academy.growdataskills.com | H40: One video per problem — search '[problem name] neetcode' | I40: Free
C41: M6-Spark | D41: Learning Spark 2E (Jules Damji et al.) | E41: Book | F41: FREE PDF | G41: databricks.com/resources/ebook/learning-spark-lightning-fast-data-analytics | H41: Ch.1 pp.88-107 (Arrays), Ch.4 pp.130-171 (Trees/Graphs), Ch.8 pp.225-271 (DP) | I41: No
